Workbook

Sheet All Districts
A1: District | B1: Code | C1: Incumbent Party | D1: 2022 Winners | G1: 2020 President | I1: 2016 President | K1: 2020 Census Voting Age Population by Race | Q1: 2020 ACS Adult Educational Attainment | S1: Non-College White Share | T1: Party | U1: Candidate Status | V1: Candidate Name | X1: First Elected | Y1: Race / Ethnicity | Z1: LGBTQ | AA1: Party | AB1: Candidate Status | AC1: Candidate Name | AE1: First Elected | AF1: Race / Ethnicity
D2: Name | E2: Party | F2: Outcome | G2: Biden | H2: Trump | I2: Clinton | J2: Trump | K2: White (Non-Hispanic, Single Race) | L2: Hispanic/Latino | M2: Black | N2: Asian | O2: Native | P2: Pacific | Q2: Bachelor's Degree or Higher | R2: White BA (Bachelor's Degree or Higher Among Whites Only) | V2: First | W2: Last | AC2: First | AD2: Last
A3: Nationwide | B3: USA | C3: 222D - 213R | G3: 51.4 | H3: 46.9 | I3: 48.4 | J3: 46.3 | K3: 60.8 | L3: 16.8 | M3: 13.2 | N3: 7 | O3: 2.7 | P3: 0.4 | Q3: 32.9 | R3: 36.5 | S3: 42.9
A4: Alabama's 7th | B4: AL-07 | C4: Democratic | D4: Terri Sewell | E4: Democratic | F4: Hold | G4: 65.6 | H4: 33.6 | I4: 64.1 | J4: 33.5 | K4: 38.6 | L4: 3.7 | M4: 55.3 | N4: 1.5 | O4: 1.3 | P4: 0.1 | Q4: 22.8 | R4: 32.2 | S4: 27.3 | T4: Dem | U4: Incumbent | V4: Terri | W4: Sewell | X4: 2010 | Y4: Black | Z4: No
A5: Arizona's 3rd | B5: AZ-03 | C5: Democratic | D5: Ruben Gallego | E5: Democratic | F5: Hold | G5: 74.5 | H5: 23.9 | I5: 71.4 | J5: 21.5 | K5: 23.8 | L5: 58.2 | M5: 11.9 | N5: 3.8 | O5: 5.1 | P5: 0.5 | Q5: 16.1 | R5: 31.5 | S5: 20.5 | T5: Dem | U5: Incumbent | V5: Ruben | W5: Gallego | X5: 2014 | Y5: Hispanic - Mexican/Colombian | Z5: No
A6: Arizona's 4th | B6: AZ-04 | C6: Democratic | D6: Greg Stanton | E6: Democratic | F6: Hold | G6: 54.2 | H6: 43.9 | I6: 46.5 | J6: 44.1 | K6: 59.4 | L6: 23.1 | M6: 6.6 | N6: 7.3 | O6: 4.3 | P6: 0.6 | Q6: 35.4 | R6: 39.3 | S6: 40.7 | T6: Dem | U6: Incumbent | V6: Greg | W6: Stanton | X6: 2018 | Y6: White | Z6: No
A7: Arizona's 7th | B7: AZ-07 | C7: Democratic | D7: Raúl Grijalva | E7: Democratic | F7: Hold | G7: 65.6 | H7: 32.9 | I7: 63.4 | J7: 29.8 | K7: 32.9 | L7: 55.5 | M7: 4.9 | N7: 3 | O7: 5.8 | P7: 0.4 | Q7: 19.8 | R7: 31.9 | S7: 25.6 | T7: Dem | U7: Incumbent | V7: Raúl | W7: Grijalva | X7: 2002 | Y7: Hispanic - Mexican | Z7: No
A8: California's 2nd | B8: CA-02 | C8: Democratic | D8: Jared Huffman | E8: Democratic | F8: Hold | G8: 73.5 | H8: 24 | I8: 68.9 | J8: 23.4 | K8: 68.4 | L8: 17.9 | M8: 2.6 | N8: 5.9 | O8: 5.4 | P8: 0.6 | Q8: 41.7 | R8: 46.8 | S8: 41.5 | T8: Dem | U8: Incumbent | V8: Jared | W8: Huffman | X8: 2012 | Y8: White | Z8: No
A9: California's 4th | B9: CA-04 | C9: Democratic | D9: Mike Thompson | E9: Democratic | F9: Hold | G9: 67.1 | H9: 30.5 | I9: 63.7 | J9: 29.3 | K9: 55.3 | L9: 27.5 | M9: 4.1 | N9: 10 | O9: 4 | P9: 0.8 | Q9: 34.2 | R9: 40.3 | S9: 38.9 | T9: Dem | U9: Incumbent | V9: Mike | W9: Thompson | X9: 1998 | Y9: White | Z9: No
A10: California's 6th | B10: CA-06 | C10: Democratic | D10: Ami Bera | E10: Democratic | F10: Hold | G10: 57.9 | H10: 39.4 | I10: 54.8 | J10: 38 | K10: 51.1 | L10: 20.3 | M10: 11.1 | N10: 14.7 | O10: 3.8 | P10: 1.5 | Q10: 28.8 | R10: 30.7 | S10: 39.9 | T10: Dem | U10: Incumbent | V10: Ami | W10: Bera | X10: 2012 | Y10: Asian - Indian | Z10: No
A11: California's 7th | B11: CA-07 | C11: Democratic | D11: Doris Matsui | E11: Democratic | F11: Hold | G11: 67.4 | H11: 30.3 | I11: 66.3 | J11: 27.7 | K11: 35 | L11: 24.1 | M11: 12.4 | N11: 26 | O11: 3.5 | P11: 2.4 | Q11: 31.7 | R11: 40.5 | S11: 24.6 | T11: Dem | U11: Incumbent | V11: Doris | W11: Matsui | X11: 2005 Special | Y11: Asian - Japanese | Z11: No
A12: California's 8th | B12: CA-08 | C12: Democratic | D12: John Garamendi | E12: Democratic | F12: Hold | G12: 76 | H12: 22 | I12: 75.3 | J12: 19.4 | K12: 26.9 | L12: 31.5 | M12: 17.7 | N12: 22.4 | O12: 3.6 | P12: 1.6 | Q12: 28.6 | R12: 37.1 | S12: 21.5 | T12: Dem | U12: Incumbent | V12: John | W12: Garamendi | X12: 2009 Special | Y12: White | Z12: No
A13: California's 10th | B13: CA-10 | C13: Democratic | D13: Mark DeSaulnier | E13: Democratic | F13: Hold | G13: 68.6 | H13: 29.3 | I13: 65.1 | J13: 28.9 | K13: 51.3 | L13: 16.7 | M13: 5.8 | N13: 24.5 | O13: 2.3 | P13: 0.9 | Q13: 53.8 | R13: 55.6 | S13: 26.9 | T13: Dem | U13: Incumbent | V13: Mark | W13: DeSaulnier | X13: 2014 | Y13: White | Z13: No
A14: California's 11th | B14: CA-11 | C14: Democratic | D14: Nancy Pelosi | E14: Democratic | F14: Hold | G14: 86.3 | H14: 11.7 | I14: 86 | J14: 8.9 | K14: 44.6 | L14: 13.2 | M14: 6.6 | N14: 34.2 | O14: 1.9 | P14: 0.7 | Q14: 63.4 | R14: 78.3 | S14: 10.8 | T14: Dem | U14: Incumbent | V14: Nancy | W14: Pelosi | X14: 1987 Special | Y14: White | Z14: No
A15: California's 12th | B15: CA-12 | C15: Democratic | D15: Barbara Lee | E15: Democratic | F15: Hold | G15: 89.3 | H15: 8.6 | I15: 87.6 | J15: 6.5 | K15: 35.2 | L15: 21.2 | M15: 18 | N15: 24.6 | O15: 3.1 | P15: 0.9 | Q15: 51.8 | R15: 73.7 | S15: 11 | T15: Dem | U15: Incumbent | V15: Barbara | W15: Lee | X15: 1998 Special | Y15: Black | Z15: No
A16: California's 14th | B16: CA-14 | C16: Democratic | D16: Eric Swalwell | E16: Democratic | F16: Hold | G16: 71.7 | H16: 26.2 | I16: 70.6 | J16: 23.5 | K16: 28.2 | L16: 22.8 | M16: 6.6 | N16: 40.8 | O16: 2.6 | P16: 1.9 | Q16: 44 | R16: 44.5 | S16: 20.8 | T16: Dem | U16: Incumbent | V16: Eric | W16: Swalwell | X16: 2012 | Y16: White | Z16: No
A17: California's 15th | B17: CA-15 | C17: Democratic | D17: Kevin Mullin | E17: Democratic | F17: Hold | G17: 77.7 | H17: 20.4 | I17: 77.3 | J17: 17.9 | K17: 30.2 | L17: 24.6 | M17: 3.7 | N17: 39.6 | O17: 2.2 | P17: 1.8 | Q17: 46.7 | R17: 59.3 | S17: 14.9 | T17: Dem | U17: Open Seat | V17: Kevin | W17: Mullin | Y17: White | Z17: No
A18: California's 16th | B18: CA-16 | C18: Democratic | D18: Anna Eshoo | E18: Democratic | F18: Hold | G18: 75.4 | H18: 22.4 | I18: 74.4 | J18: 19.6 | K18: 46.3 | L18: 17.4 | M18: 2.8 | N18: 32.1 | O18: 2 | P18: 0.7 | Q18: 60.1 | R18: 68.1 | S18: 17.7 | T18: Dem | U18: Incumbent | V18: Anna | W18: Eshoo | X18: 1992 | Y18: White - Armenian | Z18: No
A19: California's 17th | B19: CA-17 | C19: Democratic | D19: Ro Khanna | E19: Democratic | F19: Hold | G19: 72.7 | H19: 25.3 | I19: 74.1 | J19: 20.2 | K19: 22.8 | L19: 15.1 | M19: 2.7 | N19: 58.5 | O19: 1.6 | P19: 0.8 | Q19: 59.8 | R19: 56.5 | S19: 14.1 | T19: Dem | U19: Incumbent | V19: Ro | W19: Khanna | X19: 2016 | Y19: Asian - Indian | Z19: No
A20: California's 18th | B20: CA-18 | C20: Democratic | D20: Zoe Lofgren | E20: Democratic | F20: Hold | G20: 71 | H20: 26.9 | I20: 71.5 | J20: 22.7 | K20: 21.3 | L20: 60.8 | M20: 3 | N20: 14.3 | O20: 4.9 | P20: 0.7 | Q20: 23.1 | R20: 39.5 | S20: 18.3 | T20: Dem | U20: Incumbent | V20: Zoe | W20: Lofgren | X20: 1994 | Y20: White | Z20: No
A21: California's 19th | B21: CA-19 | C21: Democratic | D21: Jimmy Panetta | E21: Democratic | F21: Hold | G21: 68.7 | H21: 29.1 | I21: 66.4 | J21: 27 | K21: 51.7 | L21: 22 | M21: 3.2 | N21: 20.9 | O21: 3.1 | P21: 0.8 | Q21: 45.2 | R21: 50 | S21: 30 | T21: Dem | U21: Incumbent | V21: Jimmy | W21: Panetta | X21: 2016 | Y21: White | Z21: No
A22: California's 24th | B22: CA-24 | C22: Democratic | D22: Salud Carbajal | E22: Democratic | F22: Hold | G22: 63.3 | H22: 34.3 | I22: 59.1 | J22: 34 | K22: 54.2 | L22: 33.9 | M22: 2.6 | N22: 7.3 | O22: 3.8 | P22: 0.5 | Q22: 36.8 | R22: 47.7 | S22: 33.6 | T22: Dem | U22: Incumbent | V22: Salud | W22: Carbajal | X22: 2016 | Y22: Hispanic - Mexican | Z22: No
A23: California's 25th | B23: CA-25 | C23: Democratic | D23: Raul Ruiz | E23: Democratic | F23: Hold | G23: 56.7 | H23: 41.4 | I23: 56.3 | J23: 38.9 | K23: 28.4 | L23: 60.4 | M23: 5.6 | N23: 4.2 | O23: 4.3 | P23: 0.4 | Q23: 15.9 | R23: 24.1 | S23: 26.9 | T23: Dem | U23: Incumbent | V23: Raul | W23: Ruiz | X23: 2012 | Y23: Hispanic - Mexican | Z23: No
A24: California's 26th | B24: CA-26 | C24: Democratic | D24: Julia Brownley | E24: Democratic | F24: Hold | G24: 58.9 | H24: 39 | I24: 55.7 | J24: 38.4 | K24: 46.2 | L24: 39.1 | M24: 2.7 | N24: 10.6 | O24: 3.4 | P24: 0.5 | Q24: 35.4 | R24: 46.3 | S24: 29.6 | T24: Dem | U24: Incumbent | V24: Julia | W24: Brownley | X24: 2012 | Y24: White | Z24: No
A25: California's 28th | B25: CA-28 | C25: Democratic | D25: Judy Chu | E25: Democratic | F25: Hold | G25: 66.1 | H25: 31.9 | I25: 64.4 | J25: 29.9 | K25: 28.9 | L25: 24.7 | M25: 4.8 | N25: 41.4 | O25: 2.3 | P25: 0.4 | Q25: 45.4 | R25: 56 | S25: 15 | T25: Dem | U25: Incumbent | V25: Judy | W25: Chu | X25: 2009 Special | Y25: Asian - Chinese | Z25: No
A26: California's 29th | B26: CA-29 | C26: Democratic | D26: Tony Cárdenas | E26: Democratic | F26: Hold | G26: 74.5 | H26: 23.2 | I26: 77.9 | J26: 16.6 | K26: 23.6 | L26: 61.1 | M26: 5.2 | N26: 9.8 | O26: 3.7 | P26: 0.3 | Q26: 23.2 | R26: 41.1 | S26: 17.2 | T26: Dem | U26: Incumbent | V26: Tony | W26: Cárdenas | X26: 2012 | Y26: Hispanic - Mexican | Z26: No
A27: California's 30th | B27: CA-30 | C27: Democratic | D27: Adam Schiff | E27: Democratic | F27: Hold | G27: 72.2 | H27: 26 | I27: 73.8 | J27: 20.8 | K27: 57.1 | L27: 21.9 | M27: 4.9 | N27: 15.1 | O27: 2.1 | P27: 0.3 | Q27: 48.1 | R27: 52.9 | S27: 28.7 | T27: Dem | U27: Incumbent | V27: Adam | W27: Schiff | X27: 2000 | Y27: White | Z27: No
A28: California's 31st | B28: CA-31 | C28: Democratic | D28: Grace Napolitano | E28: Democratic | F28: Hold | G28: 64.5 | H28: 33.4 | I28: 65.7 | J28: 28.5 | K28: 16.7 | L28: 57.4 | M28: 3.3 | N28: 22.5 | O28: 3.7 | P28: 0.4 | Q28: 23.6 | R28: 33.9 | S28: 13.6 | T28: Dem | U28: Incumbent | V28: Grace | W28: Napolitano | X28: 1998 | Y28: Hispanic - Mexican | Z28: No
A29: California's 32nd | B29: CA-32 | C29: Democratic | D29: Brad Sherman | E29: Democratic | F29: Hold | G29: 69.5 | H29: 28.7 | I29: 70 | J29: 24.9 | K29: 54.8 | L29: 23.5 | M29: 5.6 | N29: 15.1 | O29: 2 | P29: 0.4 | Q29: 50 | R29: 58.4 | S29: 25.4 | T29: Dem | U29: Incumbent | V29: Brad | W29: Sherman | X29: 1996 | Y29: White | Z29: No
A30: California's 33rd | B30: CA-33 | C30: Democratic | D30: Pete Aguilar | E30: Democratic | F30: Hold | G30: 61.5 | H30: 36.2 | I30: 62.2 | J30: 32.3 | K30: 20.1 | L30: 58.7 | M30: 11.9 | N30: 8.9 | O30: 3.9 | P30: 0.6 | Q30: 19.9 | R30: 28.3 | S30: 18.3 | T30: Dem | U30: Incumbent | V30: Pete | W30: Aguilar | X30: 2014 | Y30: Hispanic - Mexican | Z30: No
A31: California's 35th | B31: CA-35 | C31: Democratic | D31: Norma Torres | E31: Democratic | F31: Hold | G31: 62.7 | H31: 35.1 | I31: 64.6 | J31: 30 | K31: 17 | L31: 61.2 | M31: 7.6 | N31: 13.9 | O31: 3.9 | P31: 0.5 | Q31: 20.7 | R31: 27.8 | S31: 16.4 | T31: Dem | U31: Incumbent | V31: Norma | W31: Torres | X31: 2014 | Y31: Hispanic - Guatemalan | Z31: No
A32: California's 36th | B32: CA-36 | C32: Democratic | D32: Ted Lieu | E32: Democratic | F32: Hold | G32: 71 | H32: 26.9 | I32: 69.2 | J32: 24.8 | K32: 57.5 | L32: 15.5 | M32: 4.8 | N32: 20.5 | O32: 1.8 | P32: 0.5 | Q32: 64.1 | R32: 68.1 | S32: 19.9 | T32: Dem | U32: Incumbent | V32: Ted | W32: Lieu | X32: 2014 | Y32: Asian - Taiwanese | Z32: No
A33: California's 38th | B33: CA-38 | C33: Democratic | D33: Linda Sánchez | E33: Democratic | F33: Hold | G33: 64.1 | H33: 33.9 | I33: 65.2 | J33: 29.3 | K33: 15.1 | L33: 58.3 | M33: 2.7 | N33: 23.8 | O33: 3.6 | P33: 0.5 | Q33: 28.6 | R33: 31.7 | S33: 13.4 | T33: Dem | U33: Incumbent | V33: Linda | W33: Sánchez | X33: 2002 | Y33: Hispanic - Mexican | Z33: No
A34: California's 39th | B34: CA-39 | C34: Democratic | D34: Mark Takano | E34: Democratic | F34: Hold | G34: 62 | H34: 35.8 | I34: 61.4 | J34: 32.7 | K34: 22.4 | L34: 58.5 | M34: 10.4 | N34: 7.9 | O34: 3.9 | P34: 0.7 | Q34: 18.3 | R34: 26.3 | S34: 20.7 | T34: Dem | U34: Incumbent | V34: Mark | W34: Takano | X34: 2012 | Y34: Asian - Japanese | Z34: Gay
A35: California's 42nd | B35: CA-42 | C35: Democratic | D35: Robert Garcia | E35: Democratic | F35: Hold | G35: 71.7 | H35: 25.9 | I35: 72.3 | J35: 21.6 | K35: 20.7 | L35: 61.1 | M35: 7.9 | N35: 9.8 | O35: 4 | P35: 0.7 | Q35: 23.9 | R35: 44.2 | S35: 15.4 | T35: Dem | U35: Open Seat | V35: Robert | W35: Garcia | Y35: Hispanic - Peruvian | Z35: Gay
A36: California's 43rd | B36: CA-43 | C36: Democratic | D36: Maxine Waters | E36: Democratic | F36: Hold | G36: 80.8 | H36: 17 | I36: 84.1 | J36: 11.4 | K36: 8 | L36: 54.1 | M36: 27.4 | N36: 10.6 | O36: 3.5 | P36: 0.7 | Q36: 20 | R36: 41.5 | S36: 6 | T36: Dem | U36: Incumbent | V36: Maxine | W36: Waters | X36: 1990 | Y36: Black | Z36: No
A37: California's 44th | B37: CA-44 | C37: Democratic | D37: Nanette Barragán | E37: Democratic | F37: Hold | G37: 72.9 | H37: 24.7 | I37: 75.6 | J37: 19.1 | K37: 14.4 | L37: 57.9 | M37: 12.8 | N37: 14.2 | O37: 3.9 | P37: 1.4 | Q37: 20.9 | R37: 34.1 | S37: 12.2 | T37: Dem | U37: Incumbent | V37: Nanette | W37: Barragán | X37: 2016 | Y37: Hispanic - Mexican | Z37: No
A38: California's 46th | B38: CA-46 | C38: Democratic | D38: Lou Correa | E38: Democratic | F38: Hold | G38: 64.1 | H38: 33.7 | I38: 66.8 | J38: 27.3 | K38: 17.2 | L38: 61.2 | M38: 2.7 | N38: 18.3 | O38: 4.4 | P38: 0.7 | Q38: 21.2 | R38: 33 | S38: 16.9 | T38: Dem | U38: Incumbent | V38: Lou | W38: Correa | X38: 2016 | Y38: Hispanic - Mexican | Z38: No
A39: California's 50th | B39: CA-50 | C39: Democratic | D39: Scott Peters | E39: Democratic | F39: Hold | G39: 65.4 | H39: 32.2 | I39: 60.5 | J39: 33.2 | K39: 57.9 | L39: 19.6 | M39: 4 | N39: 16.8 | O39: 2.1 | P39: 0.7 | Q39: 57.6 | R39: 63.2 | S39: 24.1 | T39: Dem | U39: Incumbent | V39: Scott | W39: Peters | X39: 2012 | Y39: White | Z39: No
A40: California's 51st | B40: CA-51 | C40: Democratic | D40: Sara Jacobs | E40: Democratic | F40: Hold | G40: 62.5 | H40: 35.2 | I40: 58.4 | J40: 35.4 | K40: 48.6 | L40: 22.6 | M40: 7.5 | N40: 19.9 | O40: 2.5 | P40: 1.1 | Q40: 43 | R40: 47.6 | S40: 29 | T40: Dem | U40: Incumbent | V40: Sara | W40: Jacobs | X40: 2020 | Y40: White | Z40: No
A41: California's 52nd | B41: CA-52 | C41: Democratic | D41: Juan Vargas | E41: Democratic | F41: Hold | G41: 67.4 | H41: 30.5 | I41: 70.7 | J41: 24.1 | K41: 15.3 | L41: 57.2 | M41: 9.4 | N41: 18.3 | O41: 3.3 | P41: 1.1 | Q41: 21.6 | R41: 34 | S41: 13.4 | T41: Dem | U41: Incumbent | V41: Juan | W41: Vargas | X41: 2012 | Y41: Hispanic - Mexican | Z41: No
A42: Colorado's 1st | B42: CO-01 | C42: Democratic | D42: Diana DeGette | E42: Democratic | F42: Hold | G42: 79.5 | H42: 18.2 | I42: 73.6 | J42: 18.9 | K42: 58.8 | L42: 24.4 | M42: 9.7 | N42: 5.2 | O42: 3.3 | P42: 0.4 | Q42: 50.4 | R42: 66.1 | S42: 21.8 | T42: Dem | U42: Incumbent | V42: Diana | W42: DeGette | X42: 1996 | Y42: White | Z42: No
A43: Colorado's 2nd | B43: CO-02 | C43: Democratic | D43: Joe Neguse | E43: Democratic | F43: Hold | G43: 68.7 | H43: 28.8 | I43: 60.9 | J43: 30.4 | K43: 78.7 | L43: 12.2 | M43: 1.6 | N43: 4.8 | O43: 2.3 | P43: 0.3 | Q43: 57.1 | R43: 60.7 | S43: 33.5 | T43: Dem | U43: Incumbent | V43: Joe | W43: Neguse | X43: 2018 | Y43: Black - Eritrean | Z43: No
A44: Colorado's 6th | B44: CO-06 | C44: Democratic | D44: Jason Crow | E44: Democratic | F44: Hold | G44: 60.6 | H44: 36.8 | I44: 52.3 | J44: 39.1 | K44: 59.8 | L44: 19.4 | M44: 11.4 | N44: 7.3 | O44: 3 | P44: 0.5 | Q44: 42.2 | R44: 50.4 | S44: 34.7 | T44: Dem | U44: Incumbent | V44: Jason | W44: Crow | X44: 2018 | Y44: White | Z44: No
A45: Colorado's 7th | B45: CO-07 | C45: Democratic | D45: Brittany Pettersen | E45: Democratic | F45: Hold | G45: 55.7 | H45: 41.5 | I45: 47 | J45: 44.1 | K45: 77.4 | L45: 13.3 | M45: 2 | N45: 4.1 | O45: 3.2 | P45: 0.2 | Q45: 43.8 | R45: 47.4 | S45: 43.2 | T45: Dem | U45: Open Seat | V45: Brittany | W45: Pettersen | Y45: White | Z45: No
A46: Colorado's 8th | B46: CO-08 | C46: New | D46: Yadira Caraveo | E46: Democratic | F46: Gain | G46: 50.8 | H46: 46.3 | I46: 44.6 | J46: 46.4 | K46: 56.1 | L46: 34.5 | M46: 2.6 | N46: 4.3 | O46: 4 | P46: 0.3 | Q46: 25.9 | R46: 32.7 | S46: 43.7 | T46: Dem | U46: Open Seat | V46: Yadira | W46: Caraveo | Y46: Hispanic - Mexican | Z46: No
A47: Connecticut's 1st | B47: CT-01 | C47: Democratic | D47: John Larson | E47: Democratic | F47: Hold | G47: 63.3 | H47: 35.2 | I47: 59.4 | J47: 36.2 | K47: 60.9 | L47: 15.5 | M47: 16.9 | N47: 6.2 | O47: 1.5 | P47: 0.1 | Q47: 37.2 | R47: 42.3 | S47: 38.5 | T47: Dem | U47: Incumbent | V47: John | W47: Larson | X47: 1998 | Y47: White | Z47: No
A48: Connecticut's 2nd | B48: CT-02 | C48: Democratic | D48: Joe Courtney | E48: Democratic | F48: Hold | G48: 54.7 | H48: 43.3 | I48: 48.8 | J48: 45.4 | K48: 80.6 | L48: 7.7 | M48: 5.2 | N48: 4.4 | O48: 2.1 | P48: 0.2 | Q48: 37 | R48: 38.4 | S48: 52.6 | T48: Dem | U48: Incumbent | V48: Joe | W48: Courtney | X48: 2006 | Y48: White | Z48: No
A49: Connecticut's 3rd | B49: CT-03 | C49: Democratic | D49: Rosa DeLauro | E49: Democratic | F49: Hold | G49: 59.2 | H49: 39.5 | I49: 55 | J49: 41.1 | K49: 64.7 | L49: 14.3 | M49: 14.9 | N49: 5.3 | O49: 1.5 | P49: 0.1 | Q49: 37.4 | R49: 41.7 | S49: 40.9 | T49: Dem | U49: Incumbent | V49: Rosa | W49: DeLauro | X49: 1990 | Y49: White | Z49: No
A50: Connecticut's 4th | B50: CT-04 | C50: Democratic | D50: Jim Himes | E50: Democratic | F50: Hold | G50: 64.8 | H50: 33.8 | I50: 60.2 | J50: 35.7 | K50: 59.5 | L50: 19.9 | M50: 13.4 | N50: 6.2 | O50: 1.2 | P50: 0.1 | Q50: 52 | R50: 64.1 | S50: 24.4 | T50: Dem | U50: Incumbent | V50: Jim | W50: Himes | X50: 2008 | Y50: White | Z50: No
A51: Connecticut's 5th | B51: CT-05 | C51: Democratic | D51: Jahana Hayes | E51: Democratic | F51: Hold | G51: 54.6 | H51: 43.9 | I51: 49.9 | J51: 45.7 | K51: 67.4 | L51: 18 | M51: 8.8 | N51: 4.2 | O51: 1.5 | P51: 0.1 | Q51: 36.8 | R51: 41.6 | S51: 43.9 | T51: Dem | U51: Incumbent | V51: Jahana | W51: Hayes | X51: 2018 | Y51: Black | Z51: No
A52: Delaware's At-Large | B52: DE-AL | C52: Democratic | D52: Lisa Blunt Rochester | E52: Democratic | F52: Hold | G52: 58.8 | H52: 39.8 | I52: 53.4 | J52: 41.9 | K52: 62.4 | L52: 8.7 | M52: 22.8 | N52: 4.8 | O52: 2 | P52: 0.1 | Q52: 32.7 | R52: 35.2 | S52: 44.5 | T52: Dem | U52: Incumbent | V52: Lisa | W52: Blunt Rochester | X52: 2016 | Y52: Black | Z52: No
A53: Florida's 9th | B53: FL-09 | C53: Democratic | D53: Darren Soto | E53: Democratic | F53: Hold | G53: 58.2 | H53: 40.8 | I53: 61 | J53: 34.7 | K53: 32.3 | L53: 50 | M53: 13 | N53: 5.2 | O53: 1.9 | P53: 0.3 | Q53: 28.8 | R53: 34.7 | S53: 24.5 | T53: Dem | U53: Incumbent | V53: Darren | W53: Soto | X53: 2016 | Y53: Hispanic - Puerto Rican | Z53: No
A54: Florida's 10th | B54: FL-10 | C54: Democratic | D54: Maxwell Alejandro Frost | E54: Democratic | F54: Hold | G54: 65.3 | H54: 33.5 | I54: 63.6 | J54: 31.4 | K54: 38.5 | L54: 28.6 | M54: 26 | N54: 6.1 | O54: 1.7 | P54: 0.3 | Q54: 34 | R54: 47 | S54: 23.6 | T54: Dem | U54: Open Seat | V54: Maxwell Alejandro | W54: Frost | Y54: Multiple: Black/Hispanic - Cuban | Z54: No
A55: Florida's 14th | B55: FL-14 | C55: Democratic | D55: Kathy Castor | E55: Democratic | F55: Hold | G55: 59 | H55: 39.8 | I55: 58.3 | J55: 36.7 | K55: 49.4 | L55: 26 | M55: 19.1 | N55: 5 | O55: 1.6 | P55: 0.2 | Q55: 36.5 | R55: 47.1 | S55: 29 | T55: Dem | U55: Incumbent | V55: Kathy | W55: Castor | X55: 2006 | Y55: White | Z55: No
A56: Florida's 20th | B56: FL-20 | C56: Democratic | D56: Sheila Cherfilus-McCormick | E56: Democratic | F56: Hold | G56: 75.9 | H56: 23.5 | I56: 77.4 | J56: 20.3 | K56: 23.5 | L56: 23 | M56: 50.1 | N56: 3.4 | O56: 1.2 | P56: 0.2 | Q56: 23.4 | R56: 31.5 | S56: 19.1 | T56: Dem | U56: Incumbent | V56: Sheila | W56: Cherfilus-McCormick | X56: 2021 Special | Y56: Black - Hatian | Z56: No
A57: Florida's 22nd | B57: FL-22 | C57: Democratic | D57: Lois Frankel | E57: Democratic | F57: Hold | G57: 58.5 | H57: 40.9 | I57: 58.7 | J57: 38.5 | K57: 55.3 | L57: 24.7 | M57: 15.9 | N57: 3.3 | O57: 1.5 | P57: 0.2 | Q57: 34.7 | R57: 43.4 | S57: 36.1 | T57: Dem | U57: Incumbent | V57: Lois | W57: Frankel | X57: 2012 | Y57: White | Z57: No
A58: Florida's 23rd | B58: FL-23 | C58: Democratic | D58: Jared Moskowitz | E58: Democratic | F58: Hold | G58: 56.3 | H58: 43.1 | I58: 55.7 | J58: 41.5 | K58: 58.4 | L58: 20.5 | M58: 13.2 | N58: 4.4 | O58: 1.1 | P58: 0.2 | Q58: 42.4 | R58: 46.1 | S58: 36.1 | T58: Dem | U58: Vacant | V58: Jared | W58: Moskowitz | Y58: White | Z58: No
A59: Florida's 24th | B59: FL-24 | C59: Democratic | D59: Frederica Wilson | E59: Democratic | F59: Hold | G59: 74.3 | H59: 25.2 | I59: 80.6 | J59: 17.2 | K59: 18.2 | L59: 38.5 | M59: 42.2 | N59: 2.2 | O59: 0.9 | P59: 0.1 | Q59: 27.7 | R59: 51.8 | S59: 8.9 | T59: Dem | U59: Incumbent | V59: Frederica | W59: Wilson | X59: 2010 | Y59: Black | Z59: No
A60: Florida's 25th | B60: FL-25 | C60: Democratic | D60: Debbie Wasserman Schultz | E60: Democratic | F60: Hold | G60: 59.7 | H60: 39.7 | I60: 62.7 | J60: 34.3 | K60: 34.4 | L60: 42.3 | M60: 17.5 | N60: 6 | O60: 1.3 | P60: 0.2 | Q60: 37.4 | R60: 40 | S60: 24.3 | T60: Dem | U60: Incumbent | V60: Debbie | W60: Wasserman Schultz | X60: 2004 | Y60: White | Z60: No
A61: Georgia's 2nd | B61: GA-02 | C61: Democratic | D61: Sanford Bishop | E61: Democratic | F61: Hold | G61: 54.7 | H61: 44.4 | I61: 53.6 | J61: 44.5 | K61: 42.7 | L61: 5.1 | M61: 49.3 | N61: 1.9 | O61: 1.5 | P61: 0.2 | Q61: 19.6 | R61: 25.2 | S61: 33.4 | T61: Dem | U61: Incumbent | V61: Sanford | W61: Bishop | X61: 1992 | Y61: Black | Z61: No
A62: Georgia's 4th | B62: GA-04 | C62: Democratic | D62: Hank Johnson | E62: Democratic | F62: Hold | G62: 78.3 | H62: 20.6 | I62: 74.7 | J62: 22.4 | K62: 28.3 | L62: 10.1 | M62: 54.5 | N62: 6.7 | O62: 1.7 | P62: 0.1 | Q62: 40.5 | R62: 59.1 | S62: 13.4 | T62: Dem | U62: Incumbent | V62: Hank | W62: Johnson | X62: 2006 | Y62: Black | Z62: No
A63: Georgia's 5th | B63: GA-05 | C63: Democratic | D63: Nikema Williams | E63: Democratic | F63: Hold | G63: 82.6 | H63: 16.2 | I63: 80.7 | J63: 15.9 | K63: 37.9 | L63: 6.7 | M63: 49.6 | N63: 5.4 | O63: 1.3 | P63: 0.1 | Q63: 50.3 | R63: 77 | S63: 9.1 | T63: Dem | U63: Incumbent | V63: Nikema | W63: Williams | X63: 2020 | Y63: Black | Z63: No
A64: Georgia's 7th | B64: GA-07 | C64: Democratic | D64: Lucy McBath | E64: Democratic | F64: Hold | G64: 62.3 | H64: 36.5 | I64: 55.1 | J64: 41.1 | K64: 32.8 | L64: 21.3 | M64: 29.8 | N64: 15.9 | O64: 2.1 | P64: 0.2 | Q64: 39.7 | R64: 48.2 | S64: 22.6 | T64: Dem | U64: Incumbent | V64: Lucy | W64: McBath | X64: 2018 | Y64: Black | Z64: No
A65: Georgia's 13th | B65: GA-13 | C65: Democratic | D65: David Scott | E65: Democratic | F65: Hold | G65: 79.7 | H65: 19.3 | I65: 76.2 | J65: 21.6 | K65: 18.8 | L65: 10.5 | M65: 66.7 | N65: 3.8 | O65: 1.7 | P65: 0.1 | Q65: 28.6 | R65: 28.2 | S65: 16.7 | T65: Dem | U65: Incumbent | V65: David | W65: Scott | X65: 2002 | Y65: Black | Z65: No
A66: Hawaii's 1st | B66: HI-01 | C66: Democratic | D66: Ed Case | E66: Democratic | F66: Hold | G66: 63.9 | H66: 34.5 | I66: 63.1 | J66: 30.5 | K66: 16.1 | L66: 6.6 | M66: 3.1 | N66: 68.1 | O66: 1.9 | P66: 17.9 | Q66: 36.9 | R66: 51.4 | S66: 8.6 | T66: Dem | U66: Incumbent | V66: Ed | W66: Case | X66: 2018, 2002-2006 | Y66: White | Z66: No
A67: Hawaii's 2nd | B67: HI-02 | C67: Democratic | D67: Jill Tokuda | E67: Democratic | F67: Hold | G67: 63.6 | H67: 34.1 | I67: 61.4 | J67: 29.6 | K67: 31.8 | L67: 9.5 | M67: 2.4 | N67: 43.4 | O67: 3 | P67: 28 | Q67: 30.1 | R67: 43.3 | S67: 18.8 | T67: Dem | U67: Open Seat | V67: Jill | W67: Tokuda | Y67: Asian - Japanese | Z67: No
A68: Illinois' 1st | B68: IL-01 | C68: Democratic | D68: Jonathan Jackson | E68: Democratic | F68: Hold | G68: 70.5 | H68: 28.1 | I68: 71.9 | J68: 24 | K68: 37 | L68: 7.9 | M68: 52 | N68: 2.6 | O68: 1.4 | P68: 0.1 | Q68: 30.3 | R68: 37.2 | S68: 24.7 | T68: Dem | U68: Open Seat | V68: Jonathan | W68: Jackson | Y68: Black | Z68: No
A69: Illinois' 2nd | B69: IL-02 | C69: Democratic | D69: Robin Kelly | E69: Democratic | F69: Hold | G69: 69.3 | H69: 29.3 | I69: 69.1 | J69: 26.8 | K69: 36.3 | L69: 13.4 | M69: 48.4 | N69: 1.3 | O69: 1.8 | P69: 0.1 | Q69: 23 | R69: 22.6 | S69: 31.4 | T69: Dem | U69: Incumbent | V69: Robin | W69: Kelly | X69: 2013 Special | Y69: Black | Z69: No
A70: Illinois' 3rd | B70: IL-03 | C70: Democratic | D70: Delia Ramirez | E70: Democratic | F70: Hold | G70: 69.7 | H70: 28.3 | I70: 69.1 | J70: 24.6 | K70: 42.8 | L70: 43.8 | M70: 6 | N70: 7.3 | O70: 3.5 | P70: 0.2 | Q70: 33.8 | R70: 47.8 | S70: 26.8 | T70: Dem | U70: Open Seat | V70: Delia | W70: Ramirez | Y70: Hispanic - Guatemalan | Z70: No
A71: Illinois' 4th | B71: IL-04 | C71: Democratic | D71: Jesús "Chuy" García | E71: Democratic | F71: Hold | G71: 72.3 | H71: 25.9 | I71: 72.4 | J71: 21.7 | K71: 26.2 | L71: 63.2 | M71: 5.8 | N71: 4.7 | O71: 4.8 | P71: 0.1 | Q71: 22.2 | R71: 40.7 | S71: 20.9 | T71: Dem | U71: Incumbent | V71: Jesús "Chuy" | W71: García | X71: 2018 | Y71: Hispanic - Mexican | Z71: No
A72: Illinois' 5th | B72: IL-05 | C72: Democratic | D72: Mike Quigley | E72: Democratic | F72: Hold | G72: 68.9 | H72: 29.3 | I72: 65.5 | J72: 27.3 | K72: 73.3 | L72: 10.7 | M72: 3.3 | N72: 11.8 | O72: 1.2 | P72: 0.1 | Q72: 62.9 | R72: 65.8 | S72: 26.9 | T72: Dem | U72: Incumbent | V72: Mike | W72: Quigley | X72: 2008 | Y72: White | Z72: No
A73: Illinois' 6th | B73: IL-06 | C73: Democratic | D73: Sean Casten | E73: Democratic | F73: Hold | G73: 54.5 | H73: 43.6 | I73: 50.7 | J73: 42.4 | K73: 74.6 | L73: 11.8 | M73: 5.9 | N73: 6.5 | O73: 1.3 | P73: 0.1 | Q73: 42.8 | R73: 43.3 | S73: 44.7 | T73: Dem | U73: Incumbent | V73: Sean | W73: Casten | X73: 2018 | Y73: White | Z73: No
A74: Illinois' 7th | B74: IL-07 | C74: Democratic | D74: Danny Davis | E74: Democratic | F74: Hold | G74: 85.6 | H74: 12.8 | I74: 85.8 | J74: 9.8 | K74: 32.7 | L74: 13.8 | M74: 43 | N74: 10.2 | O74: 1.5 | P74: 0.1 | Q74: 45 | R74: 75.6 | S74: 8.7 | T74: Dem | U74: Incumbent | V74: Danny | W74: Davis | X74: 1996 | Y74: Black | Z74: No
A75: Illinois' 8th | B75: IL-08 | C75: Democratic | D75: Raja Krishnamoorthi | E75: Democratic | F75: Hold | G75: 56.8 | H75: 41.4 | I75: 54.6 | J75: 38.9 | K75: 58.4 | L75: 20.7 | M75: 4.8 | N75: 15.2 | O75: 2.1 | P75: 0.1 | Q75: 37.5 | R75: 39 | S75: 41.4 | T75: Dem | U75: Incumbent | V75: Raja | W75: Krishnamoorthi | X75: 2016 | Y75: Asian - Indian | Z75: No
A76: Illinois' 9th | B76: IL-09 | C76: Democratic | D76: Jan Schakowsky | E76: Democratic | F76: Hold | G76: 69.9 | H76: 28.4 | I76: 68.2 | J76: 25.8 | K76: 61.6 | L76: 11.7 | M76: 9.7 | N76: 16 | O76: 1.5 | P76: 0.1 | Q76: 53.8 | R76: 59.1 | S76: 28.5 | T76: Dem | U76: Incumbent | V76: Jan | W76: Schakowsky | X76: 1998 | Y76: White | Z76: No
A77: Illinois' 10th | B77: IL-10 | C77: Democratic | D77: Brad Schneider | E77: Democratic | F77: Hold | G77: 62 | H77: 36.1 | I77: 57.7 | J77: 34.9 | K77: 61.6 | L77: 21.2 | M77: 7.1 | N77: 8.7 | O77: 2.2 | P77: 0.2 | Q77: 45.4 | R77: 52.7 | S77: 33.9 | T77: Dem | U77: Incumbent | V77: Brad | W77: Schneider | X77: 2016 | Y77: White | Z77: No
A78: Illinois' 11th | B78: IL-11 | C78: Democratic | D78: Bill Foster | E78: Democratic | F78: Hold | G78: 56.6 | H78: 41.3 | I78: 51.7 | J78: 41.1 | K78: 66.6 | L78: 16.4 | M78: 6.6 | N78: 9 | O78: 1.8 | P78: 0.1 | Q78: 43.5 | R78: 46.8 | S78: 39.5 | T78: Dem | U78: Incumbent | V78: Bill | W78: Foster | X78: 2012, 2008 Special-2010 | Y78: White | Z78: No
A79: Illinois' 13th | B79: IL-13 | C79: Republican | D79: Nikki Budzinski | E79: Democratic | F79: Gain | G79: 54.4 | H79: 43.2 | I79: 50.6 | J79: 42.3 | K79: 67.8 | L79: 4.3 | M79: 20.3 | N79: 5.4 | O79: 2.1 | P79: 0.1 | Q79: 30 | R79: 31.9 | S79: 50.6 | T79: Dem | U79: Open Seat | V79: Nikki | W79: Budzinski | Y79: White | Z79: No
A80: Illinois' 14th | B80: IL-14 | C80: Democratic | D80: Lauren Underwood | E80: Democratic | F80: Hold | G80: 54.7 | H80: 43.3 | I80: 50.7 | J80: 42.1 | K80: 62.7 | L80: 20.1 | M80: 10.2 | N80: 5.7 | O80: 2.2 | P80: 0.1 | Q80: 31.5 | R80: 34.8 | S80: 45.5 | T80: Dem | U80: Incumbent | V80: Lauren | W80: Underwood | X80: 2018 | Y80: Black | Z80: No
A81: Illinois' 17th | B81: IL-17 | C81: Democratic | D81: Eric Sorensen | E81: Democratic | F81: Hold | G81: 52.7 | H81: 44.9 | I81: 49.6 | J81: 42.9 | K81: 72 | L81: 9.4 | M81: 14.2 | N81: 2.6 | O81: 2 | P81: 0.1 | Q81: 23.6 | R81: 25.7 | S81: 58.3 | T81: Dem | U81: Open Seat | V81: Eric | W81: Sorensen | Y81: White | Z81: Gay
A82: Indiana's 1st | B82: IN-01 | C82: Democratic | D82: Frank Mrvan | E82: Democratic | F82: Hold | G82: 53.4 | H82: 45 | I82: 53 | J82: 41.2 | K82: 63.2 | L82: 14.3 | M82: 18.9 | N82: 1.8 | O82: 2.1 | P82: 0.1 | Q82: 24 | R82: 27 | S82: 49.4 | T82: Dem | U82: Incumbent | V82: Frank | W82: Mrvan | X82: 2020 | Y82: White | Z82: No
A83: Indiana's 7th | B83: IN-07 | C83: Democratic | D83: André Carson | E83: Democratic | F83: Hold | G83: 70.3 | H83: 27.9 | I83: 64.7 | J83: 29 | K83: 50.4 | L83: 12.2 | M83: 33.4 | N83: 2.7 | O83: 2 | P83: 0.1 | Q83: 33.1 | R83: 42.8 | S83: 33.3 | T83: Dem | U83: Incumbent | V83: André | W83: Carson | X83: 2008 Special | Y83: Black | Z83: No
A84: Kansas' 3rd | B84: KS-03 | C84: Democratic | D84: Sharice Davids | E84: Democratic | F84: Hold | G84: 51.2 | H84: 46.7 | I84: 42.9 | J84: 48.2 | K84: 77.9 | L84: 8.5 | M84: 5.4 | N84: 5.4 | O84: 2.5 | P84: 0.1 | Q84: 50.6 | R84: 52.6 | S84: 40.5 | T84: Dem | U84: Incumbent | V84: Sharice | W84: Davids | X84: 2018 | Y84: Native American - Ho-Chunk | Z84: Lesbian
A85: Kentucky's 3rd | B85: KY-03 | C85: Democratic | D85: Morgan McGarvey | E85: Democratic | F85: Hold | G85: 60.2 | H85: 37.9 | I85: 55.1 | J85: 39.7 | K85: 65.6 | L85: 6.9 | M85: 22 | N85: 3.7 | O85: 1.9 | P85: 0.2 | Q85: 32.8 | R85: 36.9 | S85: 45.9 | T85: Dem | U85: Open Seat | V85: Morgan | W85: McGarvey | Y85: White | Z85: No
A86: Louisiana's 2nd | B86: LA-02 | C86: Democratic | D86: Troy Carter | E86: Democratic | F86: Hold | G86: 75.4 | H86: 22.9 | I86: 74.6 | J86: 22.2 | K86: 29.8 | L86: 7.8 | M86: 58.6 | N86: 3.3 | O86: 1.5 | P86: 0.1 | Q86: 24.8 | R86: 37.9 | S86: 19.5 | T86: Dem | U86: Incumbent | V86: Troy | W86: Carter | X86: 2021 Special | Y86: Black | Z86: No
A87: Maine's 1st | B87: ME-01 | C87: Democratic | D87: Chellie Pingree | E87: Democratic | F87: Hold | G87: 60 | H87: 37.2 | I87: 53.8 | J87: 39.4 | K87: 91 | L87: 1.8 | M87: 2.3 | N87: 2.1 | O87: 1.8 | P87: 0.1 | Q87: 39.2 | R87: 39.5 | S87: 57.3 | T87: Dem | U87: Incumbent | V87: Chellie | W87: Pingree | X87: 2008 | Y87: White | Z87: No
A88: Maryland's 2nd | B88: MD-02 | C88: Democratic | D88: Dutch Ruppersberger | E88: Democratic | F88: Hold | G88: 59.4 | H88: 38.6 | I88: 52.3 | J88: 41.2 | K88: 62.4 | L88: 5.1 | M88: 24.3 | N88: 6.9 | O88: 1.6 | P88: 0.1 | Q88: 30.8 | R88: 32.2 | S88: 46.9 | T88: Dem | U88: Incumbent | V88: Dutch | W88: Ruppersberger | X88: 2002 | Y88: White | Z88: No
A89: Maryland's 3rd | B89: MD-03 | C89: Democratic | D89: John Sarbanes | E89: Democratic | F89: Hold | G89: 61.7 | H89: 36.2 | I89: 53.2 | J89: 39.5 | K89: 60.6 | L89: 7.6 | M89: 18.4 | N89: 11.9 | O89: 1.8 | P89: 0.2 | Q89: 53.4 | R89: 56.3 | S89: 29.9 | T89: Dem | U89: Incumbent | V89: John | W89: Sarbanes | X89: 2006 | Y89: White | Z89: No
A90: Maryland's 4th | B90: MD-04 | C90: Democratic | D90: Glenn Ivey | E90: Democratic | F90: Hold | G90: 89.6 | H90: 8.7 | I90: 89.2 | J90: 7.4 | K90: 12.3 | L90: 22 | M90: 59.8 | N90: 6.4 | O90: 2.5 | P90: 0.2 | Q90: 36 | R90: 54.9 | S90: 7 | T90: Dem | U90: Open Seat | V90: Glenn | W90: Ivey | Y90: Black | Z90: No
A91: Maryland's 5th | B91: MD-05 | C91: Democratic | D91: Steny Hoyer | E91: Democratic | F91: Hold | G91: 67.4 | H91: 30.9 | I91: 59.2 | J91: 35.3 | K91: 45.7 | L91: 6 | M91: 43 | N91: 4.2 | O91: 2.2 | P91: 0.2 | Q91: 35.8 | R91: 37.5 | S91: 31.7 | T91: Dem | U91: Incumbent | V91: Steny | W91: Hoyer | X91: 1981 Special | Y91: White | Z91: No
A92: Maryland's 6th | B92: MD-06 | C92: Democratic | D92: David Trone | E92: Democratic | F92: Hold | G92: 53.9 | H92: 44.1 | I92: 47.4 | J92: 46.2 | K92: 63.6 | L92: 11.6 | M92: 13.9 | N92: 9.4 | O92: 2 | P92: 0.2 | Q92: 44.3 | R92: 44 | S92: 40.3 | T92: Dem | U92: Incumbent | V92: David | W92: Trone | X92: 2018 | Y92: White | Z92: No
A93: Maryland's 7th | B93: MD-07 | C93: Democratic | D93: Kweisi Mfume | E93: Democratic | F93: Hold | G93: 81 | H93: 17.5 | I93: 77.7 | J93: 17.6 | K93: 32.5 | L93: 7.2 | M93: 54.7 | N93: 4.8 | O93: 1.8 | P93: 0.1 | Q93: 38.3 | R93: 54.7 | S93: 16.1 | T93: Dem | U93: Incumbent | V93: Kweisi | W93: Mfume | X93: 2020 Special, 1986-1996 | Y93: Black | Z93: No
A94: Maryland's 8th | B94: MD-08 | C94: Democratic | D94: Jamie Raskin | E94: Democratic | F94: Hold | G94: 80.5 | H94: 17.9 | I94: 75.7 | J94: 18.4 | K94: 46.9 | L94: 17.9 | M94: 18.2 | N94: 16 | O94: 1.7 | P94: 0.2 | Q94: 53.3 | R94: 57.5 | S94: 24 | T94: Dem | U94: Incumbent | V94: Jamie | W94: Raskin | X94: 2016 | Y94: White | Z94: No
A95: Massachusetts' 1st | B95: MA-01 | C95: Democratic | D95: Richard "Richie" Neal | E95: Democratic | F95: Hold | G95: 59.8 | H95: 38.2 | I95: 54.9 | J95: 37.4 | K95: 73.2 | L95: 15.8 | M95: 7.3 | N95: 2.7 | O95: 1.8 | P95: 0.2 | Q95: 30.1 | R95: 33.2 | S95: 51.6 | T95: Dem | U95: Incumbent | V95: Richard "Richie" | W95: Neal | X95: 1988 | Y95: White | Z95: No
A96: Massachusetts' 2nd | B96: MA-02 | C96: Democratic | D96: Jim McGovern | E96: Democratic | F96: Hold | G96: 64.3 | H96: 33.5 | I96: 57.5 | J96: 33.9 | K96: 73.9 | L96: 9.6 | M96: 6.5 | N96: 7.8 | O96: 1.4 | P96: 0.1 | Q96: 44 | R96: 45.1 | S96: 45.2 | T96: Dem | U96: Incumbent | V96: Jim | W96: McGovern | X96: 1996 | Y96: White | Z96: No
A97: Massachusetts' 3rd | B97: MA-03 | C97: Democratic | D97: Lori Trahan | E97: Democratic | F97: Hold | G97: 62.7 | H97: 35.3 | I97: 56.7 | J97: 35.4 | K97: 64.3 | L97: 19.5 | M97: 6.3 | N97: 8.5 | O97: 1.4 | P97: 0.2 | Q97: 37.3 | R97: 41.7 | S97: 43.4 | T97: Dem | U97: Incumbent | V97: Lori | W97: Trahan | X97: 2018 | Y97: White - Portuguese | Z97: No
A98: Massachusetts' 4th | B98: MA-04 | C98: Democratic | D98: Jake Auchincloss | E98: Democratic | F98: Hold | G98: 63.3 | H98: 34.8 | I98: 57.6 | J98: 35 | K98: 80.6 | L98: 5.1 | M98: 4.6 | N98: 7.1 | O98: 1 | P98: 0.1 | Q98: 47.8 | R98: 47.6 | S98: 45.7 | T98: Dem | U98: Incumbent | V98: Jake | W98: Auchincloss | X98: 2020 | Y98: White | Z98: No
A99: Massachusetts' 5th | B99: MA-05 | C99: Democratic | D99: Katherine Clark | E99: Democratic | F99: Hold | G99: 74.8 | H99: 23.6 | I99: 68.6 | J99: 24.9 | K99: 66.9 | L99: 9.4 | M99: 6.3 | N99: 13.8 | O99: 0.9 | P99: 0.1 | Q99: 59.1 | R99: 61.2 | S99: 30.5 | T99: Dem | U99: Incumbent | V99: Katherine | W99: Clark | X99: 2013 Special | Y99: White | Z99: No
A100: Massachusetts' 6th | B100: MA-06 | C100: Democratic | D100: Seth Moulton | E100: Democratic | F100: Hold | G100: 62.9 | H100: 35.3 | I100: 55.4 | J100: 37.3 | K100: 79.6 | L100: 9.2 | M100: 4.4 | N100: 5.3 | O100: 1.1 | P100: 0.1 | Q100: 47.5 | R100: 49.7 | S100: 43.4 | T100: Dem | U100: Incumbent | V100: Seth | W100: Moulton | X100: 2014 | Y100: White | Z100: No
...

Sheet 119th House
A1: Grade (based on USCPR metric) | B1: Rank | C1: First Name | D1: Last Name | E1: CD | F1: Sponsor Score (1/3 of Total Palestine Score) | G1: Total Voting Score (2/3 of Total Palestine Score) | H1: Total Palestine Score ("Present" vote = half of "Yes") | I1: 2026 endorsements | J1: Calling for humanitarian aid for Gaza | K1: UNRWA Funding Emergency Restoration Act | L1: Block the Bombs Act | M1: Recognizing the genocide of the Palestinian people in Gaza | N1: Recognizing the Nakba and Palestinian Refugees’ Rights | O1: United States-Israel Defense Partnership Act | P1: 2027 NDAA that links the US and Israeli military | Q1: State Dept appropriations: $3.3B in military aid for Israel; blocks aid to Palestinian Authority or to support a Palestinian state | R1: Eliminate $3.3 billion in military aid to Israel (Massie amendment) | S1: Final appropriations bill with $3.3B for Israel, $500M for Iron Dome, total ban on UNRWA ICC/ICJ funding, etc. | T1: Appropriations bill increasing funding for military; $3.3B for Israel; defunds USAID and UNRWA | U1: 2026 NDAA with $500 million for U.S.-Israel missile defense cooperation (conference) | V1: [HFAC AMENDMENT] Condition aid to Israel on cooperating with investigations into deaths of U.S. citizens | W1: [HFAC AMENDMENT] Condition aid to Israel on ending war crimes and following international law | X1: Cut $500M for Israeli missile defense programs | Y1: Resolution condemning the Boulder attack that conflates antisemitic violence and anti-Zionism | Z1: Sanction the ICC for Netanyahu warrant | AA1: 2024 NDAA (conference, with Israel funding, anti-Gaza provisions) | AB1: Allow Trump administration to revoke non-profit tax status from pro-Palestine orgs (revote) | AC1: Antisemitism resolution mentioning IHRA definition | AD1: Allow Trump administration to revoke non-profit tax status from pro-Palestine orgs | AE1: Anti-BDS product labeling legislation that rejects the State of Palestine's existence | AF1: Ban State Department from citing Palestinian death tolls from the Gaza Health Ministry | AG1: Sanction the ICC for Netanyahu warrant | AH1: Ban any withholding or reversal of weapons to Israel | AI1: Codify IHRA definition of antisemitism ("anti-zionism is antisemitism") | AJ1: $14 billion in weapons to Israel | AK1: Rules package for Israel/Ukraine/Taiwain aid + Russian/Iran sanctions + TikTok ban | AL1: Resolution standing with Israel against Iran + promising more military aid | AM1: Condemn "from the river to the sea" as antisemitic | AN1: Expanded sanctions on alleged Palestinian use of "human shields" | AO1: Allow Secretary of Treasury to unilaterally designate and terminate tax-exempt status of "terrorist supporting organizations" (targeting pro-Palestine groups) | AP1: Spending bill that cuts UNRWA funding | AQ1: One-sided resolution only condemning Hamas for alleged sexual violence | AR1: $17.6 billion to Israel | AS1: Ban PLO members from entering the U.S. | AT1: Condemning testimony of Harvard, UPenn, MIT's presidents | AU1: Require other countries to disclose "any affiliation" to "terrorist" groups (targeting Palestine) | AV1: IHRA definition of antisemitism + "anti-zionism is antisemitism" | AW1: Declaring that only Hamas's unconditional surrender can save civilian lives | AX1: Affirming Israel's right to exist + denying that right is antisemitism | AY1: Ban funds for colleges with events that violate the pro-Israel IHRA definition of antisemitism | AZ1: Resolution condemning Tlaib saying "from the river to the sea" | BA1: Condemning pro-Palestine college students | BB1: Cut IRS budget for $14 billion in unconditional Israel aid | BC1: Sanction alleged financial backers of Palestinian militant groups | BD1: Meeks/McCaul anti-Palestinian resolution | BE1: Prohibit moving Jerusalem embassy | BF1: Pro-Israel resolution declaring it not a racist or apartheid nation | BG1: Strengthen Abraham Accords with "Special Envoy" position | BH1: Support Abraham Accords | BI1: 2023 NDAA with funding for Israel (conference) | BJ1: Defense spending (with $4.8 billion in weapons to Israel) | BK1: Iron Dome funding | BL1: Unconditional aid to Israel | BM1: Supporting 2016 MOU with Israel | BN1: Anti-BDS resolution | BO1: Pro-Israel resolution criticizing UN's position | BP1: Anti-Palestinian state | BQ1: Letter to ICC complaining about arrest warrant for Netanyahu | BR1: Statement condeming Tlaib saying "from the river to the sea" | BS1: Bipartisan anti-de- escalation letter | BU1: Total Pro-Israel $$$ (negative amount = spending against incumbent) | BV1: AIPAC contributions (direct + bundled from other donors) | BW1: AIPAC's "United Democracy Project" IE spending (for candidate + against opponent) | BX1: DMFI Contributions | BY1: DMFI IE Spending (for candidate + against opponent) | BZ1: JVP- endorsed (2022) | CA1: J Street- endorsed (2022) | CB1: DMFI- endorsed (2022) | CC1: AIPAC- endorsed (2022)
C2: Created and updated by a group of anti-Zionist DSA comrades. | J2: Resolution | K2: Bill | L2: Bill | M2: Resolution | N2: Resolution | O2: Bill | P2: NDAA | Q2: NDAA | R2: Amendment | S2: Bill | T2: Bill | U2: NDAA | V2: Committee vote | W2: Committee vote | X2: Amendment | Y2: Resolution | Z2: Bill | AA2: NDAA | AB2: Bill | AC2: Resolution | AD2: Bill | AE2: Bill | AF2: Bill | AG2: Bill | AH2: Bill | AI2: Bill | AJ2: Bill | AK2: Bill | AL2: Resolution | AM2: Resolution | AN2: Bill | AO2: Bill | AP2: Bill | AQ2: Resolution | AR2: Bill | AS2: Bill | AT2: Resolution | AU2: Bill | AV2: Resolution | AW2: Amendment | AX2: Resolution | AY2: Bill | AZ2: Resolution | BA2: Resolution | BB2: Bill | BC2: Bill | BD2: Resolution | BE2: Bill | BF2: Resolution | BG2: Bill | BH2: Resolution | BI2: NDAA | BJ2: Bill | BK2: Resolution | BL2: Bill | BM2: Resolution | BN2: Resolution | BO2: Resolution | BP2: Resolution
J3: 2025-2027 | K3: 2025-2027 | L3: 2025-2027 | M3: 2025-2027 | N3: 2026-2027 | O3: 2025-2027 | P3: 46225 | Q3: 46218 | R3: 46218 | S3: 46056 | T3: 46036 | U3: 46001 | V3: 45918 | W3: 45918 | X3: 45856 | Y3: 45817 | Z3: 45666 | AA3: 45637 | AB3: 45617 | AC3: 45616 | AD3: 45608 | AE3: 45553 | AF3: 45470 | AG3: 45447 | AH3: 45428 | AI3: 45413 | AJ3: 45402 | AK3: 45401 | AL3: 45399 | AM3: 45398 | AN3: 45398 | AO3: 45397 | AP3: 45373 | AQ3: 45336 | AR3: 45328 | AS3: 45322 | AT3: 45273 | AU3: 45266 | AV3: 45265 | AW3: 45260 | AX3: 45258 | AY3: 45245 | AZ3: 45237 | BA3: 45232 | BB3: 45232 | BC3: 45231 | BD3: 45224 | BE3: 45197 | BF3: 45125 | BG3: 45090 | BH3: 45041 | BI3: 44903 | BJ3: 44629 | BK3: 44462 | BL3: 44405 | BM3: 43805 | BN3: 43669 | BO3: 42740 | BP3: 40731 | BQ3: 45666 | BR3: 45237 | BS3: 45215
H4: % Correct: | J4: =COUNTIF(J5:J243, "Sponsor")/((COUNTIF(J5:J243, "Sponsor")+(COUNTIF(J5:J243, "Not sponsoring")))) -> 0.58490566 | K4: =COUNTIF(K5:K243, "Sponsor")/((COUNTIF(K5:K243, "Sponsor")+(COUNTIF(K5:K243, "Not sponsoring")))) -> 0.36792453 | L4: =COUNTIF(L5:L243, "Sponsor")/((COUNTIF(L5:L243, "Sponsor")+(COUNTIF(L5:L243, "Not sponsoring")))) -> 0.37735849 | M4: =COUNTIF(M5:M243, "Sponsor")/((COUNTIF(M5:M243, "Sponsor")+(COUNTIF(M5:M243, "Not sponsoring")))) -> 0.10377358 | N4: =COUNTIF(N5:N243, "Sponsor")/((COUNTIF(N5:N243, "Sponsor")+(COUNTIF(N5:N243, "Not sponsoring")))) -> 0.066037736 | O4: =COUNTIF(O5:O243, "Not sponsoring (correct)")/((COUNTIF(O5:O243, "Sponsor (incorrect)")+(COUNTIF(O5:O243, "Not sponsoring (correct)")))) -> 0.58962264 | P4: =(COUNTIF(P5:P9080, "No")+COUNTIF(P5:P9080, "Yes (correct)"))/(COUNTIF(P5:P9080, "Yes")+COUNTIF(P5:P9080, "No")+COUNTIF(P5:P9080, "Yes (correct)")+COUNTIF(P5:P9080, "No (incorrect)")) -> 0.97156398 | Q4: =(COUNTIF(Q5:Q9080, "No")+COUNTIF(Q5:Q9080, "Yes (correct)"))/(COUNTIF(Q5:Q9080, "Yes")+COUNTIF(Q5:Q9080, "No")+COUNTIF(Q5:Q9080, "Yes (correct)")+COUNTIF(Q5:Q9080, "No (incorrect)")) -> 0.99521531 | R4: =(COUNTIF(R5:R9080, "No")+COUNTIF(R5:R9080, "Yes (correct)"))/(COUNTIF(R5:R9080, "Yes")+COUNTIF(R5:R9080, "No")+COUNTIF(R5:R9080, "Yes (correct)")+COUNTIF(R5:R9080, "No (incorrect)")) -> 0.51256281 | S4: =(COUNTIF(S5:S9080, "No")+COUNTIF(S5:S9080, "Yes (correct)"))/(COUNTIF(S5:S9080, "Yes")+COUNTIF(S5:S9080, "No")+COUNTIF(S5:S9080, "Yes (correct)")+COUNTIF(S5:S9080, "No (incorrect)")) -> 0.90521327 | T4: =(COUNTIF(T5:T9080, "No")+COUNTIF(T5:T9080, "Yes (correct)"))/(COUNTIF(T5:T9080, "Yes")+COUNTIF(T5:T9080, "No")+COUNTIF(T5:T9080, "Yes (correct)")+COUNTIF(T5:T9080, "No (incorrect)")) -> 0.27536232 | U4: =(COUNTIF(U5:U9080, "No")+COUNTIF(U5:U9080, "Yes (correct)"))/(COUNTIF(U5:U9080, "Yes")+COUNTIF(U5:U9080, "No")+COUNTIF(U5:U9080, "Yes (correct)")+COUNTIF(U5:U9080, "No (incorrect)")) -> 0.45145631 | V4: =(COUNTIF(V5:V9080, "No")+COUNTIF(V5:V9080, "Yes (correct)"))/(COUNTIF(V5:V9080, "Yes")+COUNTIF(V5:V9080, "No")+COUNTIF(V5:V9080, "Yes (correct)")+COUNTIF(V5:V9080, "No (incorrect)")) -> 0.28571429 | W4: =(COUNTIF(W5:W9080, "No")+COUNTIF(W5:W9080, "Yes (correct)"))/(COUNTIF(W5:W9080, "Yes")+COUNTIF(W5:W9080, "No")+COUNTIF(W5:W9080, "Yes (correct)")+COUNTIF(W5:W9080, "No (incorrect)")) -> 0.23809524 | ... BP4: =(COUNTIF(BP5:BP9080, "No")+COUNTIF(BP5:BP9080, "Yes (correct)"))/(COUNTIF(BP5:BP9080, "Yes")+COUNTIF(BP5:BP9080, "No")+COUNTIF(BP5:BP9080, "Yes (correct)")+COUNTIF(BP5:BP9080, "No (incorrect)")) -> 0
A5: =LOOKUP(H5,'Letter grades'!$A$1:$B$6) -> A | B5: =RANK(H5,H:H) -> 1 | C5: Rashida | D5: Tlaib | E5: MI-12 | F5: =((COUNTIF($J5:$BP5,"Sponsor")+COUNTIF($J5:$BP5, "Not sponsoring (correct)"))/(COUNTIF($J5:$BP5,"Sponsor")+COUNTIF($J5:$BP5,"Not sponsoring")+COUNTIF($J5:$BP5, "Not sponsoring (correct)")+COUNTIF($J5:$BP5, "Sponsor (incorrect)"))) -> 1 | G5: =(COUNTIF($K5:$BP5,"No")+COUNTIF($K5:$BP5,"Yes (correct)")+(COUNTIF($K5:$BP5,"Present")*0.5))/(COUNTIF($K5:$BP5,"Yes")+COUNTIF($K5:$BP5,"No")+COUNTIF($K5:$BP5,"Yes (correct)")+COUNTIF($K5:$BP5,"No (incorrect)")+COUNTIF($K5:$BP5,"Present")) -> 0.96875 | H5: =((F5*(1/3))+(G5*(2/3))) -> 0.97916667 | I5: PAL PAC, DSA, JDems | J5: Sponsor | K5: Sponsor | L5: Sponsor | M5: Sponsor | N5: Sponsor | O5: Not sponsoring (correct) | P5: No | Q5: No | R5: Yes (correct) | S5: No | T5: No | U5: No | V5: Not on committee | W5: Not on committee | X5: Yes (correct) | Y5: Present | Z5: No | AA5: No | AB5: No | AC5: No | AD5: No | AE5: No | AF5: No | AG5: Not voting | AH5: No | AI5: No | AJ5: No | AK5: No | AL5: No | AM5: No | AN5: No | AO5: No | AP5: No | AQ5: Present | AR5: No | AS5: No | AT5: No | AU5: No | AV5: No | AW5: No | AX5: Present | AY5: No | AZ5: No | BA5: No | BB5: No | BC5: No | BD5: No | BE5: No | BF5: No | BG5: No | BH5: No | BI5: No | BJ5: No | BK5: No | BL5: No | BM5: No | BN5: No | BO5: Not elected | BP5: Not elected | BQ5: Non-signatory | BR5: Non-signatory | BS5: Non-signatory | BU5: =SUM(BV5:BY5) -> 0 | BZ5: Yes
A6: =LOOKUP(H6,'Letter grades'!$A$1:$B$6) -> A | B6: =RANK(H6,H:H) -> 2 | C6: Ilhan | D6: Omar | E6: MN-05 | F6: =((COUNTIF($J6:$BP6,"Sponsor")+COUNTIF($J6:$BP6, "Not sponsoring (correct)"))/(COUNTIF($J6:$BP6,"Sponsor")+COUNTIF($J6:$BP6,"Not sponsoring")+COUNTIF($J6:$BP6, "Not sponsoring (correct)")+COUNTIF($J6:$BP6, "Sponsor (incorrect)"))) -> 1 | G6: =(COUNTIF($K6:$BP6,"No")+COUNTIF($K6:$BP6,"Yes (correct)")+(COUNTIF($K6:$BP6,"Present")*0.5))/(COUNTIF($K6:$BP6,"Yes")+COUNTIF($K6:$BP6,"No")+COUNTIF($K6:$BP6,"Yes (correct)")+COUNTIF($K6:$BP6,"No (incorrect)")+COUNTIF($K6:$BP6,"Present")) -> 0.91666667 | H6: =((F6*(1/3))+(G6*(2/3))) -> 0.94444444 | I6: PAL PAC, JDems | J6: Sponsor | K6: Sponsor | L6: Sponsor | M6: Sponsor | N6: Sponsor | O6: Not sponsoring (correct) | P6: No | Q6: No | R6: Yes (correct) | S6: No | T6: No | U6: No | V6: Not on committee | W6: Not on committee | X6: Yes (correct) | Y6: Yes | Z6: No | AA6: No | AB6: No | AC6: No | AD6: No | AE6: No | AF6: No | AG6: No | AH6: No | AI6: No | AJ6: No | AK6: No | AL6: No | AM6: No | AN6: No | AO6: No | AP6: No | AQ6: Not voting | AR6: No | AS6: Yes | AT6: No | AU6: No | AV6: No | AW6: No | AX6: Yes | AY6: No | AZ6: No | BA6: No | BB6: No | BC6: No | BD6: No | BE6: No | BF6: No | BG6: No | BH6: No | BI6: No | BJ6: No | BK6: No | BL6: Yes | BM6: No | BN6: No | BO6: Not elected | BP6: Not elected | BQ6: Non-signatory | BR6: Non-signatory | BS6: Non-signatory | BU6: =SUM(BV6:BY6) -> 0 | BZ6: Yes
A7: =LOOKUP(H7,'Letter grades'!$A$1:$B$6) -> A | B7: =RANK(H7,H:H) -> 3 | C7: Delia | D7: Ramirez | E7: IL-03 | F7: =((COUNTIF($J7:$BP7,"Sponsor")+COUNTIF($J7:$BP7, "Not sponsoring (correct)"))/(COUNTIF($J7:$BP7,"Sponsor")+COUNTIF($J7:$BP7,"Not sponsoring")+COUNTIF($J7:$BP7, "Not sponsoring (correct)")+COUNTIF($J7:$BP7, "Sponsor (incorrect)"))) -> 1 | G7: =(COUNTIF($K7:$BP7,"No")+COUNTIF($K7:$BP7,"Yes (correct)")+(COUNTIF($K7:$BP7,"Present")*0.5))/(COUNTIF($K7:$BP7,"Yes")+COUNTIF($K7:$BP7,"No")+COUNTIF($K7:$BP7,"Yes (correct)")+COUNTIF($K7:$BP7,"No (incorrect)")+COUNTIF($K7:$BP7,"Present")) -> 0.86904762 | H7: =((F7*(1/3))+(G7*(2/3))) -> 0.91269841 | I7: PAL PAC, J Street, JDems | J7: Sponsor | K7: Sponsor | L7: Sponsor | M7: Sponsor | N7: Sponsor | O7: Not sponsoring (correct) | P7: No | Q7: No | R7: Yes (correct) | S7: No | T7: No | U7: No | V7: Not on committee | W7: Not on committee | X7: Not voting | Y7: Yes | Z7: No | AA7: No | AB7: No | AC7: Yes | AD7: No | AE7: No | AF7: No | AG7: No | AH7: No | AI7: No | AJ7: No | AK7: No | AL7: No | AM7: No | AN7: Yes | AO7: No | AP7: No | AQ7: Yes | AR7: No | AS7: Present | AT7: No | AU7: No | AV7: No | AW7: No | AX7: Yes | AY7: No | AZ7: No | BA7: No | BB7: No | BC7: No | BD7: No | BE7: No | BF7: No | BG7: No | BH7: No | BI7: Not elected | BJ7: Not elected | BK7: Not elected | BL7: Not elected | BM7: Not elected | BN7: Not elected | BO7: Not elected | BP7: Not elected | BQ7: Non-signatory | BR7: Non-signatory | BS7: Non-signatory | BU7: =SUM(BV7:BY7) -> -157223 | BY7: -157223 | CA7: Yes
A8: =LOOKUP(H8,'Letter grades'!$A$1:$B$6) -> A | B8: =RANK(H8,H:H) -> 4 | C8: Summer | D8: Lee | E8: PA-12 | F8: =((COUNTIF($J8:$BP8,"Sponsor")+COUNTIF($J8:$BP8, "Not sponsoring (correct)"))/(COUNTIF($J8:$BP8,"Sponsor")+COUNTIF($J8:$BP8,"Not sponsoring")+COUNTIF($J8:$BP8, "Not sponsoring (correct)")+COUNTIF($J8:$BP8, "Sponsor (incorrect)"))) -> 1 | G8: =(COUNTIF($K8:$BP8,"No")+COUNTIF($K8:$BP8,"Yes (correct)")+(COUNTIF($K8:$BP8,"Present")*0.5))/(COUNTIF($K8:$BP8,"Yes")+COUNTIF($K8:$BP8,"No")+COUNTIF($K8:$BP8,"Yes (correct)")+COUNTIF($K8:$BP8,"No (incorrect)")+COUNTIF($K8:$BP8,"Present")) -> 0.86046512 | H8: =((F8*(1/3))+(G8*(2/3))) -> 0.90697674 | I8: PAL PAC, JDems | J8: Sponsor | K8: Sponsor | L8: Sponsor | M8: Sponsor | N8: Sponsor | O8: Not sponsoring (correct) | P8: No | Q8: No | R8: Yes (correct) | S8: No | T8: No | U8: No | V8: Not on committee | W8: Not on committee | X8: Yes (correct) | Y8: Yes | Z8: No | AA8: No | AB8: No | AC8: Yes | AD8: No | AE8: No | AF8: No | AG8: No | AH8: No | AI8: No | AJ8: No | AK8: No | AL8: No | AM8: No | AN8: Yes | AO8: No | AP8: No | AQ8: Yes | AR8: No | AS8: Yes | AT8: No | AU8: No | AV8: No | AW8: No | AX8: Yes | AY8: No | AZ8: No | BA8: No | BB8: No | BC8: No | BD8: No | BE8: No | BF8: No | BG8: No | BH8: No | BI8: Not elected | BJ8: Not elected | BK8: Not elected | BL8: Not elected | BM8: Not elected | BN8: Not elected | BO8: Not elected | BP8: Not elected | BQ8: Non-signatory | BR8: Non-signatory | BS8: Non-signatory | BU8: =SUM(BV8:BY8) -> -5099105 | BV8: -699642 | BW8: =-3924473 -> -3924473 | BX8: =-2000 -> -2000 | BY8: -472990 | CA8: Yes
A9: =LOOKUP(H9,'Letter grades'!$A$1:$B$6) -> B | B9: =RANK(H9,H:H) -> 5 | C9: Alexandria | D9: Ocasio-Cortez | E9: NY-14 | F9: =((COUNTIF($J9:$BP9,"Sponsor")+COUNTIF($J9:$BP9, "Not sponsoring (correct)"))/(COUNTIF($J9:$BP9,"Sponsor")+COUNTIF($J9:$BP9,"Not sponsoring")+COUNTIF($J9:$BP9, "Not sponsoring (correct)")+COUNTIF($J9:$BP9, "Sponsor (incorrect)"))) -> 1 | G9: =(COUNTIF($K9:$BP9,"No")+COUNTIF($K9:$BP9,"Yes (correct)")+(COUNTIF($K9:$BP9,"Present")*0.5))/(COUNTIF($K9:$BP9,"Yes")+COUNTIF($K9:$BP9,"No")+COUNTIF($K9:$BP9,"Yes (correct)")+COUNTIF($K9:$BP9,"No (incorrect)")+COUNTIF($K9:$BP9,"Present")) -> 0.84375 | H9: =((F9*(1/3))+(G9*(2/3))) -> 0.89583333 | I9: NYC-DSA, JDems | J9: Sponsor | K9: Sponsor | L9: Sponsor | M9: Sponsor | N9: Sponsor | O9: Not sponsoring (correct) | P9: No | Q9: No | R9: Yes (correct) | S9: No | T9: No | U9: No | V9: Not on committee | W9: Not on committee | X9: No (incorrect) | Y9: Yes | Z9: No | AA9: No | AB9: No | AC9: Yes | AD9: No | AE9: No | AF9: No | AG9: No | AH9: No | AI9: No | AJ9: No | AK9: No | AL9: No | AM9: No | AN9: Yes | AO9: No | AP9: No | AQ9: Yes | AR9: No | AS9: Yes | AT9: No | AU9: No | AV9: No | AW9: Not voting | AX9: Yes | AY9: No | AZ9: No | BA9: No | BB9: No | BC9: No | BD9: No | BE9: No | BF9: No | BG9: No | BH9: No | BI9: No | BJ9: No | BK9: Present | BL9: No | BM9: No | BN9: No | BO9: Not elected | BP9: Not elected | BQ9: Non-signatory | BR9: Non-signatory | BS9: Non-signatory | BU9: =SUM(BV9:BY9) -> 0 | BZ9: Yes
A10: =LOOKUP(H10,'Letter grades'!$A$1:$B$6) -> B | B10: =RANK(H10,H:H) -> 6 | C10: Ayanna | D10: Pressley | E10: MA-07 | F10: =((COUNTIF($J10:$BP10,"Sponsor")+COUNTIF($J10:$BP10, "Not sponsoring (correct)"))/(COUNTIF($J10:$BP10,"Sponsor")+COUNTIF($J10:$BP10,"Not sponsoring")+COUNTIF($J10:$BP10, "Not sponsoring (correct)")+COUNTIF($J10:$BP10, "Sponsor (incorrect)"))) -> 1 | G10: =(COUNTIF($K10:$BP10,"No")+COUNTIF($K10:$BP10,"Yes (correct)")+(COUNTIF($K10:$BP10,"Present")*0.5))/(COUNTIF($K10:$BP10,"Yes")+COUNTIF($K10:$BP10,"No")+COUNTIF($K10:$BP10,"Yes (correct)")+COUNTIF($K10:$BP10,"No (incorrect)")+COUNTIF($K10:$BP10,"Present")) -> 0.80208333 | H10: =((F10*(1/3))+(G10*(2/3))) -> 0.86805556 | I10: JDems | J10: Sponsor | K10: Sponsor | L10: Sponsor | M10: Sponsor | N10: Sponsor | O10: Not sponsoring (correct) | P10: No | Q10: No | R10: Yes (correct) | S10: No | T10: No | U10: No | V10: Not on committee | W10: Not on committee | X10: No (incorrect) | Y10: Yes | Z10: No | AA10: No | AB10: No | AC10: Yes | AD10: No | AE10: No | AF10: No | AG10: No | AH10: No | AI10: No | AJ10: No | AK10: No | AL10: No | AM10: No | AN10: Yes | AO10: No | AP10: Not voting | AQ10: Yes | AR10: No | AS10: Yes | AT10: No | AU10: No | AV10: No | AW10: No | AX10: Yes | AY10: No | AZ10: No | BA10: No | BB10: No | BC10: No | BD10: Present | BE10: No | BF10: No | BG10: No | BH10: No | BI10: No | BJ10: No | BK10: No | BL10: Yes | BM10: No | BN10: Yes | BO10: Not elected | BP10: Not elected | BQ10: Non-signatory | BR10: Non-signatory | BS10: Non-signatory | BU10: =SUM(BV10:BY10) -> 0
A11: =LOOKUP(H11,'Letter grades'!$A$1:$B$6) -> B | B11: =RANK(H11,H:H) -> 7 | C11: Lateefah | D11: Simon | E11: CA-12 | F11: =((COUNTIF($J11:$BP11,"Sponsor")+COUNTIF($J11:$BP11, "Not sponsoring (correct)"))/(COUNTIF($J11:$BP11,"Sponsor")+COUNTIF($J11:$BP11,"Not sponsoring")+COUNTIF($J11:$BP11, "Not sponsoring (correct)")+COUNTIF($J11:$BP11, "Sponsor (incorrect)"))) -> 1 | G11: =(COUNTIF($K11:$BP11,"No")+COUNTIF($K11:$BP11,"Yes (correct)")+(COUNTIF($K11:$BP11,"Present")*0.5))/(COUNTIF($K11:$BP11,"Yes")+COUNTIF($K11:$BP11,"No")+COUNTIF($K11:$BP11,"Yes (correct)")+COUNTIF($K11:$BP11,"No (incorrect)")+COUNTIF($K11:$BP11,"Present")) -> 0.77777778 | H11: =((F11*(1/3))+(G11*(2/3))) -> 0.85185185 | I11: J Street | J11: Sponsor | K11: Sponsor | L11: Sponsor | M11: Sponsor | N11: Sponsor | O11: Not sponsoring (correct) | P11: No | Q11: No | R11: Yes (correct) | S11: No | T11: No | U11: No | V11: Not on committee | W11: Not on committee | X11: No (incorrect) | Y11: Yes | Z11: No | AA11: Not elected | AB11: Not elected | AC11: Not elected | AD11: Not elected | AE11: Not elected | AF11: Not elected | AG11: Not elected | AH11: Not elected | AI11: Not elected | AJ11: Not elected | AK11: Not elected | AL11: Not elected | AM11: Not elected | AN11: Not elected | AO11: Not elected | AP11: Not elected | AQ11: Not elected | AR11: Not elected | AS11: Not elected | AT11: Not elected | AU11: Not elected | AV11: Not elected | AW11: Not elected | AX11: Not elected | AY11: Not elected | AZ11: Not elected | BA11: Not elected | BB11: Not elected | BC11: Not elected | BD11: Not elected | BE11: Not elected | BF11: Not elected | BG11: Not elected | BH11: Not elected | BI11: Not elected | BJ11: Not elected | BK11: Not elected | BL11: Not elected | BM11: Not elected | BN11: Not elected | BO11: Not elected | BP11: Not elected | BQ11: Non-signatory | BR11: Not elected | BS11: Not elected
A12: =LOOKUP(H12,'Letter grades'!$A$1:$B$6) -> B | B12: =RANK(H12,H:H) -> 8 | C12: Jesús "Chuy" | D12: García | E12: IL-04 | F12: =((COUNTIF($J12:$BP12,"Sponsor")+COUNTIF($J12:$BP12, "Not sponsoring (correct)"))/(COUNTIF($J12:$BP12,"Sponsor")+COUNTIF($J12:$BP12,"Not sponsoring")+COUNTIF($J12:$BP12, "Not sponsoring (correct)")+COUNTIF($J12:$BP12, "Sponsor (incorrect)"))) -> 1 | G12: =(COUNTIF($K12:$BP12,"No")+COUNTIF($K12:$BP12,"Yes (correct)")+(COUNTIF($K12:$BP12,"Present")*0.5))/(COUNTIF($K12:$BP12,"Yes")+COUNTIF($K12:$BP12,"No")+COUNTIF($K12:$BP12,"Yes (correct)")+COUNTIF($K12:$BP12,"No (incorrect)")+COUNTIF($K12:$BP12,"Present")) -> 0.7755102 | H12: =((F12*(1/3))+(G12*(2/3))) -> 0.85034014 | I12: J Street | J12: Sponsor | K12: Sponsor | L12: Sponsor | M12: Sponsor | N12: Sponsor | O12: Not sponsoring (correct) | P12: No | Q12: No | R12: Yes (correct) | S12: No | T12: No | U12: No | V12: Not on committee | W12: Not on committee | X12: No (incorrect) | Y12: Yes | Z12: No | AA12: No | AB12: No | AC12: Yes | AD12: No | AE12: No | AF12: No | AG12: No | AH12: No | AI12: No | AJ12: No | AK12: No | AL12: Yes | AM12: No | AN12: Yes | AO12: No | AP12: No | AQ12: Yes | AR12: No | AS12: Yes | AT12: No | AU12: No | AV12: No | AW12: No | AX12: Yes | AY12: No | AZ12: No | BA12: No | BB12: No | BC12: No | BD12: Present | BE12: No | BF12: Yes | BG12: No | BH12: No | BI12: No | BJ12: No | BK12: No | BL12: Yes | BM12: Present | BN12: No | BO12: Not elected | BP12: Not elected | BQ12: Non-signatory | BR12: Non-signatory | BS12: Non-signatory | BU12: =SUM(BV12:BY12) -> 0 | BZ12: Yes | CA12: Yes
A13: =LOOKUP(H13,'Letter grades'!$A$1:$B$6) -> C | B13: =RANK(H13,H:H) -> 9 | C13: Maxine | D13: Dexter | E13: OR-03 | F13: =((COUNTIF($J13:$BP13,"Sponsor")+COUNTIF($J13:$BP13, "Not sponsoring (correct)"))/(COUNTIF($J13:$BP13,"Sponsor")+COUNTIF($J13:$BP13,"Not sponsoring")+COUNTIF($J13:$BP13, "Not sponsoring (correct)")+COUNTIF($J13:$BP13, "Sponsor (incorrect)"))) -> 0.83333333 | G13: =(COUNTIF($K13:$BP13,"No")+COUNTIF($K13:$BP13,"Yes (correct)")+(COUNTIF($K13:$BP13,"Present")*0.5))/(COUNTIF($K13:$BP13,"Yes")+COUNTIF($K13:$BP13,"No")+COUNTIF($K13:$BP13,"Yes (correct)")+COUNTIF($K13:$BP13,"No (incorrect)")+COUNTIF($K13:$BP13,"Present")) -> 0.77777778 | H13: =((F13*(1/3))+(G13*(2/3))) -> 0.7962963 | J13: Sponsor | K13: Sponsor | L13: Sponsor | M13: Sponsor | N13: Not sponsoring | O13: Not sponsoring (correct) | P13: No | Q13: No | R13: Yes (correct) | S13: No | T13: No | U13: No | V13: Not on committee | W13: Not on committee | X13: No (incorrect) | Y13: Yes | Z13: No | AA13: Not elected | AB13: Not elected | AC13: Not elected | AD13: Not elected | AE13: Not elected | AF13: Not elected | AG13: Not elected | AH13: Not elected | AI13: Not elected | AJ13: Not elected | AK13: Not elected | AL13: Not elected | AM13: Not elected | AN13: Not elected | AO13: Not elected | AP13: Not elected | AQ13: Not elected | AR13: Not elected | AS13: Not elected | AT13: Not elected | AU13: Not elected | AV13: Not elected | AW13: Not elected | AX13: Not elected | AY13: Not elected | AZ13: Not elected | BA13: Not elected | BB13: Not elected | BC13: Not elected | BD13: Not elected | BE13: Not elected | BF13: Not elected | BG13: Not elected | BH13: Not elected | BI13: Not elected | BJ13: Not elected | BK13: Not elected | BL13: Not elected | BM13: Not elected | BN13: Not elected | BO13: Not elected | BP13: Not elected | BQ13: Non-signatory | BR13: Not elected | BS13: Not elected
A14: =LOOKUP(H14,'Letter grades'!$A$1:$B$6) -> C | B14: =RANK(H14,H:H) -> 10 | C14: Adelita | D14: Grijalva | E14: AZ-07 | F14: =((COUNTIF($J14:$BP14,"Sponsor")+COUNTIF($J14:$BP14, "Not sponsoring (correct)"))/(COUNTIF($J14:$BP14,"Sponsor")+COUNTIF($J14:$BP14,"Not sponsoring")+COUNTIF($J14:$BP14, "Not sponsoring (correct)")+COUNTIF($J14:$BP14, "Sponsor (incorrect)"))) -> 0.33333333 | G14: =(COUNTIF($K14:$BP14,"No")+COUNTIF($K14:$BP14,"Yes (correct)")+(COUNTIF($K14:$BP14,"Present")*0.5))/(COUNTIF($K14:$BP14,"Yes")+COUNTIF($K14:$BP14,"No")+COUNTIF($K14:$BP14,"Yes (correct)")+COUNTIF($K14:$BP14,"No (incorrect)")+COUNTIF($K14:$BP14,"Present")) -> 1 | H14: =((F14*(1/3))+(G14*(2/3))) -> 0.77777778 | I14: J Street | J14: Not sponsoring | K14: Not sponsoring | L14: Sponsor | M14: Not sponsoring | N14: Not sponsoring | O14: Not sponsoring (correct) | P14: No | Q14: No | R14: Yes (correct) | S14: No | T14: No | U14: No | V14: Not elected | W14: Not elected | X14: Not elected | Y14: Not elected | Z14: Not elected | AA14: Not elected | AB14: Not elected | AC14: Not elected | AD14: Not elected | AE14: Not elected | AF14: Not elected | AG14: Not elected | AH14: Not elected | AI14: Not elected | AJ14: Not elected | AK14: Not elected | AL14: Not elected | AM14: Not elected | AN14: Not elected | AO14: Not elected | AP14: Not elected | AQ14: Not elected | AR14: Not elected | AS14: Not elected | AT14: Not elected | AU14: Not elected | AV14: Not elected | AW14: Not elected | AX14: Not elected | AY14: Not elected | AZ14: Not elected | BA14: Not elected | BB14: Not elected | BC14: Not elected | BD14: Not elected | BE14: Not elected | BF14: Not elected | BG14: Not elected | BH14: Not elected | BI14: Not elected | BJ14: Not elected | BK14: Not elected | BL14: Not elected | BM14: Not elected | BN14: Not elected | BO14: Not elected | BP14: Not elected | BQ14: Not elected | BR14: Not elected | BS14: Not elected
A15: =LOOKUP(H15,'Letter grades'!$A$1:$B$6) -> C | B15: =RANK(H15,H:H) -> 11 | C15: André | D15: Carson | E15: IN-07 | F15: =((COUNTIF($J15:$BP15,"Sponsor")+COUNTIF($J15:$BP15, "Not sponsoring (correct)"))/(COUNTIF($J15:$BP15,"Sponsor")+COUNTIF($J15:$BP15,"Not sponsoring")+COUNTIF($J15:$BP15, "Not sponsoring (correct)")+COUNTIF($J15:$BP15, "Sponsor (incorrect)"))) -> 1 | G15: =(COUNTIF($K15:$BP15,"No")+COUNTIF($K15:$BP15,"Yes (correct)")+(COUNTIF($K15:$BP15,"Present")*0.5))/(COUNTIF($K15:$BP15,"Yes")+COUNTIF($K15:$BP15,"No")+COUNTIF($K15:$BP15,"Yes (correct)")+COUNTIF($K15:$BP15,"No (incorrect)")+COUNTIF($K15:$BP15,"Present")) -> 0.66 | H15: =((F15*(1/3))+(G15*(2/3))) -> 0.77333333 | I15: J Street | J15: Sponsor | K15: Sponsor | L15: Sponsor | M15: Sponsor | N15: Sponsor | O15: Not sponsoring (correct) | P15: No | Q15: No | R15: Yes (correct) | S15: No | T15: No | U15: No | V15: Not on committee | W15: Not on committee | X15: No (incorrect) | Y15: Yes | Z15: No | AA15: No | AB15: No | AC15: Yes | AD15: No | AE15: No | AF15: No | AG15: No | AH15: Not voting | AI15: No | AJ15: No | AK15: No | AL15: Yes | AM15: No | AN15: Yes | AO15: Yes | AP15: No | AQ15: Yes | AR15: No | AS15: Yes | AT15: No | AU15: No | AV15: Present | AW15: Yes | AX15: Yes | AY15: Yes | AZ15: No | BA15: No | BB15: No | BC15: No | BD15: No | BE15: No | BF15: No | BG15: Yes | BH15: No | BI15: Yes | BJ15: Yes | BK15: No | BL15: Yes | BM15: Yes | BN15: No | BO15: No | BP15: Present | BQ15: Non-signatory | BR15: Non-signatory | BS15: Non-signatory | BU15: =SUM(BV15:BY15) -> 0 | BZ15: Yes | CA15: Yes
A16: =LOOKUP(H16,'Letter grades'!$A$1:$B$6) -> C | B16: =RANK(H16,H:H) -> 12 | C16: Pramila | D16: Jayapal | E16: WA-07 | F16: =((COUNTIF($J16:$BP16,"Sponsor")+COUNTIF($J16:$BP16, "Not sponsoring (correct)"))/(COUNTIF($J16:$BP16,"Sponsor")+COUNTIF($J16:$BP16,"Not sponsoring")+COUNTIF($J16:$BP16, "Not sponsoring (correct)")+COUNTIF($J16:$BP16, "Sponsor (incorrect)"))) -> 0.83333333 | G16: =(COUNTIF($K16:$BP16,"No")+COUNTIF($K16:$BP16,"Yes (correct)")+(COUNTIF($K16:$BP16,"Present")*0.5))/(COUNTIF($K16:$BP16,"Yes")+COUNTIF($K16:$BP16,"No")+COUNTIF($K16:$BP16,"Yes (correct)")+COUNTIF($K16:$BP16,"No (incorrect)")+COUNTIF($K16:$BP16,"Present")) -> 0.72115385 | H16: =((F16*(1/3))+(G16*(2/3))) -> 0.75854701 | I16: J Street, JDems | J16: Sponsor | K16: Sponsor | L16: Sponsor | M16: Sponsor | N16: Not sponsoring | O16: Not sponsoring (correct) | P16: No | Q16: No | R16: Yes (correct) | S16: No | T16: No | U16: No | V16: Yes (correct) | W16: Yes (correct) | X16: No (incorrect) | Y16: Yes | Z16: No | AA16: No | AB16: No | AC16: Yes | AD16: No | AE16: No | AF16: No | AG16: No | AH16: No | AI16: No | AJ16: No | AK16: No | AL16: No | AM16: No | AN16: Yes | AO16: Yes | AP16: No | AQ16: Yes | AR16: No | AS16: Yes | AT16: No | AU16: No | AV16: No | AW16: Yes | AX16: Yes | AY16: No | AZ16: No | BA16: No | BB16: No | BC16: No | BD16: Present | BE16: No | BF16: Yes | BG16: Yes | BH16: No | BI16: No | BJ16: No | BK16: Yes | BL16: Yes | BM16: Yes | BN16: No | BO16: No | BP16: Not elected | BQ16: Non-signatory | BR16: Non-signatory | BS16: Non-signatory | BU16: =SUM(BV16:BY16) -> 0 | BZ16: Yes | CA16: Yes
A17: =LOOKUP(H17,'Letter grades'!$A$1:$B$6) -> C | B17: =RANK(H17,H:H) -> 13 | C17: Greg | D17: Casar | E17: TX-35 | F17: =((COUNTIF($J17:$BP17,"Sponsor")+COUNTIF($J17:$BP17, "Not sponsoring (correct)"))/(COUNTIF($J17:$BP17,"Sponsor")+COUNTIF($J17:$BP17,"Not sponsoring")+COUNTIF($J17:$BP17, "Not sponsoring (correct)")+COUNTIF($J17:$BP17, "Sponsor (incorrect)"))) -> 0.83333333 | G17: =(COUNTIF($K17:$BP17,"No")+COUNTIF($K17:$BP17,"Yes (correct)")+(COUNTIF($K17:$BP17,"Present")*0.5))/(COUNTIF($K17:$BP17,"Yes")+COUNTIF($K17:$BP17,"No")+COUNTIF($K17:$BP17,"Yes (correct)")+COUNTIF($K17:$BP17,"No (incorrect)")+COUNTIF($K17:$BP17,"Present")) -> 0.69047619 | H17: =((F17*(1/3))+(G17*(2/3))) -> 0.73809524 | I17: J Street, JDems | J17: Sponsor | K17: Sponsor | L17: Sponsor | M17: Sponsor | N17: Not sponsoring | O17: Not sponsoring (correct) | P17: No | Q17: No | R17: Yes (correct) | S17: No | T17: Not voting | U17: No | V17: Not on committee | W17: Not on committee | X17: No (incorrect) | Y17: Yes | Z17: No | AA17: No | AB17: No | AC17: Yes | AD17: No | AE17: No | AF17: No | AG17: No | AH17: No | AI17: No | AJ17: No | AK17: No | AL17: No | AM17: No | AN17: Yes | AO17: Yes | AP17: No | AQ17: Yes | AR17: No | AS17: Yes | AT17: No | AU17: No | AV17: Present | AW17: No | AX17: Yes | AY17: No | AZ17: No | BA17: Yes | BB17: No | BC17: No | BD17: Present | BE17: No | BF17: Yes | BG17: Yes | BH17: Yes | BI17: Not elected | BJ17: Not elected | BK17: Not elected | BL17: Not elected | BM17: Not elected | BN17: Not elected | BO17: Not elected | BP17: Not elected | BQ17: Non-signatory | BR17: Non-signatory | BS17: Non-signatory | BU17: =SUM(BV17:BY17) -> 0 | CA17: Yes
A18: =LOOKUP(H18,'Letter grades'!$A$1:$B$6) -> C | B18: =RANK(H18,H:H) -> 14 | C18: Bonnie | D18: Watson Coleman | E18: NJ-12 | F18: =((COUNTIF($J18:$BP18,"Sponsor")+COUNTIF($J18:$BP18, "Not sponsoring (correct)"))/(COUNTIF($J18:$BP18,"Sponsor")+COUNTIF($J18:$BP18,"Not sponsoring")+COUNTIF($J18:$BP18, "Not sponsoring (correct)")+COUNTIF($J18:$BP18, "Sponsor (incorrect)"))) -> 1 | G18: =(COUNTIF($K18:$BP18,"No")+COUNTIF($K18:$BP18,"Yes (correct)")+(COUNTIF($K18:$BP18,"Present")*0.5))/(COUNTIF($K18:$BP18,"Yes")+COUNTIF($K18:$BP18,"No")+COUNTIF($K18:$BP18,"Yes (correct)")+COUNTIF($K18:$BP18,"No (incorrect)")+COUNTIF($K18:$BP18,"Present")) -> 0.59574468 | H18: =((F18*(1/3))+(G18*(2/3))) -> 0.73049645 | I18: J Street | J18: Sponsor | K18: Sponsor | L18: Sponsor | M18: Sponsor | N18: Sponsor | O18: Not sponsoring (correct) | P18: No | Q18: No | R18: Yes (correct) | S18: No | T18: No | U18: No | V18: Not on committee | W18: Not on committee | X18: No (incorrect) | Y18: Yes | Z18: No | AA18: No | AB18: No | AC18: Yes | AD18: No | AE18: No | AF18: Not voting | AG18: Not voting | AH18: No | AI18: No | AJ18: No | AK18: No | AL18: Yes | AM18: No | AN18: Yes | AO18: Yes | AP18: Yes | AQ18: Yes | AR18: No | AS18: Yes | AT18: No | AU18: No | AV18: No | AW18: Yes | AX18: Yes | AY18: No | AZ18: No | BA18: No | BB18: No | BC18: Yes | BD18: Yes | BE18: Yes | BF18: Yes | BG18: Yes | BH18: Not voting | BI18: No | BJ18: No | BK18: Yes | BL18: Yes | BM18: Yes | BN18: No | BO18: No | BP18: Not elected | BQ18: Non-signatory | BR18: Non-signatory | BS18: Non-signatory | BU18: =SUM(BV18:BY18) -> 0 | CA18: Yes
A19: =LOOKUP(H19,'Letter grades'!$A$1:$B$6) -> C | B19: =RANK(H19,H:H) -> 15 | C19: Maxwell | D19: Frost | E19: FL-10 | F19: =((COUNTIF($J19:$BP19,"Sponsor")+COUNTIF($J19:$BP19, "Not sponsoring (correct)"))/(COUNTIF($J19:$BP19,"Sponsor")+COUNTIF($J19:$BP19,"Not sponsoring")+COUNTIF($J19:$BP19, "Not sponsoring (correct)")+COUNTIF($J19:$BP19, "Sponsor (incorrect)"))) -> 0.83333333 | G19: =(COUNTIF($K19:$BP19,"No")+COUNTIF($K19:$BP19,"Yes (correct)")+(COUNTIF($K19:$BP19,"Present")*0.5))/(COUNTIF($K19:$BP19,"Yes")+COUNTIF($K19:$BP19,"No")+COUNTIF($K19:$BP19,"Yes (correct)")+COUNTIF($K19:$BP19,"No (incorrect)")+COUNTIF($K19:$BP19,"Present")) -> 0.62790698 | H19: =((F19*(1/3))+(G19*(2/3))) -> 0.69638243 | J19: Sponsor | K19: Sponsor | L19: Sponsor | M19: Sponsor | N19: Not sponsoring | O19: Not sponsoring (correct) | P19: No | Q19: No | R19: Yes (correct) | S19: No | T19: No | U19: No | V19: Not on committee | W19: Not on committee | X19: No (incorrect) | Y19: Yes | Z19: No | AA19: No | AB19: No | AC19: Yes | AD19: No | AE19: No | AF19: No | AG19: No | AH19: No | AI19: No | AJ19: No | AK19: No | AL19: Yes | AM19: No | AN19: Yes | AO19: Yes | AP19: No | AQ19: Yes | AR19: No | AS19: Yes | AT19: No | AU19: No | AV19: Yes | AW19: Yes | AX19: Yes | AY19: Yes | AZ19: No | BA19: No | BB19: No | BC19: No | BD19: Yes | BE19: No | BF19: Yes | BG19: Yes | BH19: Yes | BI19: Not elected | BJ19: Not elected | BK19: Not elected | BL19: Not elected | BM19: Not elected | BN19: Not elected | BO19: Not elected | BP19: Not elected | BQ19: Non-signatory | BR19: Non-signatory | BS19: Non-signatory | BU19: =SUM(BV19:BY19) -> 0
A20: =LOOKUP(H20,'Letter grades'!$A$1:$B$6) -> C | B20: =RANK(H20,H:H) -> 16 | C20: Mark | D20: Pocan | E20: WI-02 | F20: =((COUNTIF($J20:$BP20,"Sponsor")+COUNTIF($J20:$BP20, "Not sponsoring (correct)"))/(COUNTIF($J20:$BP20,"Sponsor")+COUNTIF($J20:$BP20,"Not sponsoring")+COUNTIF($J20:$BP20, "Not sponsoring (correct)")+COUNTIF($J20:$BP20, "Sponsor (incorrect)"))) -> 0.83333333 | G20: =(COUNTIF($K20:$BP20,"No")+COUNTIF($K20:$BP20,"Yes (correct)")+(COUNTIF($K20:$BP20,"Present")*0.5))/(COUNTIF($K20:$BP20,"Yes")+COUNTIF($K20:$BP20,"No")+COUNTIF($K20:$BP20,"Yes (correct)")+COUNTIF($K20:$BP20,"No (incorrect)")+COUNTIF($K20:$BP20,"Present")) -> 0.62244898 | H20: =((F20*(1/3))+(G20*(2/3))) -> 0.69274376 | I20: J Street | J20: Sponsor | K20: Sponsor | L20: Sponsor | M20: Sponsor | N20: Not sponsoring | O20: Not sponsoring (correct) | P20: No | Q20: No | R20: Yes (correct) | S20: No | T20: No | U20: No | V20: Not on committee | W20: Not on committee | X20: No (incorrect) | Y20: Yes | Z20: No | AA20: No | AB20: No | AC20: Yes | AD20: No | AE20: No | AF20: Not voting | AG20: No | AH20: No | AI20: No | AJ20: No | AK20: No | AL20: Yes | AM20: No | AN20: Yes | AO20: Yes | AP20: Yes | AQ20: Yes | AR20: No | AS20: Yes | AT20: No | AU20: No | AV20: Present | AW20: Yes | AX20: Yes | AY20: No | AZ20: No | BA20: Yes | BB20: No | BC20: No | BD20: Yes | BE20: No | BF20: Yes | BG20: Yes | BH20: No | BI20: No | BJ20: No | BK20: Yes | BL20: Yes | BM20: Yes | BN20: No | BO20: No | BP20: Not elected | BQ20: Non-signatory | BR20: Non-signatory | BS20: Non-signatory | BU20: =SUM(BV20:BY20) -> 0 | BZ20: Yes | CA20: Yes
A21: =LOOKUP(H21,'Letter grades'!$A$1:$B$6) -> C | B21: =RANK(H21,H:H) -> 17 | C21: Hank | D21: Johnson | E21: GA-04 | F21: =((COUNTIF($J21:$BP21,"Sponsor")+COUNTIF($J21:$BP21, "Not sponsoring (correct)"))/(COUNTIF($J21:$BP21,"Sponsor")+COUNTIF($J21:$BP21,"Not sponsoring")+COUNTIF($J21:$BP21, "Not sponsoring (correct)")+COUNTIF($J21:$BP21, "Sponsor (incorrect)"))) -> 1 | G21: =(COUNTIF($K21:$BP21,"No")+COUNTIF($K21:$BP21,"Yes (correct)")+(COUNTIF($K21:$BP21,"Present")*0.5))/(COUNTIF($K21:$BP21,"Yes")+COUNTIF($K21:$BP21,"No")+COUNTIF($K21:$BP21,"Yes (correct)")+COUNTIF($K21:$BP21,"No (incorrect)")+COUNTIF($K21:$BP21,"Present")) -> 0.53 | H21: =((F21*(1/3))+(G21*(2/3))) -> 0.68666667 | I21: J Street | J21: Sponsor | K21: Sponsor | L21: Sponsor | M21: Sponsor | N21: Sponsor | O21: Not sponsoring (correct) | P21: No | Q21: No | R21: Yes (correct) | S21: No | T21: Yes | U21: No | V21: Not on committee | W21: Not on committee | X21: No (incorrect) | Y21: Yes | Z21: No | AA21: No | AB21: No | AC21: Yes | AD21: No | AE21: No | AF21: No | AG21: No | AH21: No | AI21: No | AJ21: No | AK21: Yes | AL21: No | AM21: No | AN21: Yes | AO21: Yes | AP21: Yes | AQ21: Yes | AR21: No | AS21: Yes | AT21: No | AU21: Not voting | AV21: Present | AW21: Yes | AX21: Yes | AY21: No | AZ21: No | BA21: Yes | BB21: No | BC21: Yes | BD21: Yes | BE21: No | BF21: Yes | BG21: Yes | BH21: No | BI21: Yes | BJ21: Yes | BK21: Present | BL21: Yes | BM21: Yes | BN21: Present | BO21: No | BP21: Yes | BQ21: Non-signatory | BR21: Non-signatory | BS21: Non-signatory | BU21: =SUM(BV21:BY21) -> 0 | CA21: Yes
A22: =LOOKUP(H22,'Letter grades'!$A$1:$B$6) -> C | B22: =RANK(H22,H:H) -> 18 | C22: Emily | D22: Randall | E22: WA-06 | F22: =((COUNTIF($J22:$BP22,"Sponsor")+COUNTIF($J22:$BP22, "Not sponsoring (correct)"))/(COUNTIF($J22:$BP22,"Sponsor")+COUNTIF($J22:$BP22,"Not sponsoring")+COUNTIF($J22:$BP22, "Not sponsoring (correct)")+COUNTIF($J22:$BP22, "Sponsor (incorrect)"))) -> 0.5 | G22: =(COUNTIF($K22:$BP22,"No")+COUNTIF($K22:$BP22,"Yes (correct)")+(COUNTIF($K22:$BP22,"Present")*0.5))/(COUNTIF($K22:$BP22,"Yes")+COUNTIF($K22:$BP22,"No")+COUNTIF($K22:$BP22,"Yes (correct)")+COUNTIF($K22:$BP22,"No (incorrect)")+COUNTIF($K22:$BP22,"Present")) -> 0.77777778 | H22: =((F22*(1/3))+(G22*(2/3))) -> 0.68518519 | I22: J Street | J22: Sponsor | K22: Sponsor | L22: Not sponsoring | M22: Not sponsoring | N22: Not sponsoring | O22: Not sponsoring (correct) | P22: No | Q22: No | R22: Yes (correct) | S22: No | T22: No | U22: No | V22: Not on committee | W22: Not on committee | X22: No (incorrect) | Y22: Yes | Z22: No | AA22: Not elected | AB22: Not elected | AC22: Not elected | AD22: Not elected | AE22: Not elected | AF22: Not elected | AG22: Not elected | AH22: Not elected | AI22: Not elected | AJ22: Not elected | AK22: Not elected | AL22: Not elected | AM22: Not elected | AN22: Not elected | AO22: Not elected | AP22: Not elected | AQ22: Not elected | AR22: Not elected | AS22: Not elected | AT22: Not elected | AU22: Not elected | AV22: Not elected | AW22: Not elected | AX22: Not elected | AY22: Not elected | AZ22: Not elected | BA22: Not elected | BB22: Not elected | BC22: Not elected | BD22: Not elected | BE22: Not elected | BF22: Not elected | BG22: Not elected | BH22: Not elected | BI22: Not elected | BJ22: Not elected | BK22: Not elected | BL22: Not elected | BM22: Not elected | BN22: Not elected | BO22: Not elected | BP22: Not elected | BQ22: Non-signatory | BR22: Not elected | BS22: Not elected
A23: =LOOKUP(H23,'Letter grades'!$A$1:$B$6) -> C | B23: =RANK(H23,H:H) -> 19 | C23: Becca | D23: Balint | E23: VT-AL | F23: =((COUNTIF($J23:$BP23,"Sponsor")+COUNTIF($J23:$BP23, "Not sponsoring (correct)"))/(COUNTIF($J23:$BP23,"Sponsor")+COUNTIF($J23:$BP23,"Not sponsoring")+COUNTIF($J23:$BP23, "Not sponsoring (correct)")+COUNTIF($J23:$BP23, "Sponsor (incorrect)"))) -> 0.83333333 | G23: =(COUNTIF($K23:$BP23,"No")+COUNTIF($K23:$BP23,"Yes (correct)")+(COUNTIF($K23:$BP23,"Present")*0.5))/(COUNTIF($K23:$BP23,"Yes")+COUNTIF($K23:$BP23,"No")+COUNTIF($K23:$BP23,"Yes (correct)")+COUNTIF($K23:$BP23,"No (incorrect)")+COUNTIF($K23:$BP23,"Present")) -> 0.60714286 | H23: =((F23*(1/3))+(G23*(2/3))) -> 0.68253968 | I23: J Street | J23: Sponsor | K23: Sponsor | L23: Sponsor | M23: Sponsor | N23: Not sponsoring | O23: Not sponsoring (correct) | P23: No | Q23: No | R23: Yes (correct) | S23: No | T23: No | U23: No | V23: Not on committee | W23: Not on committee | X23: No (incorrect) | Y23: Yes | Z23: No | AA23: No | AB23: No | AC23: Yes | AD23: No | AE23: No | AF23: No | AG23: No | AH23: No | AI23: No | AJ23: No | AK23: No | AL23: Yes | AM23: No | AN23: Yes | AO23: Yes | AP23: No | AQ23: Yes | AR23: No | AS23: Yes | AT23: No | AU23: Not voting | AV23: Present | AW23: Yes | AX23: Yes | AY23: No | AZ23: No | BA23: Yes | BB23: No | BC23: No | BD23: Yes | BE23: Yes | BF23: Yes | BG23: Yes | BH23: Yes | BI23: Not elected | BJ23: Not elected | BK23: Not elected | BL23: Not elected | BM23: Not elected | BN23: Not elected | BO23: Not elected | BP23: Not elected | BQ23: Non-signatory | BR23: Non-signatory | BS23: Non-signatory | BU23: =SUM(BV23:BY23) -> 0 | CA23: Yes
A24: =LOOKUP(H24,'Letter grades'!$A$1:$B$6) -> C | B24: =RANK(H24,H:H) -> 20 | C24: LaMonica | D24: McIver | E24: NJ-10 | F24: =((COUNTIF($J24:$BP24,"Sponsor")+COUNTIF($J24:$BP24, "Not sponsoring (correct)"))/(COUNTIF($J24:$BP24,"Sponsor")+COUNTIF($J24:$BP24,"Not sponsoring")+COUNTIF($J24:$BP24, "Not sponsoring (correct)")+COUNTIF($J24:$BP24, "Sponsor (incorrect)"))) -> 0.5 | G24: =(COUNTIF($K24:$BP24,"No")+COUNTIF($K24:$BP24,"Yes (correct)")+(COUNTIF($K24:$BP24,"Present")*0.5))/(COUNTIF($K24:$BP24,"Yes")+COUNTIF($K24:$BP24,"No")+COUNTIF($K24:$BP24,"Yes (correct)")+COUNTIF($K24:$BP24,"No (incorrect)")+COUNTIF($K24:$BP24,"Present")) -> 0.76923077 | H24: =((F24*(1/3))+(G24*(2/3))) -> 0.67948718 | J24: Sponsor | K24: Not sponsoring | L24: Sponsor | M24: Not sponsoring | N24: Not sponsoring | O24: Not sponsoring (correct) | P24: No | Q24: No | R24: Yes (correct) | S24: No | T24: No | U24: No | V24: Not on committee | W24: Not on committee | X24: No (incorrect) | Y24: Yes | Z24: No | AA24: No | AB24: No | AC24: Yes | AD24: No | AE24: Not elected | AF24: Not elected | AG24: Not elected | AH24: Not elected | AI24: Not elected | AJ24: Not elected | AK24: Not elected | AL24: Not elected | AM24: Not elected | AN24: Not elected | AO24: Not elected | AP24: Not elected | AQ24: Not elected | AR24: Not elected | AS24: Not elected | AT24: Not elected | AU24: Not elected | AV24: Not elected | AW24: Not elected | AX24: Not elected | AY24: Not elected | AZ24: Not elected | BA24: Not elected | BB24: Not elected | BC24: Not elected | BD24: Not elected | BE24: Not elected | BF24: Not elected | BG24: Not elected | BH24: Not elected | BI24: Not elected | BJ24: Not elected | BK24: Not elected | BL24: Not elected | BM24: Not elected | BN24: Not elected | BO24: Not elected | BP24: Not elected | BQ24: Non-signatory | BR24: Not elected | BS24: Not elected | BU24: Not elected | BV24: Not elected | BW24: Not elected | BX24: Not elected | BY24: Not elected | BZ24: Not elected | CA24: Not elected | CB24: Not elected | CC24: Not elected
A25: =LOOKUP(H25,'Letter grades'!$A$1:$B$6) -> C | B25: =RANK(H25,H:H) -> 21 | C25: Al | D25: Green | E25: TX-09 | F25: =((COUNTIF($J25:$BP25,"Sponsor")+COUNTIF($J25:$BP25, "Not sponsoring (correct)"))/(COUNTIF($J25:$BP25,"Sponsor")+COUNTIF($J25:$BP25,"Not sponsoring")+COUNTIF($J25:$BP25, "Not sponsoring (correct)")+COUNTIF($J25:$BP25, "Sponsor (incorrect)"))) -> 1 | G25: =(COUNTIF($K25:$BP25,"No")+COUNTIF($K25:$BP25,"Yes (correct)")+(COUNTIF($K25:$BP25,"Present")*0.5))/(COUNTIF($K25:$BP25,"Yes")+COUNTIF($K25:$BP25,"No")+COUNTIF($K25:$BP25,"Yes (correct)")+COUNTIF($K25:$BP25,"No (incorrect)")+COUNTIF($K25:$BP25,"Present")) -> 0.51 | H25: =((F25*(1/3))+(G25*(2/3))) -> 0.67333333 | J25: Sponsor | K25: Sponsor | L25: Sponsor | M25: Sponsor | N25: Sponsor | O25: Not sponsoring (correct) | P25: No | Q25: No | R25: Yes (correct) | S25: No | T25: Yes | U25: No | V25: Not on committee | W25: Not on committee | X25: Yes (correct) | Y25: Yes | Z25: No | AA25: No | AB25: No | AC25: Yes | AD25: No | AE25: No | AF25: No | AG25: No | AH25: No | AI25: No | AJ25: No | AK25: Yes | AL25: Yes | AM25: No | AN25: Yes | AO25: Not voting | AP25: Yes | AQ25: Yes | AR25: No | AS25: Yes | AT25: No | AU25: Yes | AV25: Present | AW25: No | AX25: Yes | AY25: No | AZ25: No | BA25: Yes | BB25: No | BC25: Yes | BD25: No | BE25: Yes | BF25: Yes | BG25: Yes | BH25: Yes | BI25: Yes | BJ25: Yes | BK25: Yes | BL25: Yes | BM25: Yes | BN25: Yes | BO25: No | BP25: Yes | BQ25: Non-signatory | BR25: Non-signatory | BS25: Non-signatory | BU25: =SUM(BV25:BY25) -> 0 | CA25: Yes
A26: =LOOKUP(H26,'Letter grades'!$A$1:$B$6) -> C | B26: =RANK(H26,H:H) -> 22 | C26: Nydia | D26: Velázquez | E26: NY-07 | F26: =((COUNTIF($J26:$BP26,"Sponsor")+COUNTIF($J26:$BP26, "Not sponsoring (correct)"))/(COUNTIF($J26:$BP26,"Sponsor")+COUNTIF($J26:$BP26,"Not sponsoring")+COUNTIF($J26:$BP26, "Not sponsoring (correct)")+COUNTIF($J26:$BP26, "Sponsor (incorrect)"))) -> 0.83333333 | G26: =(COUNTIF($K26:$BP26,"No")+COUNTIF($K26:$BP26,"Yes (correct)")+(COUNTIF($K26:$BP26,"Present")*0.5))/(COUNTIF($K26:$BP26,"Yes")+COUNTIF($K26:$BP26,"No")+COUNTIF($K26:$BP26,"Yes (correct)")+COUNTIF($K26:$BP26,"No (incorrect)")+COUNTIF($K26:$BP26,"Present")) -> 0.58823529 | H26: =((F26*(1/3))+(G26*(2/3))) -> 0.66993464 | I26: J Street | J26: Sponsor | K26: Sponsor | L26: Sponsor | M26: Sponsor | N26: Not sponsoring | O26: Not sponsoring (correct) | P26: No | Q26: No | R26: Yes (correct) | S26: No | T26: No | U26: No | V26: Not on committee | W26: Not on committee | X26: No (incorrect) | Y26: Yes | Z26: No | AA26: No | AB26: No | AC26: Yes | AD26: No | AE26: No | AF26: No | AG26: No | AH26: No | AI26: No | AJ26: No | AK26: Yes | AL26: Yes | AM26: No | AN26: Yes | AO26: Yes | AP26: No | AQ26: Yes | AR26: No | AS26: Yes | AT26: No | AU26: No | AV26: Present | AW26: Yes | AX26: Yes | AY26: No | AZ26: No | BA26: No | BB26: No | BC26: No | BD26: Present | BE26: No | BF26: Yes | BG26: Yes | BH26: No | BI26: No | BJ26: Yes | BK26: Yes | BL26: Yes | BM26: Yes | BN26: Yes | BO26: Yes | BP26: Yes | BQ26: Non-signatory | BR26: Non-signatory | BS26: Non-signatory | BU26: =SUM(BV26:BY26) -> 0 | CA26: Yes
A27: =LOOKUP(H27,'Letter grades'!$A$1:$B$6) -> C | B27: =RANK(H27,H:H) -> 23 | C27: Jim | D27: McGovern | E27: MA-02 | F27: =((COUNTIF($J27:$BP27,"Sponsor")+COUNTIF($J27:$BP27, "Not sponsoring (correct)"))/(COUNTIF($J27:$BP27,"Sponsor")+COUNTIF($J27:$BP27,"Not sponsoring")+COUNTIF($J27:$BP27, "Not sponsoring (correct)")+COUNTIF($J27:$BP27, "Sponsor (incorrect)"))) -> 0.83333333 | G27: =(COUNTIF($K27:$BP27,"No")+COUNTIF($K27:$BP27,"Yes (correct)")+(COUNTIF($K27:$BP27,"Present")*0.5))/(COUNTIF($K27:$BP27,"Yes")+COUNTIF($K27:$BP27,"No")+COUNTIF($K27:$BP27,"Yes (correct)")+COUNTIF($K27:$BP27,"No (incorrect)")+COUNTIF($K27:$BP27,"Present")) -> 0.55 | H27: =((F27*(1/3))+(G27*(2/3))) -> 0.64444444 | I27: J Street | J27: Sponsor | K27: Sponsor | L27: Sponsor | M27: Sponsor | N27: Not sponsoring | O27: Not sponsoring (correct) | P27: No | Q27: No | R27: Yes (correct) | S27: No | T27: No | U27: No | V27: Not on committee | W27: Not on committee | X27: No (incorrect) | Y27: Yes | Z27: No | AA27: Not voting | AB27: No | AC27: Yes | AD27: No | AE27: No | AF27: No | AG27: No | AH27: No | AI27: No | AJ27: No | AK27: Yes | AL27: Yes | AM27: No | AN27: Yes | AO27: Yes | AP27: No | AQ27: Yes | AR27: No | AS27: Yes | AT27: No | AU27: Yes | AV27: Present | AW27: Yes | AX27: Yes | AY27: Yes | AZ27: No | BA27: No | BB27: No | BC27: No | BD27: Yes | BE27: No | BF27: Yes | BG27: Yes | BH27: Yes | BI27: No | BJ27: No | BK27: Yes | BL27: Yes | BM27: Yes | BN27: Yes | BO27: No | BP27: Yes | BQ27: Non-signatory | BR27: Non-signatory | BS27: Non-signatory | BU27: =SUM(BV27:BY27) -> 0 | CA27: Yes
A28: =LOOKUP(H28,'Letter grades'!$A$1:$B$6) -> C | B28: =RANK(H28,H:H) -> 24 | C28: Ro | D28: Khanna | E28: CA-17 | F28: =((COUNTIF($J28:$BP28,"Sponsor")+COUNTIF($J28:$BP28, "Not sponsoring (correct)"))/(COUNTIF($J28:$BP28,"Sponsor")+COUNTIF($J28:$BP28,"Not sponsoring")+COUNTIF($J28:$BP28, "Not sponsoring (correct)")+COUNTIF($J28:$BP28, "Sponsor (incorrect)"))) -> 1 | G28: =(COUNTIF($K28:$BP28,"No")+COUNTIF($K28:$BP28,"Yes (correct)")+(COUNTIF($K28:$BP28,"Present")*0.5))/(COUNTIF($K28:$BP28,"Yes")+COUNTIF($K28:$BP28,"No")+COUNTIF($K28:$BP28,"Yes (correct)")+COUNTIF($K28:$BP28,"No (incorrect)")+COUNTIF($K28:$BP28,"Present")) -> 0.45918367 | H28: =((F28*(1/3))+(G28*(2/3))) -> 0.63945578 | I28: J Street, JDems | J28: Sponsor | K28: Sponsor | L28: Sponsor | M28: Sponsor | N28: Sponsor | O28: Not sponsoring (correct) | P28: No | Q28: No | R28: Yes (correct) | S28: No | T28: Yes | U28: No | V28: Not on committee | W28: Not on committee | X28: No (incorrect) | Y28: Yes | Z28: No | AA28: No | AB28: No | AC28: Yes | AD28: No | AE28: No | AF28: No | AG28: No | AH28: Not voting | AI28: No | AJ28: No | AK28: No | AL28: Yes | AM28: Yes | AN28: Yes | AO28: Yes | AP28: No | AQ28: Yes | AR28: No | AS28: Yes | AT28: No | AU28: Yes | AV28: Present | AW28: Yes | AX28: Yes | AY28: Yes | AZ28: No | BA28: Yes | BB28: No | BC28: Yes | BD28: Yes | BE28: No | BF28: Yes | BG28: Yes | BH28: Yes | BI28: No | BJ28: Yes | BK28: Yes | BL28: Yes | BM28: Yes | BN28: Yes | BO28: Yes | BP28: Not elected | BQ28: Non-signatory | BR28: Non-signatory | BS28: Non-signatory | BU28: =SUM(BV28:BY28) -> 0 | CA28: Yes
A29: =LOOKUP(H29,'Letter grades'!$A$1:$B$6) -> C | B29: =RANK(H29,H:H) -> 25 | C29: Betty | D29: McCollum | E29: MN-04 | F29: =((COUNTIF($J29:$BP29,"Sponsor")+COUNTIF($J29:$BP29, "Not sponsoring (correct)"))/(COUNTIF($J29:$BP29,"Sponsor")+COUNTIF($J29:$BP29,"Not sponsoring")+COUNTIF($J29:$BP29, "Not sponsoring (correct)")+COUNTIF($J29:$BP29, "Sponsor (incorrect)"))) -> 0.83333333 | G29: =(COUNTIF($K29:$BP29,"No")+COUNTIF($K29:$BP29,"Yes (correct)")+(COUNTIF($K29:$BP29,"Present")*0.5))/(COUNTIF($K29:$BP29,"Yes")+COUNTIF($K29:$BP29,"No")+COUNTIF($K29:$BP29,"Yes (correct)")+COUNTIF($K29:$BP29,"No (incorrect)")+COUNTIF($K29:$BP29,"Present")) -> 0.53921569 | H29: =((F29*(1/3))+(G29*(2/3))) -> 0.6372549 | I29: J Street | J29: Sponsor | K29: Sponsor | L29: Sponsor | M29: Not sponsoring | N29: Sponsor | O29: Not sponsoring (correct) | P29: No | Q29: No | R29: Present | S29: No | T29: Yes | U29: No | V29: Not on committee | W29: Not on committee | X29: No (incorrect) | Y29: Yes | Z29: No | AA29: No | AB29: No | AC29: Yes | AD29: No | AE29: No | AF29: No | AG29: No | AH29: No | AI29: No | AJ29: Yes | AK29: Yes | AL29: Yes | AM29: Yes | AN29: Yes | AO29: Yes | AP29: Yes | AQ29: Yes | AR29: No | AS29: Yes | AT29: No | AU29: No | AV29: Present | AW29: Yes | AX29: Yes | AY29: No | AZ29: No | BA29: Yes | BB29: No | BC29: No | BD29: Yes | BE29: No | BF29: Present | BG29: No | BH29: No | BI29: Yes | BJ29: Yes | BK29: Yes | BL29: Yes | BM29: Present | BN29: No | BO29: No | BP29: Present | BQ29: Non-signatory | BR29: Non-signatory | BS29: Non-signatory | BU29: =SUM(BV29:BY29) -> 0 | BZ29: Yes | CA29: Yes
A30: =LOOKUP(H30,'Letter grades'!$A$1:$B$6) -> C | B30: =RANK(H30,H:H) -> 26 | C30: Sarah | D30: McBride | E30: DE-AL | F30: =((COUNTIF($J30:$BP30,"Sponsor")+COUNTIF($J30:$BP30, "Not sponsoring (correct)"))/(COUNTIF($J30:$BP30,"Sponsor")+COUNTIF($J30:$BP30,"Not sponsoring")+COUNTIF($J30:$BP30, "Not sponsoring (correct)")+COUNTIF($J30:$BP30, "Sponsor (incorrect)"))) -> 0.33333333 | G30: =(COUNTIF($K30:$BP30,"No")+COUNTIF($K30:$BP30,"Yes (correct)")+(COUNTIF($K30:$BP30,"Present")*0.5))/(COUNTIF($K30:$BP30,"Yes")+COUNTIF($K30:$BP30,"No")+COUNTIF($K30:$BP30,"Yes (correct)")+COUNTIF($K30:$BP30,"No (incorrect)")+COUNTIF($K30:$BP30,"Present")) -> 0.77777778 | H30: =((F30*(1/3))+(G30*(2/3))) -> 0.62962963 | I30: J Street | J30: Sponsor | K30: Sponsor | L30: Not sponsoring | M30: Not sponsoring | N30: Not sponsoring | O30: Sponsor (incorrect) | P30: No | Q30: No | R30: Yes (correct) | S30: No | T30: No | U30: No | V30: Not voting | W30: Not voting | X30: No (incorrect) | Y30: Yes | Z30: No | AA30: Not elected | AB30: Not elected | AC30: Not elected | AD30: Not elected | AE30: Not elected | AF30: Not elected | AG30: Not elected | AH30: Not elected | AI30: Not elected | AJ30: Not elected | AK30: Not elected | AL30: Not elected | AM30: Not elected | AN30: Not elected | AO30: Not elected | AP30: Not elected | AQ30: Not elected | AR30: Not elected | AS30: Not elected | AT30: Not elected | AU30: Not elected | AV30: Not elected | AW30: Not elected | AX30: Not elected | AY30: Not elected | AZ30: Not elected | BA30: Not elected | BB30: Not elected | BC30: Not elected | BD30: Not elected | BE30: Not elected | BF30: Not elected | BG30: Not elected | BH30: Not elected | BI30: Not elected | BJ30: Not elected | BK30: Not elected | BL30: Not elected | BM30: Not elected | BN30: Not elected | BO30: Not elected | BP30: Not elected | BQ30: Signatory | BR30: Signatory | BS30: Signatory | BU30: =SUM(BV30:BY30) -> 54240 | BV30: 54240 | CC30: Yes
A31: =LOOKUP(H31,'Letter grades'!$A$1:$B$6) -> C | B31: =RANK(H31,H:H) -> 27 | C31: Chellie | D31: Pingree | E31: ME-01 | F31: =((COUNTIF($J31:$BP31,"Sponsor")+COUNTIF($J31:$BP31, "Not sponsoring (correct)"))/(COUNTIF($J31:$BP31,"Sponsor")+COUNTIF($J31:$BP31,"Not sponsoring")+COUNTIF($J31:$BP31, "Not sponsoring (correct)")+COUNTIF($J31:$BP31, "Sponsor (incorrect)"))) -> 0.83333333 | G31: =(COUNTIF($K31:$BP31,"No")+COUNTIF($K31:$BP31,"Yes (correct)")+(COUNTIF($K31:$BP31,"Present")*0.5))/(COUNTIF($K31:$BP31,"Yes")+COUNTIF($K31:$BP31,"No")+COUNTIF($K31:$BP31,"Yes (correct)")+COUNTIF($K31:$BP31,"No (incorrect)")+COUNTIF($K31:$BP31,"Present")) -> 0.51020408 | H31: =((F31*(1/3))+(G31*(2/3))) -> 0.61791383 | I31: J Street | J31: Sponsor | K31: Sponsor | L31: Sponsor | M31: Sponsor | N31: Not sponsoring | O31: Not sponsoring (correct) | P31: No | Q31: No | R31: Yes (correct) | S31: No | T31: Yes | U31: Yes | V31: Not on committee | W31: Not on committee | X31: No (incorrect) | Y31: Not voting | Z31: Not voting | AA31: No | AB31: No | AC31: Yes | AD31: No | AE31: No | AF31: No | AG31: No | AH31: No | AI31: No | AJ31: No | AK31: No | AL31: Yes | AM31: No | AN31: Yes | AO31: Yes | AP31: Yes | AQ31: Yes | AR31: No | AS31: Yes | AT31: No | AU31: No | AV31: Present | AW31: Yes | AX31: Yes | AY31: No | AZ31: No | BA31: Yes | BB31: No | BC31: Yes | BD31: Yes | BE31: No | BF31: Yes | BG31: Yes | BH31: Yes | BI31: Yes | BJ31: Yes | BK31: Yes | BL31: Yes | BM31: Yes | BN31: No | BO31: No | BP31: Present | BQ31: Non-signatory | BR31: Non-signatory | BS31: Non-signatory | BU31: =SUM(BV31:BY31) -> 0 | CA31: Yes
A32: =LOOKUP(H32,'Letter grades'!$A$1:$B$6) -> C | B32: =RANK(H32,H:H) -> 28 | C32: Jonathan | D32: Jackson | E32: IL-01 | F32: =((COUNTIF($J32:$BP32,"Sponsor")+COUNTIF($J32:$BP32, "Not sponsoring (correct)"))/(COUNTIF($J32:$BP32,"Sponsor")+COUNTIF($J32:$BP32,"Not sponsoring")+COUNTIF($J32:$BP32, "Not sponsoring (correct)")+COUNTIF($J32:$BP32, "Sponsor (incorrect)"))) -> 0.5 | G32: =(COUNTIF($K32:$BP32,"No")+COUNTIF($K32:$BP32,"Yes (correct)")+(COUNTIF($K32:$BP32,"Present")*0.5))/(COUNTIF($K32:$BP32,"Yes")+COUNTIF($K32:$BP32,"No")+COUNTIF($K32:$BP32,"Yes (correct)")+COUNTIF($K32:$BP32,"No (incorrect)")+COUNTIF($K32:$BP32,"Present")) -> 0.67045455 | H32: =((F32*(1/3))+(G32*(2/3))) -> 0.61363636 | I32: J Street | J32: Sponsor | K32: Sponsor | L32: Sponsor | M32: Not sponsoring | N32: Not sponsoring | O32: Sponsor (incorrect) | P32: No | Q32: No | R32: Yes (correct) | S32: No | T32: No | U32: No | V32: Yes (correct) | W32: Yes (correct) | X32: No (incorrect) | Y32: Yes | Z32: No | AA32: No | AB32: No | AC32: Yes | AD32: No | AE32: No | AF32: Yes | AG32: No | AH32: No | AI32: No | AJ32: No | AK32: No | AL32: No | AM32: No | AN32: Yes | AO32: Yes | AP32: No | AQ32: Yes | AR32: No | AS32: Yes | AT32: No | AU32: No | AV32: Present | AW32: Yes | AX32: Yes | AY32: No | AZ32: No | BA32: No | BB32: No | BC32: No | BD32: Yes | BE32: Yes | BF32: Not voting | BG32: Yes | BH32: Yes | BI32: Not elected | BJ32: Not elected | BK32: Not elected | BL32: Not elected | BM32: Not elected | BN32: Not elected | BO32: Not elected | BP32: Not elected | BQ32: Non-signatory | BR32: Non-signatory | BS32: Non-signatory | BU32: =SUM(BV32:BY32) -> 20800 | BV32: 20800
A33: =LOOKUP(H33,'Letter grades'!$A$1:$B$6) -> C | B33: =RANK(H33,H:H) -> 29 | C33: Yassamin | D33: Ansari | E33: AZ-03 | F33: =((COUNTIF($J33:$BP33,"Sponsor")+COUNTIF($J33:$BP33, "Not sponsoring (correct)"))/(COUNTIF($J33:$BP33,"Sponsor")+COUNTIF($J33:$BP33,"Not sponsoring")+COUNTIF($J33:$BP33, "Not sponsoring (correct)")+COUNTIF($J33:$BP33, "Sponsor (incorrect)"))) -> 0.5 | G33: =(COUNTIF($K33:$BP33,"No")+COUNTIF($K33:$BP33,"Yes (correct)")+(COUNTIF($K33:$BP33,"Present")*0.5))/(COUNTIF($K33:$BP33,"Yes")+COUNTIF($K33:$BP33,"No")+COUNTIF($K33:$BP33,"Yes (correct)")+COUNTIF($K33:$BP33,"No (incorrect)")+COUNTIF($K33:$BP33,"Present")) -> 0.66666667 | H33: =((F33*(1/3))+(G33*(2/3))) -> 0.61111111 | J33: Sponsor | K33: Not sponsoring | L33: Sponsor | M33: Not sponsoring | N33: Not sponsoring | O33: Not sponsoring (correct) | P33: No | Q33: No | R33: Yes (correct) | S33: No | T33: No | U33: No | V33: Not on committee | W33: Not on committee | X33: No (incorrect) | Y33: Yes | Z33: Yes | AA33: Not elected | AB33: Not elected | AC33: Not elected | AD33: Not elected | AE33: Not elected | AF33: Not elected | AG33: Not elected | AH33: Not elected | AI33: Not elected | AJ33: Not elected | AK33: Not elected | AL33: Not elected | AM33: Not elected | AN33: Not elected | AO33: Not elected | AP33: Not elected | AQ33: Not elected | AR33: Not elected | AS33: Not elected | AT33: Not elected | AU33: Not elected | AV33: Not elected | AW33: Not elected | AX33: Not elected | AY33: Not elected | AZ33: Not elected | BA33: Not elected | BB33: Not elected | BC33: Not elected | BD33: Not elected | BE33: Not elected | BF33: Not elected | BG33: Not elected | BH33: Not elected | BI33: Not elected | BJ33: Not elected | BK33: Not elected | BL33: Not elected | BM33: Not elected | BN33: Not elected | BO33: Not elected | BP33: Not elected | BQ33: Non-signatory | BR33: Not elected | BS33: Not elected
A34: =LOOKUP(H34,'Letter grades'!$A$1:$B$6) -> C | B34: =RANK(H34,H:H) -> 30 | C34: Joaquin | D34: Castro | E34: TX-20 | F34: =((COUNTIF($J34:$BP34,"Sponsor")+COUNTIF($J34:$BP34, "Not sponsoring (correct)"))/(COUNTIF($J34:$BP34,"Sponsor")+COUNTIF($J34:$BP34,"Not sponsoring")+COUNTIF($J34:$BP34, "Not sponsoring (correct)")+COUNTIF($J34:$BP34, "Sponsor (incorrect)"))) -> 0.66666667 | G34: =(COUNTIF($K34:$BP34,"No")+COUNTIF($K34:$BP34,"Yes (correct)")+(COUNTIF($K34:$BP34,"Present")*0.5))/(COUNTIF($K34:$BP34,"Yes")+COUNTIF($K34:$BP34,"No")+COUNTIF($K34:$BP34,"Yes (correct)")+COUNTIF($K34:$BP34,"No (incorrect)")+COUNTIF($K34:$BP34,"Present")) -> 0.57142857 | H34: =((F34*(1/3))+(G34*(2/3))) -> 0.6031746 | I34: J Street | J34: Sponsor | K34: Sponsor | L34: Sponsor | M34: Not sponsoring | N34: Not sponsoring | O34: Not sponsoring (correct) | P34: No | Q34: No | R34: Yes (correct) | S34: No | T34: No | U34: No | V34: Yes (correct) | W34: Yes (correct) | X34: No (incorrect) | Y34: Yes | Z34: No | AA34: No | AB34: No | AC34: Yes | AD34: No | AE34: No | AF34: No | AG34: No | AH34: No | AI34: No | AJ34: No | AK34: Not voting | AL34: Yes | AM34: Not voting | AN34: Yes | AO34: Yes | AP34: No | AQ34: Yes | AR34: No | AS34: Yes | AT34: No | AU34: No | AV34: Present | AW34: Yes | AX34: Yes | AY34: Yes | AZ34: No | BA34: Not voting | BB34: No | BC34: No | BD34: Present | BE34: No | BF34: Yes | BG34: Yes | BH34: Yes | BI34: Yes | BJ34: Yes | BK34: Yes | BL34: Yes | BM34: Yes | BN34: Yes | BO34: No | BP34: Not elected | BQ34: Non-signatory | BR34: Non-signatory | BS34: Non-signatory | BU34: =SUM(BV34:BY34) -> 0 | CA34: Yes
A35: =LOOKUP(H35,'Letter grades'!$A$1:$B$6) -> D | B35: =RANK(H35,H:H) -> 31 | C35: Mark | D35: DeSaulnier | E35: CA-10 | F35: =((COUNTIF($J35:$BP35,"Sponsor")+COUNTIF($J35:$BP35, "Not sponsoring (correct)"))/(COUNTIF($J35:$BP35,"Sponsor")+COUNTIF($J35:$BP35,"Not sponsoring")+COUNTIF($J35:$BP35, "Not sponsoring (correct)")+COUNTIF($J35:$BP35, "Sponsor (incorrect)"))) -> 0.66666667 | G35: =(COUNTIF($K35:$BP35,"No")+COUNTIF($K35:$BP35,"Yes (correct)")+(COUNTIF($K35:$BP35,"Present")*0.5))/(COUNTIF($K35:$BP35,"Yes")+COUNTIF($K35:$BP35,"No")+COUNTIF($K35:$BP35,"Yes (correct)")+COUNTIF($K35:$BP35,"No (incorrect)")+COUNTIF($K35:$BP35,"Present")) -> 0.55208333 | H35: =((F35*(1/3))+(G35*(2/3))) -> 0.59027778 | I35: J Street | J35: Sponsor | K35: Sponsor | L35: Sponsor | M35: Not sponsoring | N35: Not sponsoring | O35: Not sponsoring (correct) | P35: No | Q35: No | R35: Yes (correct) | S35: No | T35: Yes | U35: No | V35: Not on committee | W35: Not on committee | X35: No (incorrect) | Y35: Yes | Z35: No | AA35: No | AB35: No | AC35: Yes | AD35: No | AE35: No | AF35: No | AG35: No | AH35: No | AI35: No | AJ35: No | AK35: No | AL35: Yes | AM35: No | AN35: Yes | AO35: Yes | AP35: Yes | AQ35: Yes | AR35: No | AS35: Yes | AT35: No | AU35: No | AV35: Present | AW35: Yes | AX35: Yes | AY35: Yes | AZ35: No | BA35: Not voting | BB35: Not voting | BC35: No | BD35: Yes | BE35: No | BF35: Yes | BG35: Yes | BH35: No | BI35: No | BJ35: Yes | BK35: Yes | BL35: Yes | BM35: Yes | BN35: Yes | BO35: No | BP35: Not elected | BQ35: Non-signatory | BR35: Non-signatory | BS35: Non-signatory | BU35: =SUM(BV35:BY35) -> 0 | CA35: Yes
A36: =LOOKUP(H36,'Letter grades'!$A$1:$B$6) -> D | B36: =RANK(H36,H:H) -> 32 | C36: Maxine | D36: Waters | E36: CA-43 | F36: =((COUNTIF($J36:$BP36,"Sponsor")+COUNTIF($J36:$BP36, "Not sponsoring (correct)"))/(COUNTIF($J36:$BP36,"Sponsor")+COUNTIF($J36:$BP36,"Not sponsoring")+COUNTIF($J36:$BP36, "Not sponsoring (correct)")+COUNTIF($J36:$BP36, "Sponsor (incorrect)"))) -> 0.66666667 | G36: =(COUNTIF($K36:$BP36,"No")+COUNTIF($K36:$BP36,"Yes (correct)")+(COUNTIF($K36:$BP36,"Present")*0.5))/(COUNTIF($K36:$BP36,"Yes")+COUNTIF($K36:$BP36,"No")+COUNTIF($K36:$BP36,"Yes (correct)")+COUNTIF($K36:$BP36,"No (incorrect)")+COUNTIF($K36:$BP36,"Present")) -> 0.54 | H36: =((F36*(1/3))+(G36*(2/3))) -> 0.58222222 | J36: Sponsor | K36: Sponsor | L36: Sponsor | M36: Not sponsoring | N36: Not sponsoring | O36: Not sponsoring (correct) | P36: No | Q36: No | R36: Yes (correct) | S36: No | T36: Yes | U36: No | V36: Not on committee | W36: Not on committee | X36: No (incorrect) | Y36: Yes | Z36: No | AA36: No | AB36: No | AC36: Yes | AD36: No | AE36: No | AF36: No | AG36: No | AH36: No | AI36: No | AJ36: No | AK36: No | AL36: Yes | AM36: No | AN36: Yes | AO36: Not voting | AP36: Yes | AQ36: Yes | AR36: No | AS36: Yes | AT36: No | AU36: No | AV36: Present | AW36: Yes | AX36: Yes | AY36: Yes | AZ36: No | BA36: No | BB36: No | BC36: No | BD36: Yes | BE36: No | BF36: Yes | BG36: Yes | BH36: Yes | BI36: Yes | BJ36: Yes | BK36: Yes | BL36: Yes | BM36: Yes | BN36: Yes | BO36: No | BP36: Present | BQ36: Non-signatory | BR36: Non-signatory | BS36: Non-signatory | BU36: =SUM(BV36:BY36) -> 0
A37: =LOOKUP(H37,'Letter grades'!$A$1:$B$6) -> D | B37: =RANK(H37,H:H) -> 33 | C37: Valerie | D37: Foushee | E37: NC-04 | F37: =((COUNTIF($J37:$BP37,"Sponsor")+COUNTIF($J37:$BP37, "Not sponsoring (correct)"))/(COUNTIF($J37:$BP37,"Sponsor")+COUNTIF($J37:$BP37,"Not sponsoring")+COUNTIF($J37:$BP37, "Not sponsoring (correct)")+COUNTIF($J37:$BP37, "Sponsor (incorrect)"))) -> 0.66666667 | G37: =(COUNTIF($K37:$BP37,"No")+COUNTIF($K37:$BP37,"Yes (correct)")+(COUNTIF($K37:$BP37,"Present")*0.5))/(COUNTIF($K37:$BP37,"Yes")+COUNTIF($K37:$BP37,"No")+COUNTIF($K37:$BP37,"Yes (correct)")+COUNTIF($K37:$BP37,"No (incorrect)")+COUNTIF($K37:$BP37,"Present")) -> 0.525 | H37: =((F37*(1/3))+(G37*(2/3))) -> 0.57222222 | J37: Sponsor | K37: Sponsor | L37: Sponsor | M37: Not sponsoring | N37: Not sponsoring | O37: Not sponsoring (correct) | P37: No | Q37: No | R37: Yes (correct) | S37: No | T37: No | U37: No | V37: Not on committee | W37: Not on committee | X37: No (incorrect) | Y37: Not voting | Z37: No | AA37: No | AB37: Not voting | AC37: Yes | AD37: No | AE37: No | AF37: No | AG37: No | AH37: No | AI37: No | AJ37: Yes | AK37: Yes | AL37: Yes | AM37: No | AN37: Yes | AO37: Yes | AP37: Yes | AQ37: Yes | AR37: No | AS37: Yes | AT37: No | AU37: No | AV37: Not voting | AW37: Yes | AX37: Yes | AY37: Yes | AZ37: No | BA37: Yes | BB37: No | BC37: No | BD37: Yes | BE37: Yes | BF37: Yes | BG37: Yes | BH37: Yes | BI37: Not elected | BJ37: Not elected | BK37: Not elected | BL37: Not elected | BM37: Not elected | BN37: Not elected | BO37: Not elected | BP37: Not elected | BQ37: Non-signatory | BR37: Non-signatory | BS37: Non-signatory | BU37: =SUM(BV37:BY37) -> 2891619 | BV37: 471294 | BW37: 2128194 | BX37: =2000 -> 2000 | BY37: 290131 | CB37: Yes | CC37: Yes
A38: =LOOKUP(H38,'Letter grades'!$A$1:$B$6) -> D | B38: =RANK(H38,H:H) -> 34 | C38: Jill | D38: Tokuda | E38: HI-02 | F38: =((COUNTIF($J38:$BP38,"Sponsor")+COUNTIF($J38:$BP38, "Not sponsoring (correct)"))/(COUNTIF($J38:$BP38,"Sponsor")+COUNTIF($J38:$BP38,"Not sponsoring")+COUNTIF($J38:$BP38, "Not sponsoring (correct)")+COUNTIF($J38:$BP38, "Sponsor (incorrect)"))) -> 0.66666667 | G38: =(COUNTIF($K38:$BP38,"No")+COUNTIF($K38:$BP38,"Yes (correct)")+(COUNTIF($K38:$BP38,"Present")*0.5))/(COUNTIF($K38:$BP38,"Yes")+COUNTIF($K38:$BP38,"No")+COUNTIF($K38:$BP38,"Yes (correct)")+COUNTIF($K38:$BP38,"No (incorrect)")+COUNTIF($K38:$BP38,"Present")) -> 0.52325581 | H38: =((F38*(1/3))+(G38*(2/3))) -> 0.57105943 | I38: J Street | J38: Sponsor | K38: Sponsor | L38: Sponsor | M38: Not sponsoring | N38: Not sponsoring | O38: Not sponsoring (correct) | P38: No | Q38: No | R38: Yes (correct) | S38: No | T38: Yes | U38: Yes | V38: Not on committee | W38: Not on committee | X38: No (incorrect) | Y38: Yes | Z38: No | AA38: No | AB38: No | AC38: Yes | AD38: No | AE38: No | AF38: No | AG38: No | AH38: No | AI38: No | AJ38: No | AK38: Yes | AL38: Yes | AM38: No | AN38: Yes | AO38: Yes | AP38: Yes | AQ38: Yes | AR38: No | AS38: Yes | AT38: No | AU38: No | AV38: Present | AW38: Yes | AX38: Yes | AY38: No | AZ38: No | BA38: Yes | BB38: No | BC38: No | BD38: Yes | BE38: Yes | BF38: Yes | BG38: Yes | BH38: Yes | BI38: Not elected | BJ38: Not elected | BK38: Not elected | BL38: Not elected | BM38: Not elected | BN38: Not elected | BO38: Not elected | BP38: Not elected | BQ38: Non-signatory | BR38: Non-signatory | BS38: Signatory | BU38: =SUM(BV38:BY38) -> 18500 | BV38: 18500
A39: =LOOKUP(H39,'Letter grades'!$A$1:$B$6) -> D | B39: =RANK(H39,H:H) -> 35 | C39: Mark | D39: Takano | E39: CA-39 | F39: =((COUNTIF($J39:$BP39,"Sponsor")+COUNTIF($J39:$BP39, "Not sponsoring (correct)"))/(COUNTIF($J39:$BP39,"Sponsor")+COUNTIF($J39:$BP39,"Not sponsoring")+COUNTIF($J39:$BP39, "Not sponsoring (correct)")+COUNTIF($J39:$BP39, "Sponsor (incorrect)"))) -> 0.66666667 | G39: =(COUNTIF($K39:$BP39,"No")+COUNTIF($K39:$BP39,"Yes (correct)")+(COUNTIF($K39:$BP39,"Present")*0.5))/(COUNTIF($K39:$BP39,"Yes")+COUNTIF($K39:$BP39,"No")+COUNTIF($K39:$BP39,"Yes (correct)")+COUNTIF($K39:$BP39,"No (incorrect)")+COUNTIF($K39:$BP39,"Present")) -> 0.52040816 | H39: =((F39*(1/3))+(G39*(2/3))) -> 0.569161 | I39: J Street | J39: Sponsor | K39: Sponsor | L39: Sponsor | M39: Not sponsoring | N39: Not sponsoring | O39: Not sponsoring (correct) | P39: No | Q39: No | R39: Yes (correct) | S39: No | T39: No | U39: No | V39: Not on committee | W39: Not on committee | X39: No (incorrect) | Y39: Yes | Z39: No | AA39: No | AB39: No | AC39: Yes | AD39: No | AE39: Not voting | AF39: No | AG39: No | AH39: No | AI39: No | AJ39: No | AK39: Yes | AL39: Yes | AM39: Yes | AN39: Yes | AO39: Yes | AP39: Yes | AQ39: Yes | AR39: No | AS39: Yes | AT39: No | AU39: No | AV39: Present | AW39: Yes | AX39: Yes | AY39: No | AZ39: No | BA39: No | BB39: No | BC39: No | BD39: Yes | BE39: Yes | BF39: Yes | BG39: Yes | BH39: Yes | BI39: No | BJ39: Yes | BK39: Yes | BL39: Yes | BM39: Yes | BN39: Yes | BO39: No | BP39: Not elected | BQ39: Non-signatory | BR39: Non-signatory | BS39: Non-signatory | BU39: =SUM(BV39:BY39) -> 0 | CA39: Yes
A40: =LOOKUP(H40,'Letter grades'!$A$1:$B$6) -> D | B40: =RANK(H40,H:H) -> 36 | C40: Judy | D40: Chu | E40: CA-28 | F40: =((COUNTIF($J40:$BP40,"Sponsor")+COUNTIF($J40:$BP40, "Not sponsoring (correct)"))/(COUNTIF($J40:$BP40,"Sponsor")+COUNTIF($J40:$BP40,"Not sponsoring")+COUNTIF($J40:$BP40, "Not sponsoring (correct)")+COUNTIF($J40:$BP40, "Sponsor (incorrect)"))) -> 0.66666667 | G40: =(COUNTIF($K40:$BP40,"No")+COUNTIF($K40:$BP40,"Yes (correct)")+(COUNTIF($K40:$BP40,"Present")*0.5))/(COUNTIF($K40:$BP40,"Yes")+COUNTIF($K40:$BP40,"No")+COUNTIF($K40:$BP40,"Yes (correct)")+COUNTIF($K40:$BP40,"No (incorrect)")+COUNTIF($K40:$BP40,"Present")) -> 0.5 | H40: =((F40*(1/3))+(G40*(2/3))) -> 0.55555556 | I40: J Street | J40: Sponsor | K40: Sponsor | L40: Sponsor | M40: Not sponsoring | N40: Not sponsoring | O40: Not sponsoring (correct) | P40: No | Q40: No | R40: Yes (correct) | S40: No | T40: Yes | U40: No | V40: Not on committee | W40: Not on committee | X40: No (incorrect) | Y40: Yes | Z40: Not voting | AA40: No | AB40: No | AC40: Yes | AD40: No | AE40: No | AF40: No | AG40: No | AH40: No | AI40: Yes | AJ40: No | AK40: Yes | AL40: Yes | AM40: No | AN40: Yes | AO40: Yes | AP40: Yes | AQ40: Not voting | AR40: No | AS40: Yes | AT40: No | AU40: No | AV40: Present | AW40: Yes | AX40: Yes | AY40: No | AZ40: No | BA40: Yes | BB40: No | BC40: No | BD40: Yes | BE40: No | BF40: Yes | BG40: Yes | BH40: Yes | BI40: No | BJ40: Yes | BK40: Yes | BL40: Yes | BM40: Yes | BN40: Yes | BO40: No | BP40: Yes | BQ40: Non-signatory | BR40: Non-signatory | BS40: Non-signatory | BU40: =SUM(BV40:BY40) -> 0 | CA40: Yes
A41: =LOOKUP(H41,'Letter grades'!$A$1:$B$6) -> D | B41: =RANK(H41,H:H) -> 36 | C41: Robert | D41: Garcia | E41: CA-42 | F41: =((COUNTIF($J41:$BP41,"Sponsor")+COUNTIF($J41:$BP41, "Not sponsoring (correct)"))/(COUNTIF($J41:$BP41,"Sponsor")+COUNTIF($J41:$BP41,"Not sponsoring")+COUNTIF($J41:$BP41, "Not sponsoring (correct)")+COUNTIF($J41:$BP41, "Sponsor (incorrect)"))) -> 0.66666667 | G41: =(COUNTIF($K41:$BP41,"No")+COUNTIF($K41:$BP41,"Yes (correct)")+(COUNTIF($K41:$BP41,"Present")*0.5))/(COUNTIF($K41:$BP41,"Yes")+COUNTIF($K41:$BP41,"No")+COUNTIF($K41:$BP41,"Yes (correct)")+COUNTIF($K41:$BP41,"No (incorrect)")+COUNTIF($K41:$BP41,"Present")) -> 0.5 | H41: =((F41*(1/3))+(G41*(2/3))) -> 0.55555556 | I41: J Street | J41: Sponsor | K41: Sponsor | L41: Sponsor | M41: Not sponsoring | N41: Not sponsoring | O41: Not sponsoring (correct) | P41: No | Q41: No | R41: Yes (correct) | S41: No | T41: No | U41: No | V41: Not on committee | W41: Not on committee | X41: No (incorrect) | Y41: Yes | Z41: No | AA41: No | AB41: No | AC41: Yes | AD41: No | AE41: No | AF41: Not voting | AG41: No | AH41: No | AI41: Not voting | AJ41: Yes | AK41: No | AL41: Yes | AM41: No | AN41: Yes | AO41: Yes | AP41: Yes | AQ41: Yes | AR41: No | AS41: Yes | AT41: Yes | AU41: Yes | AV41: Present | AW41: Yes | AX41: Yes | AY41: Yes | AZ41: No | BA41: Yes | BB41: No | BC41: No | BD41: Yes | BE41: No | BF41: Yes | BG41: Yes | BH41: Yes | BI41: Not elected | BJ41: Not elected | BK41: Not elected | BL41: Not elected | BM41: Not elected | BN41: Not elected | BO41: Not elected | BP41: Not elected | BQ41: Non-signatory | BR41: Non-signatory | BS41: Non-signatory | BU41: =SUM(BV41:BY41) -> 585594 | BV41: 68506 | BW41: 515088 | BX41: =2000 -> 2000 | CB41: Yes | CC41: Yes
A42: =LOOKUP(H42,'Letter grades'!$A$1:$B$6) -> D | B42: =RANK(H42,H:H) -> 38 | C42: Don | D42: Beyer | E42: VA-08 | F42: =((COUNTIF($J42:$BP42,"Sponsor")+COUNTIF($J42:$BP42, "Not sponsoring (correct)"))/(COUNTIF($J42:$BP42,"Sponsor")+COUNTIF($J42:$BP42,"Not sponsoring")+COUNTIF($J42:$BP42, "Not sponsoring (correct)")+COUNTIF($J42:$BP42, "Sponsor (incorrect)"))) -> 0.66666667 | G42: =(COUNTIF($K42:$BP42,"No")+COUNTIF($K42:$BP42,"Yes (correct)")+(COUNTIF($K42:$BP42,"Present")*0.5))/(COUNTIF($K42:$BP42,"Yes")+COUNTIF($K42:$BP42,"No")+COUNTIF($K42:$BP42,"Yes (correct)")+COUNTIF($K42:$BP42,"No (incorrect)")+COUNTIF($K42:$BP42,"Present")) -> 0.48958333 | H42: =((F42*(1/3))+(G42*(2/3))) -> 0.54861111 | I42: J Street | J42: Sponsor | K42: Sponsor | L42: Sponsor | M42: Not sponsoring | N42: Not sponsoring | O42: Not sponsoring (correct) | P42: No | Q42: No | R42: Yes (correct) | S42: No | T42: No | U42: Yes | V42: Not on committee | W42: Not on committee | X42: No (incorrect) | Y42: Yes | Z42: No | AA42: Not voting | AB42: No | AC42: Not voting | AD42: No | AE42: No | AF42: No | AG42: No | AH42: No | AI42: No | AJ42: No | AK42: Yes | AL42: Yes | AM42: No | AN42: Yes | AO42: Yes | AP42: Yes | AQ42: Yes | AR42: No | AS42: Yes | AT42: No | AU42: No | AV42: Present | AW42: Yes | AX42: Yes | AY42: No | AZ42: No | BA42: Yes | BB42: No | BC42: Yes | BD42: Yes | BE42: No | BF42: Yes | BG42: Yes | BH42: Yes | BI42: Yes | BJ42: Yes | BK42: Yes | BL42: Yes | BM42: Yes | BN42: Yes | BO42: No | BP42: Not elected | BQ42: Non-signatory | BR42: Non-signatory | BS42: Non-signatory | BU42: =SUM(BV42:BY42) -> 0 | CA42: Yes
A43: =LOOKUP(H43,'Letter grades'!$A$1:$B$6) -> D | B43: =RANK(H43,H:H) -> 39 | C43: Jan | D43: Schakowsky | E43: IL-09 | F43: =((COUNTIF($J43:$BP43,"Sponsor")+COUNTIF($J43:$BP43, "Not sponsoring (correct)"))/(COUNTIF($J43:$BP43,"Sponsor")+COUNTIF($J43:$BP43,"Not sponsoring")+COUNTIF($J43:$BP43, "Not sponsoring (correct)")+COUNTIF($J43:$BP43, "Sponsor (incorrect)"))) -> 0.66666667 | G43: =(COUNTIF($K43:$BP43,"No")+COUNTIF($K43:$BP43,"Yes (correct)")+(COUNTIF($K43:$BP43,"Present")*0.5))/(COUNTIF($K43:$BP43,"Yes")+COUNTIF($K43:$BP43,"No")+COUNTIF($K43:$BP43,"Yes (correct)")+COUNTIF($K43:$BP43,"No (incorrect)")+COUNTIF($K43:$BP43,"Present")) -> 0.48039216 | H43: =((F43*(1/3))+(G43*(2/3))) -> 0.54248366 | I43: J Street | J43: Sponsor | K43: Sponsor | L43: Sponsor | M43: Not sponsoring | N43: Not sponsoring | O43: Not sponsoring (correct) | P43: No | Q43: No | R43: Yes (correct) | S43: No | T43: Yes | U43: No | V43: Not on committee | W43: Not on committee | X43: No (incorrect) | Y43: Yes | Z43: No | AA43: No | AB43: No | AC43: Yes | AD43: No | AE43: No | AF43: No | AG43: No | AH43: No | AI43: No | AJ43: Yes | AK43: Yes | AL43: Yes | AM43: No | AN43: Yes | AO43: No | AP43: Yes | AQ43: Yes | AR43: No | AS43: Yes | AT43: No | AU43: Yes | AV43: Present | AW43: Yes | AX43: Yes | AY43: No | AZ43: No | BA43: Yes | BB43: No | BC43: No | BD43: Yes | BE43: Yes | BF43: Yes | BG43: Yes | BH43: Yes | BI43: No | BJ43: Yes | BK43: Yes | BL43: Yes | BM43: Yes | BN43: Yes | BO43: No | BP43: Yes | BQ43: Non-signatory | BR43: Non-signatory | BS43: Non-signatory | BU43: =SUM(BV43:BY43) -> 0 | CA43: Yes
A44: =LOOKUP(H44,'Letter grades'!$A$1:$B$6) -> D | B44: =RANK(H44,H:H) -> 40 | C44: Lloyd | D44: Doggett | E44: TX-37 | F44: =((COUNTIF($J44:$BP44,"Sponsor")+COUNTIF($J44:$BP44, "Not sponsoring (correct)"))/(COUNTIF($J44:$BP44,"Sponsor")+COUNTIF($J44:$BP44,"Not sponsoring")+COUNTIF($J44:$BP44, "Not sponsoring (correct)")+COUNTIF($J44:$BP44, "Sponsor (incorrect)"))) -> 0.66666667 | G44: =(COUNTIF($K44:$BP44,"No")+COUNTIF($K44:$BP44,"Yes (correct)")+(COUNTIF($K44:$BP44,"Present")*0.5))/(COUNTIF($K44:$BP44,"Yes")+COUNTIF($K44:$BP44,"No")+COUNTIF($K44:$BP44,"Yes (correct)")+COUNTIF($K44:$BP44,"No (incorrect)")+COUNTIF($K44:$BP44,"Present")) -> 0.47959184 | H44: =((F44*(1/3))+(G44*(2/3))) -> 0.54195011 | I44: J Street | J44: Sponsor | K44: Sponsor | L44: Sponsor | M44: Not sponsoring | N44: Not sponsoring | O44: Not sponsoring (correct) | P44: No | Q44: No | R44: Yes (correct) | S44: No | T44: No | U44: No | V44: Not on committee | W44: Not on committee | X44: No (incorrect) | Y44: Yes | Z44: No | AA44: No | AB44: No | AC44: Yes | AD44: No | AE44: No | AF44: No | AG44: Not voting | AH44: No | AI44: No | AJ44: No | AK44: No | AL44: Yes | AM44: Yes | AN44: Yes | AO44: Not voting | AP44: Yes | AQ44: Yes | AR44: No | AS44: Yes | AT44: No | AU44: No | AV44: Present | AW44: Yes | AX44: Yes | AY44: Yes | AZ44: No | BA44: Yes | BB44: No | BC44: Yes | BD44: Yes | BE44: No | BF44: Yes | BG44: Yes | BH44: Yes | BI44: Yes | BJ44: Yes | BK44: Yes | BL44: Yes | BM44: Yes | BN44: Yes | BO44: No | BP44: Yes | BQ44: Non-signatory | BR44: Signatory | BS44: Non-signatory | BU44: =SUM(BV44:BY44) -> 0 | CA44: Yes
A45: =LOOKUP(H45,'Letter grades'!$A$1:$B$6) -> D | B45: =RANK(H45,H:H) -> 41 | C45: Jared | D45: Huffman | E45: CA-02 | F45: =((COUNTIF($J45:$BP45,"Sponsor")+COUNTIF($J45:$BP45, "Not sponsoring (correct)"))/(COUNTIF($J45:$BP45,"Sponsor")+COUNTIF($J45:$BP45,"Not sponsoring")+COUNTIF($J45:$BP45, "Not sponsoring (correct)")+COUNTIF($J45:$BP45, "Sponsor (incorrect)"))) -> 0.66666667 | G45: =(COUNTIF($K45:$BP45,"No")+COUNTIF($K45:$BP45,"Yes (correct)")+(COUNTIF($K45:$BP45,"Present")*0.5))/(COUNTIF($K45:$BP45,"Yes")+COUNTIF($K45:$BP45,"No")+COUNTIF($K45:$BP45,"Yes (correct)")+COUNTIF($K45:$BP45,"No (incorrect)")+COUNTIF($K45:$BP45,"Present")) -> 0.47916667 | H45: =((F45*(1/3))+(G45*(2/3))) -> 0.54166667 | I45: J Street | J45: Sponsor | K45: Sponsor | L45: Sponsor | M45: Not sponsoring | N45: Not sponsoring | O45: Not sponsoring (correct) | P45: No | Q45: No | R45: Present | S45: No | T45: No | U45: No | V45: Not on committee | W45: Not on committee | X45: No (incorrect) | Y45: Not voting | Z45: No | AA45: No | AB45: No | AC45: Yes | AD45: No | AE45: No | AF45: No | AG45: No | AH45: No | AI45: Yes | AJ45: Yes | AK45: Yes | AL45: Yes | AM45: No | AN45: Yes | AO45: Not voting | AP45: Yes | AQ45: Yes | AR45: No | AS45: Yes | AT45: No | AU45: Yes | AV45: Yes | AW45: Yes | AX45: Yes | AY45: Yes | AZ45: No | BA45: Yes | BB45: No | BC45: No | BD45: Yes | BE45: No | BF45: Yes | BG45: Yes | BH45: No | BI45: Yes | BJ45: Yes | BK45: Yes | BL45: Yes | BM45: Yes | BN45: Present | BO45: No | BP45: Not elected | BQ45: Non-signatory | BR45: Signatory | BS45: Non-signatory | BU45: =SUM(BV45:BY45) -> 0 | CA45: Yes
A46: =LOOKUP(H46,'Letter grades'!$A$1:$B$6) -> D | B46: =RANK(H46,H:H) -> 42 | C46: Valerie | D46: Hoyle | E46: OR-04 | F46: =((COUNTIF($J46:$BP46,"Sponsor")+COUNTIF($J46:$BP46, "Not sponsoring (correct)"))/(COUNTIF($J46:$BP46,"Sponsor")+COUNTIF($J46:$BP46,"Not sponsoring")+COUNTIF($J46:$BP46, "Not sponsoring (correct)")+COUNTIF($J46:$BP46, "Sponsor (incorrect)"))) -> 0.66666667 | G46: =(COUNTIF($K46:$BP46,"No")+COUNTIF($K46:$BP46,"Yes (correct)")+(COUNTIF($K46:$BP46,"Present")*0.5))/(COUNTIF($K46:$BP46,"Yes")+COUNTIF($K46:$BP46,"No")+COUNTIF($K46:$BP46,"Yes (correct)")+COUNTIF($K46:$BP46,"No (incorrect)")+COUNTIF($K46:$BP46,"Present")) -> 0.47674419 | H46: =((F46*(1/3))+(G46*(2/3))) -> 0.54005168 | I46: J Street | J46: Sponsor | K46: Sponsor | L46: Sponsor | M46: Not sponsoring | N46: Not sponsoring | O46: Not sponsoring (correct) | P46: No | Q46: No | R46: Yes (correct) | S46: No | T46: No | U46: No | V46: Not on committee | W46: Not on committee | X46: No (incorrect) | Y46: Yes | Z46: No | AA46: No | AB46: No | AC46: Yes | AD46: No | AE46: No | AF46: No | AG46: No | AH46: No | AI46: No | AJ46: Yes | AK46: Yes | AL46: Yes | AM46: Yes | AN46: Yes | AO46: Yes | AP46: Yes | AQ46: Yes | AR46: No | AS46: Yes | AT46: No | AU46: Yes | AV46: Present | AW46: Yes | AX46: Yes | AY46: No | AZ46: No | BA46: Yes | BB46: No | BC46: Yes | BD46: Yes | BE46: Yes | BF46: Yes | BG46: Yes | BH46: Yes | BI46: Not elected | BJ46: Not elected | BK46: Not elected | BL46: Not elected | BM46: Not elected | BN46: Not elected | BO46: Not elected | BP46: Not elected | BQ46: Non-signatory | BR46: Non-signatory | BS46: Signatory | BU46: =SUM(BV46:BY46) -> 17170 | BV46: 15170 | BX46: =2000 -> 2000 | CB46: Yes
A47: =LOOKUP(H47,'Letter grades'!$A$1:$B$6) -> D | B47: =RANK(H47,H:H) -> 43 | C47: Sam | D47: Liccardo | E47: CA-16 | F47: =((COUNTIF($J47:$BP47,"Sponsor")+COUNTIF($J47:$BP47, "Not sponsoring (correct)"))/(COUNTIF($J47:$BP47,"Sponsor")+COUNTIF($J47:$BP47,"Not sponsoring")+COUNTIF($J47:$BP47, "Not sponsoring (correct)")+COUNTIF($J47:$BP47, "Sponsor (incorrect)"))) -> 0.5 | G47: =(COUNTIF($K47:$BP47,"No")+COUNTIF($K47:$BP47,"Yes (correct)")+(COUNTIF($K47:$BP47,"Present")*0.5))/(COUNTIF($K47:$BP47,"Yes")+COUNTIF($K47:$BP47,"No")+COUNTIF($K47:$BP47,"Yes (correct)")+COUNTIF($K47:$BP47,"No (incorrect)")+COUNTIF($K47:$BP47,"Present")) -> 0.55555556 | H47: =((F47*(1/3))+(G47*(2/3))) -> 0.53703704 | I47: J Street | J47: Sponsor | K47: Not sponsoring | L47: Sponsor | M47: Not sponsoring | N47: Not sponsoring | O47: Not sponsoring (correct) | P47: No | Q47: No | R47: No (incorrect) | S47: No | T47: Yes | U47: No | V47: Not on committee | W47: Not on committee | X47: No (incorrect) | Y47: Yes | Z47: No | AA47: Not elected | AB47: Not elected | AC47: Not elected | AD47: Not elected | AE47: Not elected | AF47: Not elected | AG47: Not elected | AH47: Not elected | AI47: Not elected | AJ47: Not elected | AK47: Not elected | AL47: Not elected | AM47: Not elected | AN47: Not elected | AO47: Not elected | AP47: Not elected | AQ47: Not elected | AR47: Not elected | AS47: Not elected | AT47: Not elected | AU47: Not elected | AV47: Not elected | AW47: Not elected | AX47: Not elected | AY47: Not elected | AZ47: Not elected | BA47: Not elected | BB47: Not elected | BC47: Not elected | BD47: Not elected | BE47: Not elected | BF47: Not elected | BG47: Not elected | BH47: Not elected | BI47: Not elected | BJ47: Not elected | BK47: Not elected | BL47: Not elected | BM47: Not elected | BN47: Not elected | BO47: Not elected | BP47: Not elected | BQ47: Non-signatory | BR47: Not elected | BS47: Not elected
A48: =LOOKUP(H48,'Letter grades'!$A$1:$B$6) -> D | B48: =RANK(H48,H:H) -> 43 | C48: Dave | D48: Min | E48: CA-47 | F48: =((COUNTIF($J48:$BP48,"Sponsor")+COUNTIF($J48:$BP48, "Not sponsoring (correct)"))/(COUNTIF($J48:$BP48,"Sponsor")+COUNTIF($J48:$BP48,"Not sponsoring")+COUNTIF($J48:$BP48, "Not sponsoring (correct)")+COUNTIF($J48:$BP48, "Sponsor (incorrect)"))) -> 0.5 | G48: =(COUNTIF($K48:$BP48,"No")+COUNTIF($K48:$BP48,"Yes (correct)")+(COUNTIF($K48:$BP48,"Present")*0.5))/(COUNTIF($K48:$BP48,"Yes")+COUNTIF($K48:$BP48,"No")+COUNTIF($K48:$BP48,"Yes (correct)")+COUNTIF($K48:$BP48,"No (incorrect)")+COUNTIF($K48:$BP48,"Present")) -> 0.55555556 | H48: =((F48*(1/3))+(G48*(2/3))) -> 0.53703704 | I48: J Street | J48: Sponsor | K48: Not sponsoring | L48: Sponsor | M48: Not sponsoring | N48: Not sponsoring | O48: Not sponsoring (correct) | P48: No | Q48: No | R48: Yes (correct) | S48: No | T48: Yes | U48: Yes | V48: Not on committee | W48: Not on committee | X48: No (incorrect) | Y48: Yes | Z48: No | AA48: Not elected | AB48: Not elected | AC48: Not elected | AD48: Not elected | AE48: Not elected | AF48: Not elected | AG48: Not elected | AH48: Not elected | AI48: Not elected | AJ48: Not elected | AK48: Not elected | AL48: Not elected | AM48: Not elected | AN48: Not elected | AO48: Not elected | AP48: Not elected | AQ48: Not elected | AR48: Not elected | AS48: Not elected | AT48: Not elected | AU48: Not elected | AV48: Not elected | AW48: Not elected | AX48: Not elected | AY48: Not elected | AZ48: Not elected | BA48: Not elected | BB48: Not elected | BC48: Not elected | BD48: Not elected | BE48: Not elected | BF48: Not elected | BG48: Not elected | BH48: Not elected | BI48: Not elected | BJ48: Not elected | BK48: Not elected | BL48: Not elected | BM48: Not elected | BN48: Not elected | BO48: Not elected | BP48: Not elected | BQ48: Non-signatory | BR48: Not elected | BS48: Not elected
A49: =LOOKUP(H49,'Letter grades'!$A$1:$B$6) -> D | B49: =RANK(H49,H:H) -> 43 | C49: Derek | D49: Tran | E49: CA-45 | F49: =((COUNTIF($J49:$BP49,"Sponsor")+COUNTIF($J49:$BP49, "Not sponsoring (correct)"))/(COUNTIF($J49:$BP49,"Sponsor")+COUNTIF($J49:$BP49,"Not sponsoring")+COUNTIF($J49:$BP49, "Not sponsoring (correct)")+COUNTIF($J49:$BP49, "Sponsor (incorrect)"))) -> 0.5 | G49: =(COUNTIF($K49:$BP49,"No")+COUNTIF($K49:$BP49,"Yes (correct)")+(COUNTIF($K49:$BP49,"Present")*0.5))/(COUNTIF($K49:$BP49,"Yes")+COUNTIF($K49:$BP49,"No")+COUNTIF($K49:$BP49,"Yes (correct)")+COUNTIF($K49:$BP49,"No (incorrect)")+COUNTIF($K49:$BP49,"Present")) -> 0.55555556 | H49: =((F49*(1/3))+(G49*(2/3))) -> 0.53703704 | I49: J Street | J49: Sponsor | K49: Not sponsoring | L49: Sponsor | M49: Not sponsoring | N49: Not sponsoring | O49: Not sponsoring (correct) | P49: No | Q49: No | R49: Yes (correct) | S49: No | T49: Yes | U49: Yes | V49: Not on committee | W49: Not on committee | X49: No (incorrect) | Y49: Yes | Z49: No | AA49: Not elected | AB49: Not elected | AC49: Not elected | AD49: Not elected | AE49: Not elected | AF49: Not elected | AG49: Not elected | AH49: Not elected | AI49: Not elected | AJ49: Not elected | AK49: Not elected | AL49: Not elected | AM49: Not elected | AN49: Not elected | AO49: Not elected | AP49: Not elected | AQ49: Not elected | AR49: Not elected | AS49: Not elected | AT49: Not elected | AU49: Not elected | AV49: Not elected | AW49: Not elected | AX49: Not elected | AY49: Not elected | AZ49: Not elected | BA49: Not elected | BB49: Not elected | BC49: Not elected | BD49: Not elected | BE49: Not elected | BF49: Not elected | BG49: Not elected | BH49: Not elected | BI49: Not elected | BJ49: Not elected | BK49: Not elected | BL49: Not elected | BM49: Not elected | BN49: Not elected | BO49: Not elected | BP49: Not elected | BQ49: Non-signatory | BR49: Not elected | BS49: Not elected
A50: =LOOKUP(H50,'Letter grades'!$A$1:$B$6) -> D | B50: =RANK(H50,H:H) -> 46 | C50: Gwen | D50: Moore | E50: WI-04 | F50: =((COUNTIF($J50:$BP50,"Sponsor")+COUNTIF($J50:$BP50, "Not sponsoring (correct)"))/(COUNTIF($J50:$BP50,"Sponsor")+COUNTIF($J50:$BP50,"Not sponsoring")+COUNTIF($J50:$BP50, "Not sponsoring (correct)")+COUNTIF($J50:$BP50, "Sponsor (incorrect)"))) -> 0.5 | G50: =(COUNTIF($K50:$BP50,"No")+COUNTIF($K50:$BP50,"Yes (correct)")+(COUNTIF($K50:$BP50,"Present")*0.5))/(COUNTIF($K50:$BP50,"Yes")+COUNTIF($K50:$BP50,"No")+COUNTIF($K50:$BP50,"Yes (correct)")+COUNTIF($K50:$BP50,"No (incorrect)")+COUNTIF($K50:$BP50,"Present")) -> 0.55102041 | H50: =((F50*(1/3))+(G50*(2/3))) -> 0.53401361 | I50: J Street | J50: Sponsor | K50: Sponsor | L50: Not sponsoring | M50: Not sponsoring | N50: Not sponsoring | O50: Not sponsoring (correct) | P50: No | Q50: No | R50: Yes (correct) | S50: No | T50: No | U50: No | V50: Not on committee | W50: Not on committee | X50: No (incorrect) | Y50: Yes | Z50: No | AA50: No | AB50: No | AC50: Yes | AD50: Yes | AE50: No | AF50: No | AG50: No | AH50: No | AI50: No | AJ50: Yes | AK50: Yes | AL50: Yes | AM50: No | AN50: Yes | AO50: Not voting | AP50: No | AQ50: Yes | AR50: No | AS50: Yes | AT50: No | AU50: Yes | AV50: Present | AW50: Not voting | AX50: Yes | AY50: No | AZ50: No | BA50: Yes | BB50: No | BC50: No | BD50: Yes | BE50: No | BF50: Yes | BG50: Yes | BH50: Yes | BI50: No | BJ50: Yes | BK50: Yes | BL50: Yes | BM50: Yes | BN50: No | BO50: No | BP50: Present | BQ50: Non-signatory | BR50: Non-signatory | BS50: Non-signatory | BU50: =SUM(BV50:BY50) -> 0 | CA50: Yes
A51: =LOOKUP(H51,'Letter grades'!$A$1:$B$6) -> D | B51: =RANK(H51,H:H) -> 47 | C51: Nanette | D51: Barragán | E51: CA-44 | F51: =((COUNTIF($J51:$BP51,"Sponsor")+COUNTIF($J51:$BP51, "Not sponsoring (correct)"))/(COUNTIF($J51:$BP51,"Sponsor")+COUNTIF($J51:$BP51,"Not sponsoring")+COUNTIF($J51:$BP51, "Not sponsoring (correct)")+COUNTIF($J51:$BP51, "Sponsor (incorrect)"))) -> 0.66666667 | G51: =(COUNTIF($K51:$BP51,"No")+COUNTIF($K51:$BP51,"Yes (correct)")+(COUNTIF($K51:$BP51,"Present")*0.5))/(COUNTIF($K51:$BP51,"Yes")+COUNTIF($K51:$BP51,"No")+COUNTIF($K51:$BP51,"Yes (correct)")+COUNTIF($K51:$BP51,"No (incorrect)")+COUNTIF($K51:$BP51,"Present")) -> 0.45918367 | H51: =((F51*(1/3))+(G51*(2/3))) -> 0.52834467 | J51: Sponsor | K51: Sponsor | L51: Sponsor | M51: Not sponsoring | N51: Not sponsoring | O51: Not sponsoring (correct) | P51: No | Q51: No | R51: Yes (correct) | S51: No | T51: Yes | U51: No | V51: Not on committee | W51: Not on committee | X51: No (incorrect) | Y51: Yes | Z51: No | AA51: No | AB51: No | AC51: Yes | AD51: No | AE51: No | AF51: No | AG51: No | AH51: No | AI51: Yes | AJ51: Yes | AK51: No | AL51: Yes | AM51: Yes | AN51: Yes | AO51: Not voting | AP51: Yes | AQ51: Yes | AR51: No | AS51: Yes | AT51: No | AU51: No | AV51: Present | AW51: Yes | AX51: Yes | AY51: No | AZ51: No | BA51: Yes | BB51: No | BC51: Yes | BD51: Yes | BE51: No | BF51: Yes | BG51: Yes | BH51: Yes | BI51: No | BJ51: Yes | BK51: Yes | BL51: Yes | BM51: Yes | BN51: Yes | BO51: Yes | BP51: Not elected | BQ51: Non-signatory | BR51: Non-signatory | BS51: Non-signatory | BU51: =SUM(BV51:BY51) -> 44441 | BV51: 44441 | CC51: Yes
A52: =LOOKUP(H52,'Letter grades'!$A$1:$B$6) -> D | B52: =RANK(H52,H:H) -> 47 | C52: Lauren | D52: Underwood | E52: IL-14 | F52: =((COUNTIF($J52:$BP52,"Sponsor")+COUNTIF($J52:$BP52, "Not sponsoring (correct)"))/(COUNTIF($J52:$BP52,"Sponsor")+COUNTIF($J52:$BP52,"Not sponsoring")+COUNTIF($J52:$BP52, "Not sponsoring (correct)")+COUNTIF($J52:$BP52, "Sponsor (incorrect)"))) -> 0.66666667 | G52: =(COUNTIF($K52:$BP52,"No")+COUNTIF($K52:$BP52,"Yes (correct)")+(COUNTIF($K52:$BP52,"Present")*0.5))/(COUNTIF($K52:$BP52,"Yes")+COUNTIF($K52:$BP52,"No")+COUNTIF($K52:$BP52,"Yes (correct)")+COUNTIF($K52:$BP52,"No (incorrect)")+COUNTIF($K52:$BP52,"Present")) -> 0.45918367 | H52: =((F52*(1/3))+(G52*(2/3))) -> 0.52834467 | J52: Sponsor | K52: Sponsor | L52: Sponsor | M52: Not sponsoring | N52: Not sponsoring | O52: Not sponsoring (correct) | P52: No | Q52: No | R52: Yes (correct) | S52: No | T52: Yes | U52: Yes | V52: Not on committee | W52: Not on committee | X52: No (incorrect) | Y52: Yes | Z52: No | AA52: No | AB52: No | AC52: Yes | AD52: No | AE52: No | AF52: No | AG52: No | AH52: No | AI52: No | AJ52: Yes | AK52: No | AL52: Yes | AM52: No | AN52: Yes | AO52: Yes | AP52: Yes | AQ52: Yes | AR52: No | AS52: Yes | AT52: No | AU52: Yes | AV52: Present | AW52: Yes | AX52: Yes | AY52: Yes | AZ52: No | BA52: No | BB52: No | BC52: No | BD52: Yes | BE52: No | BF52: Yes | BG52: Yes | BH52: Yes | BI52: Yes | BJ52: Yes | BK52: Yes | BL52: Yes | BM52: Yes | BN52: Yes | BO52: Not elected | BP52: Not elected | BQ52: Non-signatory | BR52: Non-signatory | BS52: Non-signatory | BU52: =SUM(BV52:BY52) -> 2000 | BX52: =2000 -> 2000
A53: =LOOKUP(H53,'Letter grades'!$A$1:$B$6) -> D | B53: =RANK(H53,H:H) -> 49 | C53: Danny | D53: Davis | E53: IL-07 | F53: =((COUNTIF($J53:$BP53,"Sponsor")+COUNTIF($J53:$BP53, "Not sponsoring (correct)"))/(COUNTIF($J53:$BP53,"Sponsor")+COUNTIF($J53:$BP53,"Not sponsoring")+COUNTIF($J53:$BP53, "Not sponsoring (correct)")+COUNTIF($J53:$BP53, "Sponsor (incorrect)"))) -> 0.66666667 | G53: =(COUNTIF($K53:$BP53,"No")+COUNTIF($K53:$BP53,"Yes (correct)")+(COUNTIF($K53:$BP53,"Present")*0.5))/(COUNTIF($K53:$BP53,"Yes")+COUNTIF($K53:$BP53,"No")+COUNTIF($K53:$BP53,"Yes (correct)")+COUNTIF($K53:$BP53,"No (incorrect)")+COUNTIF($K53:$BP53,"Present")) -> 0.45833333 | H53: =((F53*(1/3))+(G53*(2/3))) -> 0.52777778 | I53: J Street | J53: Sponsor | K53: Sponsor | L53: Sponsor | M53: Not sponsoring | N53: Not sponsoring | O53: Not sponsoring (correct) | P53: No | Q53: No | R53: Yes (correct) | S53: No | T53: Yes | U53: No | V53: Not on committee | W53: Not on committee | X53: No (incorrect) | Y53: Not voting | Z53: No | AA53: No | AB53: No | AC53: Yes | AD53: Not voting | AE53: No | AF53: No | AG53: No | AH53: Not voting | AI53: No | AJ53: Yes | AK53: No | AL53: Yes | AM53: No | AN53: Yes | AO53: Yes | AP53: Yes | AQ53: Yes | AR53: No | AS53: Yes | AT53: No | AU53: Yes | AV53: Present | AW53: Yes | AX53: Yes | AY53: Yes | AZ53: No | BA53: Yes | BB53: No | BC53: Yes | BD53: Yes | BE53: No | BF53: Yes | BG53: Yes | BH53: Yes | BI53: No | BJ53: Yes | BK53: Yes | BL53: Yes | BM53: Yes | BN53: Present | BO53: No | BP53: Yes | BQ53: Non-signatory | BR53: Signatory | BS53: Non-signatory | BU53: =SUM(BV53:BY53) -> 0 | CA53: Yes
A54: =LOOKUP(H54,'Letter grades'!$A$1:$B$6) -> D | B54: =RANK(H54,H:H) -> 50 | C54: Sara | D54: Jacobs | E54: CA-51 | F54: =((COUNTIF($J54:$BP54,"Sponsor")+COUNTIF($J54:$BP54, "Not sponsoring (correct)"))/(COUNTIF($J54:$BP54,"Sponsor")+COUNTIF($J54:$BP54,"Not sponsoring")+COUNTIF($J54:$BP54, "Not sponsoring (correct)")+COUNTIF($J54:$BP54, "Sponsor (incorrect)"))) -> 0.5 | G54: =(COUNTIF($K54:$BP54,"No")+COUNTIF($K54:$BP54,"Yes (correct)")+(COUNTIF($K54:$BP54,"Present")*0.5))/(COUNTIF($K54:$BP54,"Yes")+COUNTIF($K54:$BP54,"No")+COUNTIF($K54:$BP54,"Yes (correct)")+COUNTIF($K54:$BP54,"No (incorrect)")+COUNTIF($K54:$BP54,"Present")) -> 0.54081633 | H54: =((F54*(1/3))+(G54*(2/3))) -> 0.52721088 | I54: J Street | J54: Not sponsoring | K54: Sponsor | L54: Sponsor | M54: Not sponsoring | N54: Not sponsoring | O54: Not sponsoring (correct) | P54: No | Q54: No | R54: Yes (correct) | S54: No | T54: No | U54: No | V54: Yes (correct) | W54: Yes (correct) | X54: No (incorrect) | Y54: Yes | Z54: No | AA54: No | AB54: No | AC54: Yes | AD54: No | AE54: No | AF54: No | AG54: No | AH54: No | AI54: No | AJ54: Yes | AK54: Yes | AL54: Yes | AM54: No | AN54: Yes | AO54: Yes | AP54: Yes | AQ54: Yes | AR54: No | AS54: Yes | AT54: No | AU54: Yes | AV54: Present | AW54: Yes | AX54: Yes | AY54: No | AZ54: No | BA54: Yes | BB54: No | BC54: No | BD54: Yes | BE54: No | BF54: Yes | BG54: Yes | BH54: Yes | BI54: Yes | BJ54: No | BK54: Yes | BL54: Yes | BM54: Not elected | BN54: Not elected | BO54: Not elected | BP54: Not elected | BQ54: Non-signatory | BR54: Non-signatory | BS54: Non-signatory | BU54: =SUM(BV54:BY54) -> -471343 | BX54: =-5000 -> -5000 | BY54: -466343 | CA54: Yes
A55: =LOOKUP(H55,'Letter grades'!$A$1:$B$6) -> D | B55: =RANK(H55,H:H) -> 51 | C55: Robin | D55: Kelly | E55: IL-02 | F55: =((COUNTIF($J55:$BP55,"Sponsor")+COUNTIF($J55:$BP55, "Not sponsoring (correct)"))/(COUNTIF($J55:$BP55,"Sponsor")+COUNTIF($J55:$BP55,"Not sponsoring")+COUNTIF($J55:$BP55, "Not sponsoring (correct)")+COUNTIF($J55:$BP55, "Sponsor (incorrect)"))) -> 0.66666667 | G55: =(COUNTIF($K55:$BP55,"No")+COUNTIF($K55:$BP55,"Yes (correct)")+(COUNTIF($K55:$BP55,"Present")*0.5))/(COUNTIF($K55:$BP55,"Yes")+COUNTIF($K55:$BP55,"No")+COUNTIF($K55:$BP55,"Yes (correct)")+COUNTIF($K55:$BP55,"No (incorrect)")+COUNTIF($K55:$BP55,"Present")) -> 0.45 | H55: =((F55*(1/3))+(G55*(2/3))) -> 0.52222222 | I55: AIPAC, J Street | J55: Sponsor | K55: Sponsor | L55: Sponsor | M55: Not sponsoring | N55: Not sponsoring | O55: Not sponsoring (correct) | P55: No | Q55: No | R55: Yes (correct) | S55: No | T55: No | U55: No | V55: Not on committee | W55: Not on committee | X55: No (incorrect) | Y55: Yes | Z55: No | AA55: No | AB55: No | AC55: Yes | AD55: No | AE55: No | AF55: No | AG55: No | AH55: No | AI55: No | AJ55: Yes | AK55: Yes | AL55: Yes | AM55: Yes | AN55: Yes | AO55: Yes | AP55: Yes | AQ55: Yes | AR55: No | AS55: Yes | AT55: No | AU55: Yes | AV55: Present | AW55: Yes | AX55: Yes | AY55: Yes | AZ55: No | BA55: Yes | BB55: No | BC55: No | BD55: Yes | BE55: No | BF55: Yes | BG55: Yes | BH55: Yes | BI55: Yes | BJ55: Yes | BK55: Yes | BL55: Yes | BM55: Yes | BN55: Yes | BO55: No | BP55: Not elected | BQ55: Non-signatory | BR55: Non-signatory | BS55: Non-signatory | BU55: =SUM(BV55:BY55) -> 0 | CA55: Yes
A56: =LOOKUP(H56,'Letter grades'!$A$1:$B$6) -> D | B56: =RANK(H56,H:H) -> 51 | C56: Suzanne | D56: Bonamici | E56: OR-01 | F56: =((COUNTIF($J56:$BP56,"Sponsor")+COUNTIF($J56:$BP56, "Not sponsoring (correct)"))/(COUNTIF($J56:$BP56,"Sponsor")+COUNTIF($J56:$BP56,"Not sponsoring")+COUNTIF($J56:$BP56, "Not sponsoring (correct)")+COUNTIF($J56:$BP56, "Sponsor (incorrect)"))) -> 0.66666667 | G56: =(COUNTIF($K56:$BP56,"No")+COUNTIF($K56:$BP56,"Yes (correct)")+(COUNTIF($K56:$BP56,"Present")*0.5))/(COUNTIF($K56:$BP56,"Yes")+COUNTIF($K56:$BP56,"No")+COUNTIF($K56:$BP56,"Yes (correct)")+COUNTIF($K56:$BP56,"No (incorrect)")+COUNTIF($K56:$BP56,"Present")) -> 0.45 | H56: =((F56*(1/3))+(G56*(2/3))) -> 0.52222222 | I56: J Street | J56: Sponsor | K56: Sponsor | L56: Sponsor | M56: Not sponsoring | N56: Not sponsoring | O56: Not sponsoring (correct) | P56: No | Q56: No | R56: Yes (correct) | S56: No | T56: Yes | U56: No | V56: Not on committee | W56: Not on committee | X56: No (incorrect) | Y56: Yes | Z56: No | AA56: No | AB56: No | AC56: Yes | AD56: No | AE56: No | AF56: No | AG56: No | AH56: No | AI56: No | AJ56: Yes | AK56: Yes | AL56: Yes | AM56: No | AN56: Yes | AO56: Yes | AP56: Yes | AQ56: Yes | AR56: No | AS56: Yes | AT56: No | AU56: Yes | AV56: Present | AW56: Yes | AX56: Yes | AY56: No | AZ56: No | BA56: Yes | BB56: No | BC56: Yes | BD56: Yes | BE56: No | BF56: Yes | BG56: Yes | BH56: Yes | BI56: No | BJ56: Yes | BK56: Yes | BL56: Yes | BM56: Yes | BN56: Yes | BO56: Yes | BP56: Not elected | BQ56: Non-signatory | BR56: Non-signatory | BS56: Non-signatory | BU56: =SUM(BV56:BY56) -> 20250 | BV56: 20250 | CA56: Yes
A57: =LOOKUP(H57,'Letter grades'!$A$1:$B$6) -> D | B57: =RANK(H57,H:H) -> 53 | C57: Sylvia | D57: Garcia | E57: TX-29 | F57: =((COUNTIF($J57:$BP57,"Sponsor")+COUNTIF($J57:$BP57, "Not sponsoring (correct)"))/(COUNTIF($J57:$BP57,"Sponsor")+COUNTIF($J57:$BP57,"Not sponsoring")+COUNTIF($J57:$BP57, "Not sponsoring (correct)")+COUNTIF($J57:$BP57, "Sponsor (incorrect)"))) -> 0.66666667 | G57: =(COUNTIF($K57:$BP57,"No")+COUNTIF($K57:$BP57,"Yes (correct)")+(COUNTIF($K57:$BP57,"Present")*0.5))/(COUNTIF($K57:$BP57,"Yes")+COUNTIF($K57:$BP57,"No")+COUNTIF($K57:$BP57,"Yes (correct)")+COUNTIF($K57:$BP57,"No (incorrect)")+COUNTIF($K57:$BP57,"Present")) -> 0.43478261 | H57: =((F57*(1/3))+(G57*(2/3))) -> 0.51207729 | I57: J Street | J57: Sponsor | K57: Sponsor | L57: Sponsor | M57: Not sponsoring | N57: Not sponsoring | O57: Not sponsoring (correct) | P57: No | Q57: No | R57: Yes (correct) | S57: No | T57: Yes | U57: No | V57: Not on committee | W57: Not on committee | X57: No (incorrect) | Y57: Yes | Z57: Not voting | AA57: No | AB57: No | AC57: Yes | AD57: No | AE57: No | AF57: No | AG57: No | AH57: No | AI57: No | AJ57: Yes | AK57: Yes | AL57: Yes | AM57: No | AN57: Yes | AO57: Yes | AP57: Yes | AQ57: Yes | AR57: No | AS57: Yes | AT57: No | AU57: Not voting | AV57: Not voting | AW57: Yes | AX57: Yes | AY57: Yes | AZ57: No | BA57: Yes | BB57: No | BC57: No | BD57: Yes | BE57: No | BF57: Yes | BG57: Yes | BH57: Yes | BI57: Yes | BJ57: Yes | BK57: Yes | BL57: Yes | BM57: Yes | BN57: Yes | BO57: Not elected | BP57: Not elected | BQ57: Non-signatory | BR57: Non-signatory | BS57: Signatory | BU57: =SUM(BV57:BY57) -> 41510 | BV57: 41510 | CC57: Yes
A58: =LOOKUP(H58,'Letter grades'!$A$1:$B$6) -> D | B58: =RANK(H58,H:H) -> 54 | C58: Jamie | D58: Raskin | E58: MD-08 | F58: =((COUNTIF($J58:$BP58,"Sponsor")+COUNTIF($J58:$BP58, "Not sponsoring (correct)"))/(COUNTIF($J58:$BP58,"Sponsor")+COUNTIF($J58:$BP58,"Not sponsoring")+COUNTIF($J58:$BP58, "Not sponsoring (correct)")+COUNTIF($J58:$BP58, "Sponsor (incorrect)"))) -> 0.66666667 | G58: =(COUNTIF($K58:$BP58,"No")+COUNTIF($K58:$BP58,"Yes (correct)")+(COUNTIF($K58:$BP58,"Present")*0.5))/(COUNTIF($K58:$BP58,"Yes")+COUNTIF($K58:$BP58,"No")+COUNTIF($K58:$BP58,"Yes (correct)")+COUNTIF($K58:$BP58,"No (incorrect)")+COUNTIF($K58:$BP58,"Present")) -> 0.43 | H58: =((F58*(1/3))+(G58*(2/3))) -> 0.50888889 | I58: J Street | J58: Sponsor | K58: Sponsor | L58: Sponsor | M58: Not sponsoring | N58: Not sponsoring | O58: Not sponsoring (correct) | P58: No | Q58: No | R58: Yes (correct) | S58: No | T58: No | U58: No | V58: Not on committee | W58: Not on committee | X58: No (incorrect) | Y58: Yes | Z58: No | AA58: No | AB58: No | AC58: Yes | AD58: No | AE58: No | AF58: No | AG58: No | AH58: No | AI58: Yes | AJ58: No | AK58: No | AL58: Yes | AM58: Yes | AN58: Yes | AO58: Yes | AP58: Yes | AQ58: Yes | AR58: No | AS58: Yes | AT58: No | AU58: Yes | AV58: Present | AW58: Yes | AX58: Yes | AY58: Yes | AZ58: No | BA58: Yes | BB58: No | BC58: Yes | BD58: Yes | BE58: Yes | BF58: Yes | BG58: Yes | BH58: Yes | BI58: No | BJ58: Yes | BK58: Yes | BL58: Yes | BM58: Yes | BN58: Yes | BO58: Yes | BP58: Not elected | BQ58: Non-signatory | BR58: Non-signatory | BS58: Non-signatory | BU58: =SUM(BV58:BY58) -> 0 | CA58: Yes
A59: =LOOKUP(H59,'Letter grades'!$A$1:$B$6) -> D | B59: =RANK(H59,H:H) -> 55 | C59: Melanie | D59: Stansbury | E59: NM-01 | F59: =((COUNTIF($J59:$BP59,"Sponsor")+COUNTIF($J59:$BP59, "Not sponsoring (correct)"))/(COUNTIF($J59:$BP59,"Sponsor")+COUNTIF($J59:$BP59,"Not sponsoring")+COUNTIF($J59:$BP59, "Not sponsoring (correct)")+COUNTIF($J59:$BP59, "Sponsor (incorrect)"))) -> 0.66666667 | G59: =(COUNTIF($K59:$BP59,"No")+COUNTIF($K59:$BP59,"Yes (correct)")+(COUNTIF($K59:$BP59,"Present")*0.5))/(COUNTIF($K59:$BP59,"Yes")+COUNTIF($K59:$BP59,"No")+COUNTIF($K59:$BP59,"Yes (correct)")+COUNTIF($K59:$BP59,"No (incorrect)")+COUNTIF($K59:$BP59,"Present")) -> 0.42553191 | H59: =((F59*(1/3))+(G59*(2/3))) -> 0.50591017 | I59: J Street | J59: Sponsor | K59: Sponsor | L59: Sponsor | M59: Not sponsoring | N59: Not sponsoring | O59: Not sponsoring (correct) | P59: No | Q59: No | R59: Yes (correct) | S59: No | T59: No | U59: No | V59: Not on committee | W59: Not on committee | X59: No (incorrect) | Y59: Yes | Z59: No | AA59: No | AB59: No | AC59: Yes | AD59: No | AE59: No | AF59: No | AG59: No | AH59: No | AI59: No | AJ59: Yes | AK59: Yes | AL59: Yes | AM59: Yes | AN59: Yes | AO59: Yes | AP59: Yes | AQ59: Yes | AR59: No | AS59: Yes | AT59: Yes | AU59: Yes | AV59: Yes | AW59: Yes | AX59: Yes | AY59: No | AZ59: No | BA59: Yes | BB59: No | BC59: Yes | BD59: Yes | BE59: No | BF59: Yes | BG59: Yes | BH59: Yes | BI59: Yes | BJ59: Yes | BK59: Yes | BL59: Yes | BM59: Not elected | BN59: Not elected | BO59: Not elected | BP59: Not elected | BQ59: Non-signatory | BR59: Non-signatory | BS59: Non-signatory | BU59: =SUM(BV59:BY59) -> 0 | CA59: Yes
A60: =LOOKUP(H60,'Letter grades'!$A$1:$B$6) -> D | B60: =RANK(H60,H:H) -> 56 | C60: Laura | D60: Friedman | E60: CA-30 | F60: =((COUNTIF($J60:$BP60,"Sponsor")+COUNTIF($J60:$BP60, "Not sponsoring (correct)"))/(COUNTIF($J60:$BP60,"Sponsor")+COUNTIF($J60:$BP60,"Not sponsoring")+COUNTIF($J60:$BP60, "Not sponsoring (correct)")+COUNTIF($J60:$BP60, "Sponsor (incorrect)"))) -> 0 | G60: =(COUNTIF($K60:$BP60,"No")+COUNTIF($K60:$BP60,"Yes (correct)")+(COUNTIF($K60:$BP60,"Present")*0.5))/(COUNTIF($K60:$BP60,"Yes")+COUNTIF($K60:$BP60,"No")+COUNTIF($K60:$BP60,"Yes (correct)")+COUNTIF($K60:$BP60,"No (incorrect)")+COUNTIF($K60:$BP60,"Present")) -> 0.75 | H60: =((F60*(1/3))+(G60*(2/3))) -> 0.5 | I60: AIPAC, DMFI, J Street | J60: Not sponsoring | K60: Not sponsoring | L60: Not sponsoring | M60: Not sponsoring | N60: Not sponsoring | O60: Sponsor (incorrect) | P60: No | Q60: No | R60: Yes (correct) | S60: No | T60: No | U60: No | V60: Not on committee | W60: Not on committee | X60: No (incorrect) | Y60: Yes | Z60: Not voting | AA60: Not elected | AB60: Not elected | AC60: Not elected | AD60: Not elected | AE60: Not elected | AF60: Not elected | AG60: Not elected | AH60: Not elected | AI60: Not elected | AJ60: Not elected | AK60: Not elected | AL60: Not elected | AM60: Not elected | AN60: Not elected | AO60: Not elected | AP60: Not elected | AQ60: Not elected | AR60: Not elected | AS60: Not elected | AT60: Not elected | AU60: Not elected | AV60: Not elected | AW60: Not elected | AX60: Not elected | AY60: Not elected | AZ60: Not elected | BA60: Not elected | BB60: Not elected | BC60: Not elected | BD60: Not elected | BE60: Not elected | BF60: Not elected | BG60: Not elected | BH60: Not elected | BI60: Not elected | BJ60: Not elected | BK60: Not elected | BL60: Not elected | BM60: Not elected | BN60: Not elected | BO60: Not elected | BP60: Not elected | BQ60: Non-signatory | BR60: Not elected | BS60: Not elected
A61: =LOOKUP(H61,'Letter grades'!$A$1:$B$6) -> D | B61: =RANK(H61,H:H) -> 57 | C61: John | D61: Garamendi | E61: CA-08 | F61: =((COUNTIF($J61:$BP61,"Sponsor")+COUNTIF($J61:$BP61, "Not sponsoring (correct)"))/(COUNTIF($J61:$BP61,"Sponsor")+COUNTIF($J61:$BP61,"Not sponsoring")+COUNTIF($J61:$BP61, "Not sponsoring (correct)")+COUNTIF($J61:$BP61, "Sponsor (incorrect)"))) -> 0.66666667 | G61: =(COUNTIF($K61:$BP61,"No")+COUNTIF($K61:$BP61,"Yes (correct)")+(COUNTIF($K61:$BP61,"Present")*0.5))/(COUNTIF($K61:$BP61,"Yes")+COUNTIF($K61:$BP61,"No")+COUNTIF($K61:$BP61,"Yes (correct)")+COUNTIF($K61:$BP61,"No (incorrect)")+COUNTIF($K61:$BP61,"Present")) -> 0.40196078 | H61: =((F61*(1/3))+(G61*(2/3))) -> 0.49019608 | I61: J Street | J61: Sponsor | K61: Sponsor | L61: Sponsor | M61: Not sponsoring | N61: Not sponsoring | O61: Not sponsoring (correct) | P61: No | Q61: No | R61: Yes (correct) | S61: No | T61: Yes | U61: No | V61: Not on committee | W61: Not on committee | X61: No (incorrect) | Y61: Yes | Z61: No | AA61: No | AB61: No | AC61: Yes | AD61: No | AE61: No | AF61: No | AG61: No | AH61: No | AI61: No | AJ61: No | AK61: Yes | AL61: Yes | AM61: Yes | AN61: Yes | AO61: Yes | AP61: Yes | AQ61: Yes | AR61: No | AS61: Yes | AT61: Yes | AU61: Yes | AV61: Present | AW61: Yes | AX61: Yes | AY61: Yes | AZ61: No | BA61: Yes | BB61: No | BC61: Yes | BD61: Yes | BE61: No | BF61: Yes | BG61: Yes | BH61: Yes | BI61: Yes | BJ61: Yes | BK61: Yes | BL61: Yes | BM61: Yes | BN61: Yes | BO61: No | BP61: Yes | BQ61: Non-signatory | BR61: Non-signatory | BS61: Non-signatory | BU61: =SUM(BV61:BY61) -> 0 | CA61: Yes
A62: =LOOKUP(H62,'Letter grades'!$A$1:$B$6) -> D | B62: =RANK(H62,H:H) -> 58 | C62: Jennifer | D62: McClellan | E62: VA-04 | F62: =((COUNTIF($J62:$BP62,"Sponsor")+COUNTIF($J62:$BP62, "Not sponsoring (correct)"))/(COUNTIF($J62:$BP62,"Sponsor")+COUNTIF($J62:$BP62,"Not sponsoring")+COUNTIF($J62:$BP62, "Not sponsoring (correct)")+COUNTIF($J62:$BP62, "Sponsor (incorrect)"))) -> 0.66666667 | G62: =(COUNTIF($K62:$BP62,"No")+COUNTIF($K62:$BP62,"Yes (correct)")+(COUNTIF($K62:$BP62,"Present")*0.5))/(COUNTIF($K62:$BP62,"Yes")+COUNTIF($K62:$BP62,"No")+COUNTIF($K62:$BP62,"Yes (correct)")+COUNTIF($K62:$BP62,"No (incorrect)")+COUNTIF($K62:$BP62,"Present")) -> 0.39285714 | H62: =((F62*(1/3))+(G62*(2/3))) -> 0.48412698 | I62: J Street | J62: Sponsor | K62: Sponsor | L62: Sponsor | M62: Not sponsoring | N62: Not sponsoring | O62: Not sponsoring (correct) | P62: No | Q62: No | R62: No (incorrect) | S62: No | T62: Yes | U62: Yes | V62: Not on committee | W62: Not on committee | X62: No (incorrect) | Y62: Yes | Z62: No | AA62: Yes | AB62: No | AC62: Yes | AD62: No | AE62: No | AF62: No | AG62: Not voting | AH62: No | AI62: No | AJ62: Yes | AK62: Yes | AL62: Yes | AM62: Yes | AN62: Yes | AO62: Yes | AP62: Yes | AQ62: Yes | AR62: No | AS62: Yes | AT62: No | AU62: Yes | AV62: Present | AW62: Yes | AX62: Yes | AY62: No | AZ62: No | BA62: Yes | BB62: No | BC62: Yes | BD62: Yes | BE62: No | BF62: Yes | BG62: Yes | BH62: Yes | BI62: Not elected | BJ62: Not elected | BK62: Not elected | BL62: Not elected | BM62: Not elected | BN62: Not elected | BO62: Not elected | BP62: Not elected | BQ62: Non-signatory | BR62: Non-signatory | BS62: Non-signatory | BU62: =SUM(BV62:BY62) -> 29350 | BV62: 26850 | BX62: =2500 -> 2500 | CA62: Yes
A63: =LOOKUP(H63,'Letter grades'!$A$1:$B$6) -> D | B63: =RANK(H63,H:H) -> 59 | C63: Bennie | D63: Thompson | E63: MS-02 | F63: =((COUNTIF($J63:$BP63,"Sponsor")+COUNTIF($J63:$BP63, "Not sponsoring (correct)"))/(COUNTIF($J63:$BP63,"Sponsor")+COUNTIF($J63:$BP63,"Not sponsoring")+COUNTIF($J63:$BP63, "Not sponsoring (correct)")+COUNTIF($J63:$BP63, "Sponsor (incorrect)"))) -> 0.66666667 | G63: =(COUNTIF($K63:$BP63,"No")+COUNTIF($K63:$BP63,"Yes (correct)")+(COUNTIF($K63:$BP63,"Present")*0.5))/(COUNTIF($K63:$BP63,"Yes")+COUNTIF($K63:$BP63,"No")+COUNTIF($K63:$BP63,"Yes (correct)")+COUNTIF($K63:$BP63,"No (incorrect)")+COUNTIF($K63:$BP63,"Present")) -> 0.3877551 | H63: =((F63*(1/3))+(G63*(2/3))) -> 0.48072562 | I63: J Street | J63: Sponsor | K63: Sponsor | L63: Sponsor | M63: Not sponsoring | N63: Not sponsoring | O63: Not sponsoring (correct) | P63: No | Q63: No | R63: Yes (correct) | S63: No | T63: Yes | U63: Yes | V63: Not on committee | W63: Not on committee | X63: No (incorrect) | Y63: Yes | Z63: No | AA63: Yes | AB63: No | AC63: Yes | AD63: No | AE63: No | AF63: No | AG63: No | AH63: No | AI63: No | AJ63: No | AK63: No | AL63: Yes | AM63: Yes | AN63: Yes | AO63: Not voting | AP63: Yes | AQ63: Yes | AR63: No | AS63: Yes | AT63: No | AU63: Yes | AV63: Not voting | AW63: Yes | AX63: Yes | AY63: Yes | AZ63: No | BA63: Yes | BB63: No | BC63: Yes | BD63: Yes | BE63: Yes | BF63: Yes | BG63: Yes | BH63: Yes | BI63: Yes | BJ63: Yes | BK63: Yes | BL63: Yes | BM63: Yes | BN63: Yes | BO63: No | BP63: Yes | BQ63: Non-signatory | BR63: Non-signatory | BS63: Signatory | BU63: =SUM(BV63:BY63) -> 0
A64: =LOOKUP(H64,'Letter grades'!$A$1:$B$6) -> D | B64: =RANK(H64,H:H) -> 60 | C64: Veronica | D64: Escobar | E64: TX-16 | F64: =((COUNTIF($J64:$BP64,"Sponsor")+COUNTIF($J64:$BP64, "Not sponsoring (correct)"))/(COUNTIF($J64:$BP64,"Sponsor")+COUNTIF($J64:$BP64,"Not sponsoring")+COUNTIF($J64:$BP64, "Not sponsoring (correct)")+COUNTIF($J64:$BP64, "Sponsor (incorrect)"))) -> 0.5 | G64: =(COUNTIF($K64:$BP64,"No")+COUNTIF($K64:$BP64,"Yes (correct)")+(COUNTIF($K64:$BP64,"Present")*0.5))/(COUNTIF($K64:$BP64,"Yes")+COUNTIF($K64:$BP64,"No")+COUNTIF($K64:$BP64,"Yes (correct)")+COUNTIF($K64:$BP64,"No (incorrect)")+COUNTIF($K64:$BP64,"Present")) -> 0.4673913 | H64: =((F64*(1/3))+(G64*(2/3))) -> 0.47826087 | I64: J Street | J64: Sponsor | K64: Not sponsoring | L64: Sponsor | M64: Not sponsoring | N64: Not sponsoring | O64: Not sponsoring (correct) | P64: No | Q64: No | R64: Yes (correct) | S64: No | T64: No | U64: No | V64: Not on committee | W64: Not on committee | X64: No (incorrect) | Y64: Not voting | Z64: No | AA64: Yes | AB64: No | AC64: Yes | AD64: No | AE64: No | AF64: No | AG64: No | AH64: No | AI64: Yes | AJ64: Yes | AK64: No | AL64: Yes | AM64: No | AN64: Yes | AO64: Yes | AP64: Yes | AQ64: Yes | AR64: No | AS64: Yes | AT64: No | AU64: Not voting | AV64: Present | AW64: Yes | AX64: Yes | AY64: Not voting | AZ64: No | BA64: Yes | BB64: No | BC64: No | BD64: Yes | BE64: No | BF64: Yes | BG64: Yes | BH64: Yes | BI64: Yes | BJ64: Yes | BK64: Yes | BL64: Yes | BM64: Yes | BN64: Yes | BO64: Not elected | BP64: Not elected | BQ64: Non-signatory | BR64: Non-signatory | BS64: Non-signatory | BU64: =SUM(BV64:BY64) -> 11610 | BV64: 11610 | CA64: Yes | CC64: Yes
A65: =LOOKUP(H65,'Letter grades'!$A$1:$B$6) -> D | B65: =RANK(H65,H:H) -> 61 | C65: Chris | D65: Deluzio | E65: PA-17 | F65: =((COUNTIF($J65:$BP65,"Sponsor")+COUNTIF($J65:$BP65, "Not sponsoring (correct)"))/(COUNTIF($J65:$BP65,"Sponsor")+COUNTIF($J65:$BP65,"Not sponsoring")+COUNTIF($J65:$BP65, "Not sponsoring (correct)")+COUNTIF($J65:$BP65, "Sponsor (incorrect)"))) -> 0.66666667 | G65: =(COUNTIF($K65:$BP65,"No")+COUNTIF($K65:$BP65,"Yes (correct)")+(COUNTIF($K65:$BP65,"Present")*0.5))/(COUNTIF($K65:$BP65,"Yes")+COUNTIF($K65:$BP65,"No")+COUNTIF($K65:$BP65,"Yes (correct)")+COUNTIF($K65:$BP65,"No (incorrect)")+COUNTIF($K65:$BP65,"Present")) -> 0.38095238 | H65: =((F65*(1/3))+(G65*(2/3))) -> 0.47619048 | I65: J Street | J65: Sponsor | K65: Sponsor | L65: Sponsor | M65: Not sponsoring | N65: Not sponsoring | O65: Not sponsoring (correct) | P65: No | Q65: No | R65: Yes (correct) | S65: No | T65: Yes | U65: No | V65: Not on committee | W65: Not on committee | X65: No (incorrect) | Y65: Yes | Z65: No | AA65: No | AB65: No | AC65: Yes | AD65: No | AE65: No | AF65: No | AG65: No | AH65: No | AI65: Yes | AJ65: Yes | AK65: Yes | AL65: Yes | AM65: Yes | AN65: Yes | AO65: Yes | AP65: Yes | AQ65: Yes | AR65: No | AS65: Yes | AT65: Yes | AU65: Yes | AV65: Yes | AW65: Yes | AX65: Yes | AY65: Yes | AZ65: No | BA65: Yes | BB65: No | BC65: Yes | BD65: Yes | BE65: Yes | BF65: Not voting | BG65: Yes | BH65: Yes | BI65: Not elected | BJ65: Not elected | BK65: Not elected | BL65: Not elected | BM65: Not elected | BN65: Not elected | BO65: Not elected | BP65: Not elected | BQ65: Non-signatory | BR65: Signatory | BS65: Non-signatory | BU65: =SUM(BV65:BY65) -> 0 | CA65: Yes
A66: =LOOKUP(H66,'Letter grades'!$A$1:$B$6) -> D | B66: =RANK(H66,H:H) -> 62 | C66: Teresa | D66: Leger Fernandez | E66: NM-03 | F66: =((COUNTIF($J66:$BP66,"Sponsor")+COUNTIF($J66:$BP66, "Not sponsoring (correct)"))/(COUNTIF($J66:$BP66,"Sponsor")+COUNTIF($J66:$BP66,"Not sponsoring")+COUNTIF($J66:$BP66, "Not sponsoring (correct)")+COUNTIF($J66:$BP66, "Sponsor (incorrect)"))) -> 0.66666667 | G66: =(COUNTIF($K66:$BP66,"No")+COUNTIF($K66:$BP66,"Yes (correct)")+(COUNTIF($K66:$BP66,"Present")*0.5))/(COUNTIF($K66:$BP66,"Yes")+COUNTIF($K66:$BP66,"No")+COUNTIF($K66:$BP66,"Yes (correct)")+COUNTIF($K66:$BP66,"No (incorrect)")+COUNTIF($K66:$BP66,"Present")) -> 0.38043478 | H66: =((F66*(1/3))+(G66*(2/3))) -> 0.47584541 | I66: J Street | J66: Sponsor | K66: Sponsor | L66: Sponsor | M66: Not sponsoring | N66: Not sponsoring | O66: Not sponsoring (correct) | P66: No | Q66: No | R66: Yes (correct) | S66: No | T66: No | U66: Yes | V66: Not on committee | W66: Not on committee | X66: No (incorrect) | Y66: Yes | Z66: No | AA66: No | AB66: No | AC66: Yes | AD66: Not voting | AE66: No | AF66: No | AG66: No | AH66: No | AI66: No | AJ66: Yes | AK66: Yes | AL66: Yes | AM66: Yes | AN66: Yes | AO66: Yes | AP66: Yes | AQ66: Yes | AR66: No | AS66: Yes | AT66: Yes | AU66: Yes | AV66: Present | AW66: Yes | AX66: Yes | AY66: No | AZ66: No | BA66: Yes | BB66: No | BC66: Yes | BD66: Yes | BE66: Yes | BF66: Yes | BG66: Yes | BH66: Yes | BI66: Yes | BJ66: Yes | BK66: Yes | BL66: Yes | BM66: Not elected | BN66: Not elected | BO66: Not elected | BP66: Not elected | BQ66: Non-signatory | BR66: Non-signatory | BS66: Non-signatory | BU66: =SUM(BV66:BY66) -> 15705 | BV66: 13705 | BX66: =2000 -> 2000 | CA66: Yes | CC66: Yes
A67: =LOOKUP(H67,'Letter grades'!$A$1:$B$6) -> D | B67: =RANK(H67,H:H) -> 63 | C67: Stephen | D67: Lynch | E67: MA-08 | F67: =((COUNTIF($J67:$BP67,"Sponsor")+COUNTIF($J67:$BP67, "Not sponsoring (correct)"))/(COUNTIF($J67:$BP67,"Sponsor")+COUNTIF($J67:$BP67,"Not sponsoring")+COUNTIF($J67:$BP67, "Not sponsoring (correct)")+COUNTIF($J67:$BP67, "Sponsor (incorrect)"))) -> 0.66666667 | G67: =(COUNTIF($K67:$BP67,"No")+COUNTIF($K67:$BP67,"Yes (correct)")+(COUNTIF($K67:$BP67,"Present")*0.5))/(COUNTIF($K67:$BP67,"Yes")+COUNTIF($K67:$BP67,"No")+COUNTIF($K67:$BP67,"Yes (correct)")+COUNTIF($K67:$BP67,"No (incorrect)")+COUNTIF($K67:$BP67,"Present")) -> 0.38 | H67: =((F67*(1/3))+(G67*(2/3))) -> 0.47555556 | I67: J Street | J67: Sponsor | K67: Sponsor | L67: Sponsor | M67: Not sponsoring | N67: Not sponsoring | O67: Not sponsoring (correct) | P67: No | Q67: No | R67: Yes (correct) | S67: No | T67: No | U67: No | V67: Not on committee | W67: Not on committee | X67: No (incorrect) | Y67: Yes | Z67: No | AA67: No | AB67: No | AC67: Not voting | AD67: No | AE67: No | AF67: No | AG67: No | AH67: No | AI67: Yes | AJ67: Yes | AK67: Yes | AL67: Yes | AM67: Yes | AN67: Yes | AO67: Yes | AP67: Yes | AQ67: Yes | AR67: No | AS67: Yes | AT67: Yes | AU67: Yes | AV67: Yes | AW67: Yes | AX67: Yes | AY67: Yes | AZ67: No | BA67: Yes | BB67: No | BC67: Yes | BD67: Yes | BE67: No | BF67: Yes | BG67: Yes | BH67: Yes | BI67: Yes | BJ67: Yes | BK67: Yes | BL67: Yes | BM67: Yes | BN67: Yes | BO67: No | BP67: Yes | BQ67: Non-signatory | BR67: Non-signatory | BS67: Non-signatory | BU67: =SUM(BV67:BY67) -> 0
A68: =LOOKUP(H68,'Letter grades'!$A$1:$B$6) -> D | B68: =RANK(H68,H:H) -> 64 | C68: Zoe | D68: Lofgren | E68: CA-18 | F68: =((COUNTIF($J68:$BP68,"Sponsor")+COUNTIF($J68:$BP68, "Not sponsoring (correct)"))/(COUNTIF($J68:$BP68,"Sponsor")+COUNTIF($J68:$BP68,"Not sponsoring")+COUNTIF($J68:$BP68, "Not sponsoring (correct)")+COUNTIF($J68:$BP68, "Sponsor (incorrect)"))) -> 0.66666667 | G68: =(COUNTIF($K68:$BP68,"No")+COUNTIF($K68:$BP68,"Yes (correct)")+(COUNTIF($K68:$BP68,"Present")*0.5))/(COUNTIF($K68:$BP68,"Yes")+COUNTIF($K68:$BP68,"No")+COUNTIF($K68:$BP68,"Yes (correct)")+COUNTIF($K68:$BP68,"No (incorrect)")+COUNTIF($K68:$BP68,"Present")) -> 0.37234043 | H68: =((F68*(1/3))+(G68*(2/3))) -> 0.47044917 | I68: J Street | J68: Sponsor | K68: Sponsor | L68: Sponsor | M68: Not sponsoring | N68: Not sponsoring | O68: Not sponsoring (correct) | P68: No | Q68: No | R68: Yes (correct) | S68: No | T68: No | U68: No | V68: Not on committee | W68: Not on committee | X68: No (incorrect) | Y68: Yes | Z68: Not voting | AA68: Yes | AB68: No | AC68: Yes | AD68: No | AE68: No | AF68: No | AG68: Not voting | AH68: No | AI68: No | AJ68: Yes | AK68: Yes | AL68: Yes | AM68: Yes | AN68: Yes | AO68: Yes | AP68: Yes | AQ68: Yes | AR68: No | AS68: Yes | AT68: No | AU68: Not voting | AV68: Not voting | AW68: Yes | AX68: Yes | AY68: Yes | AZ68: No | BA68: Yes | BB68: No | BC68: No | BD68: Yes | BE68: Yes | BF68: Yes | BG68: Yes | BH68: Yes | BI68: Yes | BJ68: Yes | BK68: Yes | BL68: Yes | BM68: Yes | BN68: Yes | BO68: Present | BP68: Yes | BQ68: Non-signatory | BR68: Non-signatory | BS68: Non-signatory | BU68: =SUM(BV68:BY68) -> 0 | CA68: Yes
A69: =LOOKUP(H69,'Letter grades'!$A$1:$B$6) -> D | B69: =RANK(H69,H:H) -> 65 | C69: Paul | D69: Tonko | E69: NY-20 | F69: =((COUNTIF($J69:$BP69,"Sponsor")+COUNTIF($J69:$BP69, "Not sponsoring (correct)"))/(COUNTIF($J69:$BP69,"Sponsor")+COUNTIF($J69:$BP69,"Not sponsoring")+COUNTIF($J69:$BP69, "Not sponsoring (correct)")+COUNTIF($J69:$BP69, "Sponsor (incorrect)"))) -> 0.66666667 | G69: =(COUNTIF($K69:$BP69,"No")+COUNTIF($K69:$BP69,"Yes (correct)")+(COUNTIF($K69:$BP69,"Present")*0.5))/(COUNTIF($K69:$BP69,"Yes")+COUNTIF($K69:$BP69,"No")+COUNTIF($K69:$BP69,"Yes (correct)")+COUNTIF($K69:$BP69,"No (incorrect)")+COUNTIF($K69:$BP69,"Present")) -> 0.3627451 | H69: =((F69*(1/3))+(G69*(2/3))) -> 0.46405229 | I69: J Street | J69: Sponsor | K69: Sponsor | L69: Sponsor | M69: Not sponsoring | N69: Not sponsoring | O69: Not sponsoring (correct) | P69: No | Q69: No | R69: Yes (correct) | S69: No | T69: Yes | U69: No | V69: Not on committee | W69: Not on committee | X69: No (incorrect) | Y69: Yes | Z69: No | AA69: Yes | AB69: No | AC69: Yes | AD69: No | AE69: No | AF69: No | AG69: No | AH69: No | AI69: Yes | AJ69: Yes | AK69: Yes | AL69: Yes | AM69: Yes | AN69: Yes | AO69: Yes | AP69: Yes | AQ69: Yes | AR69: No | AS69: Yes | AT69: No | AU69: Yes | AV69: Present | AW69: Yes | AX69: Yes | AY69: Yes | AZ69: No | BA69: Yes | BB69: No | BC69: Yes | BD69: Yes | BE69: No | BF69: Yes | BG69: Yes | BH69: Yes | BI69: Yes | BJ69: Yes | BK69: Yes | BL69: Yes | BM69: Yes | BN69: Yes | BO69: No | BP69: Yes | BQ69: Non-signatory | BR69: Non-signatory | BS69: Non-signatory | BU69: =SUM(BV69:BY69) -> 0 | CA69: Yes
A70: =LOOKUP(H70,'Letter grades'!$A$1:$B$6) -> D | B70: =RANK(H70,H:H) -> 66 | C70: Kelly | D70: Morrison | E70: MN-03 | F70: =((COUNTIF($J70:$BP70,"Sponsor")+COUNTIF($J70:$BP70, "Not sponsoring (correct)"))/(COUNTIF($J70:$BP70,"Sponsor")+COUNTIF($J70:$BP70,"Not sponsoring")+COUNTIF($J70:$BP70, "Not sponsoring (correct)")+COUNTIF($J70:$BP70, "Sponsor (incorrect)"))) -> 0.16666667 | G70: =(COUNTIF($K70:$BP70,"No")+COUNTIF($K70:$BP70,"Yes (correct)")+(COUNTIF($K70:$BP70,"Present")*0.5))/(COUNTIF($K70:$BP70,"Yes")+COUNTIF($K70:$BP70,"No")+COUNTIF($K70:$BP70,"Yes (correct)")+COUNTIF($K70:$BP70,"No (incorrect)")+COUNTIF($K70:$BP70,"Present")) -> 0.61111111 | H70: =((F70*(1/3))+(G70*(2/3))) -> 0.46296296 | J70: Sponsor | K70: Not sponsoring | L70: Not sponsoring | M70: Not sponsoring | N70: Not sponsoring | O70: Sponsor (incorrect) | P70: No | Q70: No | R70: Present | S70: No | T70: Yes | U70: No | V70: Not on committee | W70: Not on committee | X70: No (incorrect) | Y70: Yes | Z70: No | AA70: Not elected | AB70: Not elected | AC70: Not elected | AD70: Not elected | AE70: Not elected | AF70: Not elected | AG70: Not elected | AH70: Not elected | AI70: Not elected | AJ70: Not elected | AK70: Not elected | AL70: Not elected | AM70: Not elected | AN70: Not elected | AO70: Not elected | AP70: Not elected | AQ70: Not elected | AR70: Not elected | AS70: Not elected | AT70: Not elected | AU70: Not elected | AV70: Not elected | AW70: Not elected | AX70: Not elected | AY70: Not elected | AZ70: Not elected | BA70: Not elected | BB70: Not elected | BC70: Not elected | BD70: Not elected | BE70: Not elected | BF70: Not elected | BG70: Not elected | BH70: Not elected | BI70: Not elected | BJ70: Not elected | BK70: Not elected | BL70: Not elected | BM70: Not elected | BN70: Not elected | BO70: Not elected | BP70: Not elected | BQ70: Signatory | BR70: Not elected | BS70: Not elected
A71: =LOOKUP(H71,'Letter grades'!$A$1:$B$6) -> D | B71: =RANK(H71,H:H) -> 67 | C71: Gabe | D71: Amo | E71: RI-01 | F71: =((COUNTIF($J71:$BP71,"Sponsor")+COUNTIF($J71:$BP71, "Not sponsoring (correct)"))/(COUNTIF($J71:$BP71,"Sponsor")+COUNTIF($J71:$BP71,"Not sponsoring")+COUNTIF($J71:$BP71, "Not sponsoring (correct)")+COUNTIF($J71:$BP71, "Sponsor (incorrect)"))) -> 0.33333333 | G71: =(COUNTIF($K71:$BP71,"No")+COUNTIF($K71:$BP71,"Yes (correct)")+(COUNTIF($K71:$BP71,"Present")*0.5))/(COUNTIF($K71:$BP71,"Yes")+COUNTIF($K71:$BP71,"No")+COUNTIF($K71:$BP71,"Yes (correct)")+COUNTIF($K71:$BP71,"No (incorrect)")+COUNTIF($K71:$BP71,"Present")) -> 0.52777778 | H71: =((F71*(1/3))+(G71*(2/3))) -> 0.46296296 | I71: AIPAC, J Street | J71: Sponsor | K71: Sponsor | L71: Not sponsoring | M71: Not sponsoring | N71: Not sponsoring | O71: Sponsor (incorrect) | P71: No | Q71: No | R71: Yes (correct) | S71: No | T71: No | U71: No | V71: Yes (correct) | W71: No (incorrect) | X71: No (incorrect) | Y71: Yes | Z71: No | AA71: No | AB71: No | AC71: Yes | AD71: No | AE71: No | AF71: No | AG71: No | AH71: No | AI71: No | AJ71: Yes | AK71: Yes | AL71: Yes | AM71: Yes | AN71: Yes | AO71: Yes | AP71: Yes | AQ71: Yes | AR71: No | AS71: Yes | AT71: No | AU71: Yes | AV71: Yes | AW71: Yes | AX71: Yes | AY71: No | AZ71: Not elected | BA71: Not elected | BB71: Not elected | BC71: Not elected | BD71: Not elected | BE71: Not elected | BF71: Not elected | BG71: Not elected | BH71: Not elected | BI71: Not elected | BJ71: Not elected | BK71: Not elected | BL71: Not elected | BM71: Not elected | BN71: Not elected | BO71: Not elected | BP71: Not elected | BQ71: Non-signatory | BR71: Not elected | BS71: Not elected | CB71: Yes
A72: =LOOKUP(H72,'Letter grades'!$A$1:$B$6) -> D | B72: =RANK(H72,H:H) -> 68 | C72: Madeleine | D72: Dean | E72: PA-04 | F72: =((COUNTIF($J72:$BP72,"Sponsor")+COUNTIF($J72:$BP72, "Not sponsoring (correct)"))/(COUNTIF($J72:$BP72,"Sponsor")+COUNTIF($J72:$BP72,"Not sponsoring")+COUNTIF($J72:$BP72, "Not sponsoring (correct)")+COUNTIF($J72:$BP72, "Sponsor (incorrect)"))) -> 0.66666667 | G72: =(COUNTIF($K72:$BP72,"No")+COUNTIF($K72:$BP72,"Yes (correct)")+(COUNTIF($K72:$BP72,"Present")*0.5))/(COUNTIF($K72:$BP72,"Yes")+COUNTIF($K72:$BP72,"No")+COUNTIF($K72:$BP72,"Yes (correct)")+COUNTIF($K72:$BP72,"No (incorrect)")+COUNTIF($K72:$BP72,"Present")) -> 0.36 | H72: =((F72*(1/3))+(G72*(2/3))) -> 0.46222222 | I72: J Street | J72: Sponsor | K72: Sponsor | L72: Sponsor | M72: Not sponsoring | N72: Not sponsoring | O72: Not sponsoring (correct) | P72: No | Q72: No | R72: Yes (correct) | S72: No | T72: Yes | U72: Yes | V72: Yes (correct) | W72: Yes (correct) | X72: No (incorrect) | Y72: Not voting | Z72: No | AA72: Yes | AB72: No | AC72: Yes | AD72: No | AE72: No | AF72: No | AG72: No | AH72: No | AI72: Yes | AJ72: Yes | AK72: Yes | AL72: Yes | AM72: Present | AN72: Yes | AO72: Yes | AP72: Yes | AQ72: Yes | AR72: No | AS72: Yes | AT72: No | AU72: Yes | AV72: Present | AW72: Yes | AX72: Yes | AY72: Yes | AZ72: No | BA72: Yes | BB72: No | BC72: Yes | BD72: Yes | BE72: Yes | BF72: Yes | BG72: Yes | BH72: Yes | BI72: Yes | BJ72: Yes | BK72: Yes | BL72: Yes | BM72: Yes | BN72: Yes | BO72: Not elected | BP72: Not elected | BQ72: Non-signatory | BR72: Non-signatory | BS72: Non-signatory | BU72: =SUM(BV72:BY72) -> 6336 | BV72: 6336 | CA72: Yes | CC72: Yes
A73: =LOOKUP(H73,'Letter grades'!$A$1:$B$6) -> D | B73: =RANK(H73,H:H) -> 68 | C73: Linda | D73: Sánchez | E73: CA-38 | F73: =((COUNTIF($J73:$BP73,"Sponsor")+COUNTIF($J73:$BP73, "Not sponsoring (correct)"))/(COUNTIF($J73:$BP73,"Sponsor")+COUNTIF($J73:$BP73,"Not sponsoring")+COUNTIF($J73:$BP73, "Not sponsoring (correct)")+COUNTIF($J73:$BP73, "Sponsor (incorrect)"))) -> 0.66666667 | G73: =(COUNTIF($K73:$BP73,"No")+COUNTIF($K73:$BP73,"Yes (correct)")+(COUNTIF($K73:$BP73,"Present")*0.5))/(COUNTIF($K73:$BP73,"Yes")+COUNTIF($K73:$BP73,"No")+COUNTIF($K73:$BP73,"Yes (correct)")+COUNTIF($K73:$BP73,"No (incorrect)")+COUNTIF($K73:$BP73,"Present")) -> 0.36 | H73: =((F73*(1/3))+(G73*(2/3))) -> 0.46222222 | I73: J Street | J73: Sponsor | K73: Sponsor | L73: Sponsor | M73: Not sponsoring | N73: Not sponsoring | O73: Not sponsoring (correct) | P73: No | Q73: No | R73: Present | S73: No | T73: Yes | U73: Not voting | V73: Not on committee | W73: Not on committee | X73: No (incorrect) | Y73: Yes | Z73: No | AA73: No | AB73: No | AC73: Yes | AD73: No | AE73: No | AF73: No | AG73: No | AH73: No | AI73: No | AJ73: Yes | AK73: Yes | AL73: Yes | AM73: Yes | AN73: Yes | AO73: Yes | AP73: Yes | AQ73: Yes | AR73: No | AS73: Yes | AT73: No | AU73: Yes | AV73: Present | AW73: Yes | AX73: Yes | AY73: Yes | AZ73: No | BA73: Yes | BB73: No | BC73: Yes | BD73: Yes | BE73: No | BF73: Yes | BG73: Yes | BH73: Yes | BI73: Yes | BJ73: Yes | BK73: Yes | BL73: Yes | BM73: Yes | BN73: Yes | BO73: Yes | BP73: Yes | BQ73: Non-signatory | BR73: Non-signatory | BS73: Non-signatory | BU73: =SUM(BV73:BY73) -> 26300 | BV73: 26300 | CA73: Yes | CC73: Yes
A74: =LOOKUP(H74,'Letter grades'!$A$1:$B$6) -> D | B74: =RANK(H74,H:H) -> 70 | C74: Seth | D74: Magaziner | E74: RI-02 | F74: =((COUNTIF($J74:$BP74,"Sponsor")+COUNTIF($J74:$BP74, "Not sponsoring (correct)"))/(COUNTIF($J74:$BP74,"Sponsor")+COUNTIF($J74:$BP74,"Not sponsoring")+COUNTIF($J74:$BP74, "Not sponsoring (correct)")+COUNTIF($J74:$BP74, "Sponsor (incorrect)"))) -> 0.5 | G74: =(COUNTIF($K74:$BP74,"No")+COUNTIF($K74:$BP74,"Yes (correct)")+(COUNTIF($K74:$BP74,"Present")*0.5))/(COUNTIF($K74:$BP74,"Yes")+COUNTIF($K74:$BP74,"No")+COUNTIF($K74:$BP74,"Yes (correct)")+COUNTIF($K74:$BP74,"No (incorrect)")+COUNTIF($K74:$BP74,"Present")) -> 0.42307692 | H74: =((F74*(1/3))+(G74*(2/3))) -> 0.44871795 | I74: AIPAC, J Street | J74: Sponsor | K74: Not sponsoring | L74: Sponsor | M74: Not sponsoring | N74: Not sponsoring | O74: Not sponsoring (correct) | P74: No | Q74: No | R74: Yes (correct) | S74: No | T74: No | U74: No | V74: Not on committee | W74: Not on committee | X74: No (incorrect) | Y74: Yes | Z74: No | AA74: Yes | AB74: No | AC74: Yes | AD74: No | AE74: No | AF74: No | AG74: No | AH74: Not voting | AI74: Not voting | AJ74: Yes | AK74: Not voting | AL74: Not voting | AM74: Yes | AN74: Yes | AO74: Yes | AP74: Yes | AQ74: Yes | AR74: No | AS74: Yes | AT74: No | AU74: Yes | AV74: Present | AW74: Yes | AX74: Yes | AY74: Yes | AZ74: No | BA74: Yes | BB74: No | BC74: Yes | BD74: Yes | BE74: Yes | BF74: Yes | BG74: Yes | BH74: Yes | BI74: Not elected | BJ74: Not elected | BK74: Not elected | BL74: Not elected | BM74: Not elected | BN74: Not elected | BO74: Not elected | BP74: Not elected | BQ74: Non-signatory | BR74: Non-signatory | BS74: Non-signatory | BU74: =SUM(BV74:BY74) -> 7000 | BV74: 5000 | BX74: =2000 -> 2000 | CA74: Yes | CB74: Yes
A75: =LOOKUP(H75,'Letter grades'!$A$1:$B$6) -> D | B75: =RANK(H75,H:H) -> 71 | C75: Mike | D75: Thompson | E75: CA-04 | F75: =((COUNTIF($J75:$BP75,"Sponsor")+COUNTIF($J75:$BP75, "Not sponsoring (correct)"))/(COUNTIF($J75:$BP75,"Sponsor")+COUNTIF($J75:$BP75,"Not sponsoring")+COUNTIF($J75:$BP75, "Not sponsoring (correct)")+COUNTIF($J75:$BP75, "Sponsor (incorrect)"))) -> 0.66666667 | G75: =(COUNTIF($K75:$BP75,"No")+COUNTIF($K75:$BP75,"Yes (correct)")+(COUNTIF($K75:$BP75,"Present")*0.5))/(COUNTIF($K75:$BP75,"Yes")+COUNTIF($K75:$BP75,"No")+COUNTIF($K75:$BP75,"Yes (correct)")+COUNTIF($K75:$BP75,"No (incorrect)")+COUNTIF($K75:$BP75,"Present")) -> 0.32352941 | H75: =((F75*(1/3))+(G75*(2/3))) -> 0.4379085 | I75: J Street | J75: Sponsor | K75: Sponsor | L75: Sponsor | M75: Not sponsoring | N75: Not sponsoring | O75: Not sponsoring (correct) | P75: No | Q75: No | R75: Present | S75: No | T75: Yes | U75: Yes | V75: Not on committee | W75: Not on committee | X75: No (incorrect) | Y75: Yes | Z75: No | AA75: Yes | AB75: No | AC75: Yes | AD75: No | AE75: No | AF75: No | AG75: No | AH75: No | AI75: Yes | AJ75: Yes | AK75: Yes | AL75: Yes | AM75: Yes | AN75: Yes | AO75: Yes | AP75: Yes | AQ75: Yes | AR75: No | AS75: Yes | AT75: No | AU75: Yes | AV75: Yes | AW75: Yes | AX75: Yes | AY75: Yes | AZ75: No | BA75: Yes | BB75: No | BC75: Yes | BD75: Yes | BE75: No | BF75: Yes | BG75: Yes | BH75: Yes | BI75: Yes | BJ75: Yes | BK75: Yes | BL75: Yes | BM75: Yes | BN75: Yes | BO75: No | BP75: Yes | BQ75: Non-signatory | BR75: Non-signatory | BS75: Non-signatory | BU75: =SUM(BV75:BY75) -> 0 | CA75: Yes
A76: =LOOKUP(H76,'Letter grades'!$A$1:$B$6) -> D | B76: =RANK(H76,H:H) -> 72 | C76: Jasmine | D76: Crockett | E76: TX-30 | F76: =((COUNTIF($J76:$BP76,"Sponsor")+COUNTIF($J76:$BP76, "Not sponsoring (correct)"))/(COUNTIF($J76:$BP76,"Sponsor")+COUNTIF($J76:$BP76,"Not sponsoring")+COUNTIF($J76:$BP76, "Not sponsoring (correct)")+COUNTIF($J76:$BP76, "Sponsor (incorrect)"))) -> 0.33333333 | G76: =(COUNTIF($K76:$BP76,"No")+COUNTIF($K76:$BP76,"Yes (correct)")+(COUNTIF($K76:$BP76,"Present")*0.5))/(COUNTIF($K76:$BP76,"Yes")+COUNTIF($K76:$BP76,"No")+COUNTIF($K76:$BP76,"Yes (correct)")+COUNTIF($K76:$BP76,"No (incorrect)")+COUNTIF($K76:$BP76,"Present")) -> 0.4875 | H76: =((F76*(1/3))+(G76*(2/3))) -> 0.43611111 | J76: Sponsor | K76: Not sponsoring | L76: Not sponsoring | M76: Not sponsoring | N76: Not sponsoring | O76: Not sponsoring (correct) | P76: No | Q76: No | R76: Yes (correct) | S76: No | T76: Yes | U76: No | V76: Not on committee | W76: Not on committee | X76: No (incorrect) | Y76: Not voting | Z76: No | AA76: No | AB76: No | AC76: Yes | AD76: No | AE76: No | AF76: Not voting | AG76: No | AH76: No | AI76: No | AJ76: Yes | AK76: No | AL76: Yes | AM76: Yes | AN76: Yes | AO76: Yes | AP76: Yes | AQ76: Yes | AR76: No | AS76: Yes | AT76: No | AU76: Not voting | AV76: Present | AW76: Yes | AX76: Yes | AY76: No | AZ76: No | BA76: Yes | BB76: No | BC76: Yes | BD76: Yes | BE76: Yes | BF76: Yes | BG76: Yes | BH76: Yes | BI76: Not elected | BJ76: Not elected | BK76: Not elected | BL76: Not elected | BM76: Not elected | BN76: Not elected | BO76: Not elected | BP76: Not elected | BQ76: Non-signatory | BR76: Non-signatory | BS76: Signatory | BU76: =SUM(BV76:BY76) -> 0
A77: =LOOKUP(H77,'Letter grades'!$A$1:$B$6) -> D | B77: =RANK(H77,H:H) -> 73 | C77: Diana | D77: DeGette | E77: CO-01 | F77: =((COUNTIF($J77:$BP77,"Sponsor")+COUNTIF($J77:$BP77, "Not sponsoring (correct)"))/(COUNTIF($J77:$BP77,"Sponsor")+COUNTIF($J77:$BP77,"Not sponsoring")+COUNTIF($J77:$BP77, "Not sponsoring (correct)")+COUNTIF($J77:$BP77, "Sponsor (incorrect)"))) -> 0.5 | G77: =(COUNTIF($K77:$BP77,"No")+COUNTIF($K77:$BP77,"Yes (correct)")+(COUNTIF($K77:$BP77,"Present")*0.5))/(COUNTIF($K77:$BP77,"Yes")+COUNTIF($K77:$BP77,"No")+COUNTIF($K77:$BP77,"Yes (correct)")+COUNTIF($K77:$BP77,"No (incorrect)")+COUNTIF($K77:$BP77,"Present")) -> 0.40196078 | H77: =((F77*(1/3))+(G77*(2/3))) -> 0.43464052 | I77: J Street | J77: Sponsor | K77: Sponsor | L77: Not sponsoring | M77: Not sponsoring | N77: Not sponsoring | O77: Not sponsoring (correct) | P77: No | Q77: No | R77: Yes (correct) | S77: No | T77: Yes | U77: No | V77: Not on committee | W77: Not on committee | X77: No (incorrect) | Y77: Yes | Z77: No | AA77: No | AB77: No | AC77: Yes | AD77: No | AE77: No | AF77: No | AG77: No | AH77: No | AI77: No | AJ77: Yes | AK77: Yes | AL77: Yes | AM77: Yes | AN77: Yes | AO77: Yes | AP77: Yes | AQ77: Yes | AR77: No | AS77: Yes | AT77: No | AU77: Yes | AV77: Present | AW77: Yes | AX77: Yes | AY77: No | AZ77: No | BA77: Yes | BB77: No | BC77: Yes | BD77: Yes | BE77: Yes | BF77: Yes | BG77: Yes | BH77: Yes | BI77: Yes | BJ77: Yes | BK77: Yes | BL77: Yes | BM77: Yes | BN77: Yes | BO77: No | BP77: Yes | BQ77: Non-signatory | BR77: Non-signatory | BS77: Non-signatory | BU77: =SUM(BV77:BY77) -> 8400 | BV77: 8400 | CA77: Yes | CC77: Yes
A78: =LOOKUP(H78,'Letter grades'!$A$1:$B$6) -> D | B78: =RANK(H78,H:H) -> 74 | C78: Mary Gay | D78: Scanlon | E78: PA-05 | F78: =((COUNTIF($J78:$BP78,"Sponsor")+COUNTIF($J78:$BP78, "Not sponsoring (correct)"))/(COUNTIF($J78:$BP78,"Sponsor")+COUNTIF($J78:$BP78,"Not sponsoring")+COUNTIF($J78:$BP78, "Not sponsoring (correct)")+COUNTIF($J78:$BP78, "Sponsor (incorrect)"))) -> 0.5 | G78: =(COUNTIF($K78:$BP78,"No")+COUNTIF($K78:$BP78,"Yes (correct)")+(COUNTIF($K78:$BP78,"Present")*0.5))/(COUNTIF($K78:$BP78,"Yes")+COUNTIF($K78:$BP78,"No")+COUNTIF($K78:$BP78,"Yes (correct)")+COUNTIF($K78:$BP78,"No (incorrect)")+COUNTIF($K78:$BP78,"Present")) -> 0.39361702 | H78: =((F78*(1/3))+(G78*(2/3))) -> 0.42907801 | I78: J Street | J78: Not sponsoring | K78: Sponsor | L78: Sponsor | M78: Not sponsoring | N78: Not sponsoring | O78: Not sponsoring (correct) | P78: No | Q78: No | R78: Yes (correct) | S78: No | T78: Yes | U78: Yes | V78: Not on committee | W78: Not on committee | X78: No (incorrect) | Y78: Yes | Z78: No | AA78: No | AB78: No | AC78: Yes | AD78: No | AE78: No | AF78: No | AG78: No | AH78: No | AI78: No | AJ78: Yes | AK78: Yes | AL78: Yes | AM78: Yes | AN78: Yes | AO78: Yes | AP78: Yes | AQ78: Yes | AR78: No | AS78: Yes | AT78: No | AU78: Yes | AV78: Present | AW78: Yes | AX78: Yes | AY78: Yes | AZ78: No | BA78: Not voting | BB78: Not voting | BC78: No | BD78: Yes | BE78: No | BF78: Yes | BG78: Yes | BH78: Yes | BI78: Yes | BJ78: Yes | BK78: Yes | BL78: Yes | BM78: Yes | BN78: Yes | BO78: Not elected | BP78: Not elected | BQ78: Non-signatory | BR78: Non-signatory | BS78: Non-signatory | BU78: =SUM(BV78:BY78) -> 0 | CA78: Yes
A79: =LOOKUP(H79,'Letter grades'!$A$1:$B$6) -> D | B79: =RANK(H79,H:H) -> 75 | C79: Morgan | D79: McGarvey | E79: KY-03 | F79: =((COUNTIF($J79:$BP79,"Sponsor")+COUNTIF($J79:$BP79, "Not sponsoring (correct)"))/(COUNTIF($J79:$BP79,"Sponsor")+COUNTIF($J79:$BP79,"Not sponsoring")+COUNTIF($J79:$BP79, "Not sponsoring (correct)")+COUNTIF($J79:$BP79, "Sponsor (incorrect)"))) -> 0.33333333 | G79: =(COUNTIF($K79:$BP79,"No")+COUNTIF($K79:$BP79,"Yes (correct)")+(COUNTIF($K79:$BP79,"Present")*0.5))/(COUNTIF($K79:$BP79,"Yes")+COUNTIF($K79:$BP79,"No")+COUNTIF($K79:$BP79,"Yes (correct)")+COUNTIF($K79:$BP79,"No (incorrect)")+COUNTIF($K79:$BP79,"Present")) -> 0.47674419 | H79: =((F79*(1/3))+(G79*(2/3))) -> 0.42894057 | J79: Not sponsoring | K79: Not sponsoring | L79: Sponsor | M79: Not sponsoring | N79: Not sponsoring | O79: Not sponsoring (correct) | P79: No | Q79: No | R79: Yes (correct) | S79: No | T79: No | U79: No | V79: Not on committee | W79: Not on committee | X79: No (incorrect) | Y79: Yes | Z79: No | AA79: No | AB79: No | AC79: Yes | AD79: No | AE79: No | AF79: No | AG79: No | AH79: No | AI79: No | AJ79: Yes | AK79: No | AL79: Yes | AM79: Yes | AN79: Yes | AO79: Yes | AP79: Yes | AQ79: Yes | AR79: No | AS79: Yes | AT79: No | AU79: Yes | AV79: Present | AW79: Yes | AX79: Yes | AY79: Yes | AZ79: No | BA79: Yes | BB79: No | BC79: Yes | BD79: Yes | BE79: Yes | BF79: Yes | BG79: Yes | BH79: Yes | BI79: Not elected | BJ79: Not elected | BK79: Not elected | BL79: Not elected | BM79: Not elected | BN79: Not elected | BO79: Not elected | BP79: Not elected | BQ79: Non-signatory | BR79: Non-signatory | BS79: Non-signatory | BU79: =SUM(BV79:BY79) -> 90591 | BV79: 36450 | BX79: =2000 -> 2000 | BY79: 52141 | CB79: Yes | CC79: Yes
A80: =LOOKUP(H80,'Letter grades'!$A$1:$B$6) -> D | B80: =RANK(H80,H:H) -> 76 | C80: Jahana | D80: Hayes | E80: CT-05 | F80: =((COUNTIF($J80:$BP80,"Sponsor")+COUNTIF($J80:$BP80, "Not sponsoring (correct)"))/(COUNTIF($J80:$BP80,"Sponsor")+COUNTIF($J80:$BP80,"Not sponsoring")+COUNTIF($J80:$BP80, "Not sponsoring (correct)")+COUNTIF($J80:$BP80, "Sponsor (incorrect)"))) -> 0.66666667 | G80: =(COUNTIF($K80:$BP80,"No")+COUNTIF($K80:$BP80,"Yes (correct)")+(COUNTIF($K80:$BP80,"Present")*0.5))/(COUNTIF($K80:$BP80,"Yes")+COUNTIF($K80:$BP80,"No")+COUNTIF($K80:$BP80,"Yes (correct)")+COUNTIF($K80:$BP80,"No (incorrect)")+COUNTIF($K80:$BP80,"Present")) -> 0.30612245 | H80: =((F80*(1/3))+(G80*(2/3))) -> 0.42630385 | I80: J Street | J80: Sponsor | K80: Sponsor | L80: Sponsor | M80: Not sponsoring | N80: Not sponsoring | O80: Not sponsoring (correct) | P80: No | Q80: No | R80: Yes (correct) | S80: No | T80: Yes | U80: No | V80: Not on committee | W80: Not on committee | X80: No (incorrect) | Y80: Yes | Z80: No | AA80: Yes | AB80: No | AC80: Yes | AD80: Yes | AE80: No | AF80: No | AG80: No | AH80: No | AI80: Yes | AJ80: Yes | AK80: Yes | AL80: Yes | AM80: Yes | AN80: Yes | AO80: Yes | AP80: Yes | AQ80: Yes | AR80: No | AS80: Yes | AT80: No | AU80: Yes | AV80: Yes | AW80: Yes | AX80: Yes | AY80: Yes | AZ80: No | BA80: Yes | BB80: No | BC80: Yes | BD80: Yes | BE80: Yes | BF80: Yes | BG80: Yes | BH80: Yes | BI80: Yes | BJ80: Yes | BK80: Yes | BL80: Yes | BM80: Yes | BN80: Yes | BO80: Not elected | BP80: Not elected | BQ80: Non-signatory | BR80: Non-signatory | BS80: Non-signatory | BU80: =SUM(BV80:BY80) -> 22775 | BV80: 20775 | BX80: =2000 -> 2000 | CA80: Yes
A81: =LOOKUP(H81,'Letter grades'!$A$1:$B$6) -> D | B81: =RANK(H81,H:H) -> 77 | C81: Suhas | D81: Subramanyam | E81: VA-10 | F81: =((COUNTIF($J81:$BP81,"Sponsor")+COUNTIF($J81:$BP81, "Not sponsoring (correct)"))/(COUNTIF($J81:$BP81,"Sponsor")+COUNTIF($J81:$BP81,"Not sponsoring")+COUNTIF($J81:$BP81, "Not sponsoring (correct)")+COUNTIF($J81:$BP81, "Sponsor (incorrect)"))) -> 0.16666667 | G81: =(COUNTIF($K81:$BP81,"No")+COUNTIF($K81:$BP81,"Yes (correct)")+(COUNTIF($K81:$BP81,"Present")*0.5))/(COUNTIF($K81:$BP81,"Yes")+COUNTIF($K81:$BP81,"No")+COUNTIF($K81:$BP81,"Yes (correct)")+COUNTIF($K81:$BP81,"No (incorrect)")+COUNTIF($K81:$BP81,"Present")) -> 0.55555556 | H81: =((F81*(1/3))+(G81*(2/3))) -> 0.42592593 | J81: Sponsor | K81: Not sponsoring | L81: Not sponsoring | M81: Not sponsoring | N81: Not sponsoring | O81: Sponsor (incorrect) | P81: No | Q81: No | R81: No (incorrect) | S81: No | T81: No | U81: No | V81: Not on committee | W81: Not on committee | X81: No (incorrect) | Y81: Yes | Z81: Yes | AA81: Not elected | AB81: Not elected | AC81: Not elected | AD81: Not elected | AE81: Not elected | AF81: Not elected | AG81: Not elected | AH81: Not elected | AI81: Not elected | AJ81: Not elected | AK81: Not elected | AL81: Not elected | AM81: Not elected | AN81: Not elected | AO81: Not elected | AP81: Not elected | AQ81: Not elected | AR81: Not elected | AS81: Not elected | AT81: Not elected | AU81: Not elected | AV81: Not elected | AW81: Not elected | AX81: Not elected | AY81: Not elected | AZ81: Not elected | BA81: Not elected | BB81: Not elected | BC81: Not elected | BD81: Not elected | BE81: Not elected | BF81: Not elected | BG81: Not elected | BH81: Not elected | BI81: Not elected | BJ81: Not elected | BK81: Not elected | BL81: Not elected | BM81: Not elected | BN81: Not elected | BO81: Not elected | BP81: Not elected | BQ81: Non-signatory | BR81: Not elected | BS81: Not elected
A82: =LOOKUP(H82,'Letter grades'!$A$1:$B$6) -> D | B82: =RANK(H82,H:H) -> 77 | C82: Maggie | D82: Goodlander | E82: NH-02 | F82: =((COUNTIF($J82:$BP82,"Sponsor")+COUNTIF($J82:$BP82, "Not sponsoring (correct)"))/(COUNTIF($J82:$BP82,"Sponsor")+COUNTIF($J82:$BP82,"Not sponsoring")+COUNTIF($J82:$BP82, "Not sponsoring (correct)")+COUNTIF($J82:$BP82, "Sponsor (incorrect)"))) -> 0.16666667 | G82: =(COUNTIF($K82:$BP82,"No")+COUNTIF($K82:$BP82,"Yes (correct)")+(COUNTIF($K82:$BP82,"Present")*0.5))/(COUNTIF($K82:$BP82,"Yes")+COUNTIF($K82:$BP82,"No")+COUNTIF($K82:$BP82,"Yes (correct)")+COUNTIF($K82:$BP82,"No (incorrect)")+COUNTIF($K82:$BP82,"Present")) -> 0.55555556 | H82: =((F82*(1/3))+(G82*(2/3))) -> 0.42592593 | I82: AIPAC, J Street | J82: Sponsor | K82: Not sponsoring | L82: Not sponsoring | M82: Not sponsoring | N82: Not sponsoring | O82: Sponsor (incorrect) | P82: No | Q82: No | R82: Yes (correct) | S82: No | T82: Yes | U82: Yes | V82: Not on committee | W82: Not on committee | X82: No (incorrect) | Y82: Yes | Z82: No | AA82: Not elected | AB82: Not elected | AC82: Not elected | AD82: Not elected | AE82: Not elected | AF82: Not elected | AG82: Not elected | AH82: Not elected | AI82: Not elected | AJ82: Not elected | AK82: Not elected | AL82: Not elected | AM82: Not elected | AN82: Not elected | AO82: Not elected | AP82: Not elected | AQ82: Not elected | AR82: Not elected | AS82: Not elected | AT82: Not elected | AU82: Not elected | AV82: Not elected | AW82: Not elected | AX82: Not elected | AY82: Not elected | AZ82: Not elected | BA82: Not elected | BB82: Not elected | BC82: Not elected | BD82: Not elected | BE82: Not elected | BF82: Not elected | BG82: Not elected | BH82: Not elected | BI82: Not elected | BJ82: Not elected | BK82: Not elected | BL82: Not elected | BM82: Not elected | BN82: Not elected | BO82: Not elected | BP82: Not elected | BQ82: Signatory | BR82: Not elected | BS82: Not elected
A83: =LOOKUP(H83,'Letter grades'!$A$1:$B$6) -> D | B83: =RANK(H83,H:H) -> 79 | C83: Debbie | D83: Dingell | E83: MI-06 | F83: =((COUNTIF($J83:$BP83,"Sponsor")+COUNTIF($J83:$BP83, "Not sponsoring (correct)"))/(COUNTIF($J83:$BP83,"Sponsor")+COUNTIF($J83:$BP83,"Not sponsoring")+COUNTIF($J83:$BP83, "Not sponsoring (correct)")+COUNTIF($J83:$BP83, "Sponsor (incorrect)"))) -> 0.5 | G83: =(COUNTIF($K83:$BP83,"No")+COUNTIF($K83:$BP83,"Yes (correct)")+(COUNTIF($K83:$BP83,"Present")*0.5))/(COUNTIF($K83:$BP83,"Yes")+COUNTIF($K83:$BP83,"No")+COUNTIF($K83:$BP83,"Yes (correct)")+COUNTIF($K83:$BP83,"No (incorrect)")+COUNTIF($K83:$BP83,"Present")) -> 0.38043478 | H83: =((F83*(1/3))+(G83*(2/3))) -> 0.42028986 | I83: J Street | J83: Sponsor | K83: Sponsor | L83: Not sponsoring | M83: Not sponsoring | N83: Not sponsoring | O83: Not sponsoring (correct) | P83: No | Q83: Not voting | R83: Not voting | S83: No | T83: Yes | U83: Yes | V83: Not on committee | W83: Not on committee | X83: No (incorrect) | Y83: Yes | Z83: Not voting | AA83: No | AB83: No | AC83: Yes | AD83: Yes | AE83: No | AF83: No | AG83: No | AH83: No | AI83: Yes | AJ83: Not voting | AK83: No | AL83: Yes | AM83: No | AN83: Yes | AO83: Yes | AP83: Yes | AQ83: Yes | AR83: No | AS83: Yes | AT83: No | AU83: Yes | AV83: Present | AW83: Yes | AX83: Yes | AY83: Yes | AZ83: No | BA83: Yes | BB83: No | BC83: Yes | BD83: Yes | BE83: No | BF83: Yes | BG83: Yes | BH83: Yes | BI83: Yes | BJ83: Yes | BK83: Yes | BL83: Yes | BM83: Yes | BN83: No | BO83: No | BP83: Not elected | BQ83: Non-signatory | BR83: Non-signatory | BS83: Non-signatory | BU83: =SUM(BV83:BY83) -> 0 | CA83: Yes
A84: =LOOKUP(H84,'Letter grades'!$A$1:$B$6) -> D | B84: =RANK(H84,H:H) -> 80 | C84: Julie | D84: Johnson | E84: TX-32 | F84: =((COUNTIF($J84:$BP84,"Sponsor")+COUNTIF($J84:$BP84, "Not sponsoring (correct)"))/(COUNTIF($J84:$BP84,"Sponsor")+COUNTIF($J84:$BP84,"Not sponsoring")+COUNTIF($J84:$BP84, "Not sponsoring (correct)")+COUNTIF($J84:$BP84, "Sponsor (incorrect)"))) -> 0.16666667 | G84: =(COUNTIF($K84:$BP84,"No")+COUNTIF($K84:$BP84,"Yes (correct)")+(COUNTIF($K84:$BP84,"Present")*0.5))/(COUNTIF($K84:$BP84,"Yes")+COUNTIF($K84:$BP84,"No")+COUNTIF($K84:$BP84,"Yes (correct)")+COUNTIF($K84:$BP84,"No (incorrect)")+COUNTIF($K84:$BP84,"Present")) -> 0.54545455 | H84: =((F84*(1/3))+(G84*(2/3))) -> 0.41919192 | I84: AIPAC, J Street | J84: Sponsor | K84: Not sponsoring | L84: Not sponsoring | M84: Not sponsoring | N84: Not sponsoring | O84: Sponsor (incorrect) | P84: No | Q84: No | R84: Yes (correct) | S84: No | T84: Yes | U84: No | V84: No (incorrect) | W84: No (incorrect) | X84: No (incorrect) | Y84: Yes | Z84: No | AA84: Not elected | AB84: Not elected | AC84: Not elected | AD84: Not elected | AE84: Not elected | AF84: Not elected | AG84: Not elected | AH84: Not elected | AI84: Not elected | AJ84: Not elected | AK84: Not elected | AL84: Not elected | AM84: Not elected | AN84: Not elected | AO84: Not elected | AP84: Not elected | AQ84: Not elected | AR84: Not elected | AS84: Not elected | AT84: Not elected | AU84: Not elected | AV84: Not elected | AW84: Not elected | AX84: Not elected | AY84: Not elected | AZ84: Not elected | BA84: Not elected | BB84: Not elected | BC84: Not elected | BD84: Not elected | BE84: Not elected | BF84: Not elected | BG84: Not elected | BH84: Not elected | BI84: Not elected | BJ84: Not elected | BK84: Not elected | BL84: Not elected | BM84: Not elected | BN84: Not elected | BO84: Not elected | BP84: Not elected | BQ84: Signatory | BR84: Not elected | BS84: Not elected
A85: =LOOKUP(H85,'Letter grades'!$A$1:$B$6) -> D | B85: =RANK(H85,H:H) -> 81 | C85: Troy | D85: Carter | E85: LA-02 | F85: =((COUNTIF($J85:$BP85,"Sponsor")+COUNTIF($J85:$BP85, "Not sponsoring (correct)"))/(COUNTIF($J85:$BP85,"Sponsor")+COUNTIF($J85:$BP85,"Not sponsoring")+COUNTIF($J85:$BP85, "Not sponsoring (correct)")+COUNTIF($J85:$BP85, "Sponsor (incorrect)"))) -> 0.5 | G85: =(COUNTIF($K85:$BP85,"No")+COUNTIF($K85:$BP85,"Yes (correct)")+(COUNTIF($K85:$BP85,"Present")*0.5))/(COUNTIF($K85:$BP85,"Yes")+COUNTIF($K85:$BP85,"No")+COUNTIF($K85:$BP85,"Yes (correct)")+COUNTIF($K85:$BP85,"No (incorrect)")+COUNTIF($K85:$BP85,"Present")) -> 0.37234043 | H85: =((F85*(1/3))+(G85*(2/3))) -> 0.41489362 | I85: J Street | J85: Sponsor | K85: Not sponsoring | L85: Sponsor | M85: Not sponsoring | N85: Not sponsoring | O85: Not sponsoring (correct) | P85: No | Q85: No | R85: Yes (correct) | S85: No | T85: Yes | U85: Yes | V85: Not on committee | W85: Not on committee | X85: No (incorrect) | Y85: Yes | Z85: No | AA85: No | AB85: No | AC85: Yes | AD85: No | AE85: No | AF85: No | AG85: No | AH85: No | AI85: No | AJ85: Yes | AK85: Yes | AL85: Yes | AM85: Yes | AN85: Yes | AO85: Yes | AP85: Yes | AQ85: Yes | AR85: No | AS85: Yes | AT85: No | AU85: Yes | AV85: Present | AW85: Yes | AX85: Yes | AY85: Yes | AZ85: No | BA85: Yes | BB85: No | BC85: Yes | BD85: Yes | BE85: Yes | BF85: Yes | BG85: Yes | BH85: Yes | BI85: Yes | BJ85: Yes | BK85: Yes | BL85: Yes | BM85: Not elected | BN85: Not elected | BO85: Not elected | BP85: Not elected | BQ85: Non-signatory | BR85: Signatory | BS85: Signatory | BU85: =SUM(BV85:BY85) -> 30060 | BV85: 30060 | CC85: Yes
A86: =LOOKUP(H86,'Letter grades'!$A$1:$B$6) -> D | B86: =RANK(H86,H:H) -> 82 | C86: Bill | D86: Foster | E86: IL-11 | F86: =((COUNTIF($J86:$BP86,"Sponsor")+COUNTIF($J86:$BP86, "Not sponsoring (correct)"))/(COUNTIF($J86:$BP86,"Sponsor")+COUNTIF($J86:$BP86,"Not sponsoring")+COUNTIF($J86:$BP86, "Not sponsoring (correct)")+COUNTIF($J86:$BP86, "Sponsor (incorrect)"))) -> 0.5 | G86: =(COUNTIF($K86:$BP86,"No")+COUNTIF($K86:$BP86,"Yes (correct)")+(COUNTIF($K86:$BP86,"Present")*0.5))/(COUNTIF($K86:$BP86,"Yes")+COUNTIF($K86:$BP86,"No")+COUNTIF($K86:$BP86,"Yes (correct)")+COUNTIF($K86:$BP86,"No (incorrect)")+COUNTIF($K86:$BP86,"Present")) -> 0.37 | H86: =((F86*(1/3))+(G86*(2/3))) -> 0.41333333 | I86: J Street | J86: Sponsor | K86: Not sponsoring | L86: Sponsor | M86: Not sponsoring | N86: Not sponsoring | O86: Not sponsoring (correct) | P86: No | Q86: No | R86: No (incorrect) | S86: Yes | T86: Yes | U86: No | V86: Not on committee | W86: Not on committee | X86: No (incorrect) | Y86: Yes | Z86: No | AA86: No | AB86: No | AC86: Yes | AD86: No | AE86: No | AF86: No | AG86: No | AH86: No | AI86: No | AJ86: Yes | AK86: Yes | AL86: Yes | AM86: Yes | AN86: Yes | AO86: Yes | AP86: Yes | AQ86: Yes | AR86: No | AS86: Yes | AT86: No | AU86: Yes | AV86: Present | AW86: Yes | AX86: Yes | AY86: No | AZ86: No | BA86: Yes | BB86: No | BC86: Yes | BD86: Yes | BE86: Yes | BF86: Yes | BG86: Yes | BH86: Yes | BI86: Yes | BJ86: Yes | BK86: Yes | BL86: Yes | BM86: Yes | BN86: Yes | BO86: No | BP86: Not elected | BQ86: Non-signatory | BR86: Non-signatory | BS86: Non-signatory | BU86: =SUM(BV86:BY86) -> 0 | CA86: Yes
A87: =LOOKUP(H87,'Letter grades'!$A$1:$B$6) -> D | B87: =RANK(H87,H:H) -> 83 | C87: Kevin | D87: Mullin | E87: CA-15 | F87: =((COUNTIF($J87:$BP87,"Sponsor")+COUNTIF($J87:$BP87, "Not sponsoring (correct)"))/(COUNTIF($J87:$BP87,"Sponsor")+COUNTIF($J87:$BP87,"Not sponsoring")+COUNTIF($J87:$BP87, "Not sponsoring (correct)")+COUNTIF($J87:$BP87, "Sponsor (incorrect)"))) -> 0.33333333 | G87: =(COUNTIF($K87:$BP87,"No")+COUNTIF($K87:$BP87,"Yes (correct)")+(COUNTIF($K87:$BP87,"Present")*0.5))/(COUNTIF($K87:$BP87,"Yes")+COUNTIF($K87:$BP87,"No")+COUNTIF($K87:$BP87,"Yes (correct)")+COUNTIF($K87:$BP87,"No (incorrect)")+COUNTIF($K87:$BP87,"Present")) -> 0.45238095 | H87: =((F87*(1/3))+(G87*(2/3))) -> 0.41269841 | I87: DMFI, J Street | J87: Sponsor | K87: Not sponsoring | L87: Not sponsoring | M87: Not sponsoring | N87: Not sponsoring | O87: Not sponsoring (correct) | P87: No | Q87: No | R87: Yes (correct) | S87: No | T87: Yes | U87: No | V87: Not on committee | W87: Not on committee | X87: No (incorrect) | Y87: Yes | Z87: No | AA87: No | AB87: No | AC87: Yes | AD87: No | AE87: No | AF87: No | AG87: No | AH87: No | AI87: Yes | AJ87: Yes | AK87: No | AL87: Yes | AM87: Yes | AN87: Yes | AO87: Yes | AP87: Yes | AQ87: Yes | AR87: No | AS87: Yes | AT87: No | AU87: Yes | AV87: Not voting | AW87: Yes | AX87: Yes | AY87: Yes | AZ87: No | BA87: Yes | BB87: No | BC87: Yes | BD87: Yes | BE87: No | BF87: Yes | BG87: Yes | BH87: Yes | BI87: Not elected | BJ87: Not elected | BK87: Not elected | BL87: Not elected | BM87: Not elected | BN87: Not elected | BO87: Not elected | BP87: Not elected | BQ87: Non-signatory | BR87: Non-signatory | BS87: Non-signatory | BU87: =SUM(BV87:BY87) -> 703663 | BV87: 87895 | BW87: 588768 | BX87: =2000 -> 2000 | BY87: 25000 | CB87: Yes | CC87: Yes
A88: =LOOKUP(H88,'Letter grades'!$A$1:$B$6) -> D | B88: =RANK(H88,H:H) -> 84 | C88: Cleo | D88: Fields | E88: LA-06 | F88: =((COUNTIF($J88:$BP88,"Sponsor")+COUNTIF($J88:$BP88, "Not sponsoring (correct)"))/(COUNTIF($J88:$BP88,"Sponsor")+COUNTIF($J88:$BP88,"Not sponsoring")+COUNTIF($J88:$BP88, "Not sponsoring (correct)")+COUNTIF($J88:$BP88, "Sponsor (incorrect)"))) -> 0.33333333 | G88: =(COUNTIF($K88:$BP88,"No")+COUNTIF($K88:$BP88,"Yes (correct)")+(COUNTIF($K88:$BP88,"Present")*0.5))/(COUNTIF($K88:$BP88,"Yes")+COUNTIF($K88:$BP88,"No")+COUNTIF($K88:$BP88,"Yes (correct)")+COUNTIF($K88:$BP88,"No (incorrect)")+COUNTIF($K88:$BP88,"Present")) -> 0.44444444 | H88: =((F88*(1/3))+(G88*(2/3))) -> 0.40740741 | J88: Sponsor | K88: Not sponsoring | L88: Not sponsoring | M88: Not sponsoring | N88: Not sponsoring | O88: Not sponsoring (correct) | P88: No | Q88: No | R88: No (incorrect) | S88: No | T88: Yes | U88: Yes | V88: Not on committee | W88: Not on committee | X88: No (incorrect) | Y88: Yes | Z88: No | AA88: Not elected | AB88: Not elected | AC88: Not elected | AD88: Not elected | AE88: Not elected | AF88: Not elected | AG88: Not elected | AH88: Not elected | AI88: Not elected | AJ88: Not elected | AK88: Not elected | AL88: Not elected | AM88: Not elected | AN88: Not elected | AO88: Not elected | AP88: Not elected | AQ88: Not elected | AR88: Not elected | AS88: Not elected | AT88: Not elected | AU88: Not elected | AV88: Not elected | AW88: Not elected | AX88: Not elected | AY88: Not elected | AZ88: Not elected | BA88: Not elected | BB88: Not elected | BC88: Not elected | BD88: Not elected | BE88: Not elected | BF88: Not elected | BG88: Not elected | BH88: Not elected | BI88: Not elected | BJ88: Not elected | BK88: Not elected | BL88: Not elected | BM88: Not elected | BN88: Not elected | BO88: Not elected | BP88: Not elected | BQ88: Non-signatory | BR88: Not elected | BS88: Not elected
A89: =LOOKUP(H89,'Letter grades'!$A$1:$B$6) -> D | B89: =RANK(H89,H:H) -> 84 | C89: Herb | D89: Conaway | E89: NJ-03 | F89: =((COUNTIF($J89:$BP89,"Sponsor")+COUNTIF($J89:$BP89, "Not sponsoring (correct)"))/(COUNTIF($J89:$BP89,"Sponsor")+COUNTIF($J89:$BP89,"Not sponsoring")+COUNTIF($J89:$BP89, "Not sponsoring (correct)")+COUNTIF($J89:$BP89, "Sponsor (incorrect)"))) -> 0.33333333 | G89: =(COUNTIF($K89:$BP89,"No")+COUNTIF($K89:$BP89,"Yes (correct)")+(COUNTIF($K89:$BP89,"Present")*0.5))/(COUNTIF($K89:$BP89,"Yes")+COUNTIF($K89:$BP89,"No")+COUNTIF($K89:$BP89,"Yes (correct)")+COUNTIF($K89:$BP89,"No (incorrect)")+COUNTIF($K89:$BP89,"Present")) -> 0.44444444 | H89: =((F89*(1/3))+(G89*(2/3))) -> 0.40740741 | J89: Sponsor | K89: Not sponsoring | L89: Not sponsoring | M89: Not sponsoring | N89: Not sponsoring | O89: Not sponsoring (correct) | P89: No | Q89: No | R89: No (incorrect) | S89: No | T89: Yes | U89: Yes | V89: Not on committee | W89: Not on committee | X89: No (incorrect) | Y89: Yes | Z89: No | AA89: Not elected | AB89: Not elected | AC89: Not elected | AD89: Not elected | AE89: Not elected | AF89: Not elected | AG89: Not elected | AH89: Not elected | AI89: Not elected | AJ89: Not elected | AK89: Not elected | AL89: Not elected | AM89: Not elected | AN89: Not elected | AO89: Not elected | AP89: Not elected | AQ89: Not elected | AR89: Not elected | AS89: Not elected | AT89: Not elected | AU89: Not elected | AV89: Not elected | AW89: Not elected | AX89: Not elected | AY89: Not elected | AZ89: Not elected | BA89: Not elected | BB89: Not elected | BC89: Not elected | BD89: Not elected | BE89: Not elected | BF89: Not elected | BG89: Not elected | BH89: Not elected | BI89: Not elected | BJ89: Not elected | BK89: Not elected | BL89: Not elected | BM89: Not elected | BN89: Not elected | BO89: Not elected | BP89: Not elected | BQ89: Signatory | BR89: Not elected | BS89: Not elected
A90: =LOOKUP(H90,'Letter grades'!$A$1:$B$6) -> D | B90: =RANK(H90,H:H) -> 84 | C90: Nellie | D90: Pou | E90: NJ-09 | F90: =((COUNTIF($J90:$BP90,"Sponsor")+COUNTIF($J90:$BP90, "Not sponsoring (correct)"))/(COUNTIF($J90:$BP90,"Sponsor")+COUNTIF($J90:$BP90,"Not sponsoring")+COUNTIF($J90:$BP90, "Not sponsoring (correct)")+COUNTIF($J90:$BP90, "Sponsor (incorrect)"))) -> 0.33333333 | G90: =(COUNTIF($K90:$BP90,"No")+COUNTIF($K90:$BP90,"Yes (correct)")+(COUNTIF($K90:$BP90,"Present")*0.5))/(COUNTIF($K90:$BP90,"Yes")+COUNTIF($K90:$BP90,"No")+COUNTIF($K90:$BP90,"Yes (correct)")+COUNTIF($K90:$BP90,"No (incorrect)")+COUNTIF($K90:$BP90,"Present")) -> 0.44444444 | H90: =((F90*(1/3))+(G90*(2/3))) -> 0.40740741 | J90: Not sponsoring | K90: Not sponsoring | L90: Sponsor | M90: Not sponsoring | N90: Not sponsoring | O90: Not sponsoring (correct) | P90: No | Q90: No | R90: No (incorrect) | S90: No | T90: Yes | U90: Yes | V90: Not on committee | W90: Not on committee | X90: No (incorrect) | Y90: Yes | Z90: No | AA90: Not elected | AB90: Not elected | AC90: Not elected | AD90: Not elected | AE90: Not elected | AF90: Not elected | AG90: Not elected | AH90: Not elected | AI90: Not elected | AJ90: Not elected | AK90: Not elected | AL90: Not elected | AM90: Not elected | AN90: Not elected | AO90: Not elected | AP90: Not elected | AQ90: Not elected | AR90: Not elected | AS90: Not elected | AT90: Not elected | AU90: Not elected | AV90: Not elected | AW90: Not elected | AX90: Not elected | AY90: Not elected | AZ90: Not elected | BA90: Not elected | BB90: Not elected | BC90: Not elected | BD90: Not elected | BE90: Not elected | BF90: Not elected | BG90: Not elected | BH90: Not elected | BI90: Not elected | BJ90: Not elected | BK90: Not elected | BL90: Not elected | BM90: Not elected | BN90: Not elected | BO90: Not elected | BP90: Not elected | BQ90: Non-signatory | BR90: Not elected | BS90: Not elected
A91: =LOOKUP(H91,'Letter grades'!$A$1:$B$6) -> D | B91: =RANK(H91,H:H) -> 87 | C91: Deborah | D91: Ross | E91: NC-02 | F91: =((COUNTIF($J91:$BP91,"Sponsor")+COUNTIF($J91:$BP91, "Not sponsoring (correct)"))/(COUNTIF($J91:$BP91,"Sponsor")+COUNTIF($J91:$BP91,"Not sponsoring")+COUNTIF($J91:$BP91, "Not sponsoring (correct)")+COUNTIF($J91:$BP91, "Sponsor (incorrect)"))) -> 0.5 | G91: =(COUNTIF($K91:$BP91,"No")+COUNTIF($K91:$BP91,"Yes (correct)")+(COUNTIF($K91:$BP91,"Present")*0.5))/(COUNTIF($K91:$BP91,"Yes")+COUNTIF($K91:$BP91,"No")+COUNTIF($K91:$BP91,"Yes (correct)")+COUNTIF($K91:$BP91,"No (incorrect)")+COUNTIF($K91:$BP91,"Present")) -> 0.35869565 | H91: =((F91*(1/3))+(G91*(2/3))) -> 0.4057971 | J91: Sponsor | K91: Sponsor | L91: Not sponsoring | M91: Not sponsoring | N91: Not sponsoring | O91: Not sponsoring (correct) | P91: No | Q91: No | R91: Yes (correct) | S91: No | T91: Yes | U91: Yes | V91: Not on committee | W91: Not on committee | X91: No (incorrect) | Y91: Yes | Z91: No | AA91: No | AB91: No | AC91: Yes | AD91: No | AE91: No | AF91: No | AG91: No | AH91: No | AI91: Yes | AJ91: Yes | AK91: Yes | AL91: Yes | AM91: Yes | AN91: Yes | AO91: Yes | AP91: Yes | AQ91: Yes | AR91: No | AS91: Yes | AT91: No | AU91: Yes | AV91: Present | AW91: Yes | AX91: Yes | AY91: Yes | AZ91: No | BA91: Yes | BB91: No | BC91: Yes | BD91: Yes | BE91: Yes | BF91: Yes | BG91: Yes | BH91: Not voting | BI91: Yes | BJ91: Yes | BK91: Yes | BL91: Yes | BM91: Not elected | BN91: Not elected | BO91: Not elected | BP91: Not elected | BQ91: Non-signatory | BR91: Non-signatory | BS91: Signatory | BU91: =SUM(BV91:BY91) -> 30750 | BV91: 28750 | BX91: =2000 -> 2000 | CB91: Yes | CC91: Yes
A92: =LOOKUP(H92,'Letter grades'!$A$1:$B$6) -> F | B92: =RANK(H92,H:H) -> 88 | C92: Jimmy | D92: Gomez | E92: CA-34 | F92: =((COUNTIF($J92:$BP92,"Sponsor")+COUNTIF($J92:$BP92, "Not sponsoring (correct)"))/(COUNTIF($J92:$BP92,"Sponsor")+COUNTIF($J92:$BP92,"Not sponsoring")+COUNTIF($J92:$BP92, "Not sponsoring (correct)")+COUNTIF($J92:$BP92, "Sponsor (incorrect)"))) -> 0.33333333 | G92: =(COUNTIF($K92:$BP92,"No")+COUNTIF($K92:$BP92,"Yes (correct)")+(COUNTIF($K92:$BP92,"Present")*0.5))/(COUNTIF($K92:$BP92,"Yes")+COUNTIF($K92:$BP92,"No")+COUNTIF($K92:$BP92,"Yes (correct)")+COUNTIF($K92:$BP92,"No (incorrect)")+COUNTIF($K92:$BP92,"Present")) -> 0.42045455 | H92: =((F92*(1/3))+(G92*(2/3))) -> 0.39141414 | I92: AIPAC, DMFI | J92: Sponsor | K92: Not sponsoring | L92: Not sponsoring | M92: Not sponsoring | N92: Not sponsoring | O92: Not sponsoring (correct) | P92: No | Q92: No | R92: No (incorrect) | S92: No | T92: Yes | U92: Yes | V92: Not on committee | W92: Not on committee | X92: No (incorrect) | Y92: Not voting | Z92: No | AA92: No | AB92: No | AC92: Yes | AD92: Not voting | AE92: No | AF92: No | AG92: No | AH92: No | AI92: Not voting | AJ92: Yes | AK92: Yes | AL92: Yes | AM92: Not voting | AN92: Yes | AO92: Yes | AP92: No | AQ92: Yes | AR92: No | AS92: Yes | AT92: Present | AU92: No | AV92: Not voting | AW92: Yes | AX92: Yes | AY92: Yes | AZ92: No | BA92: Yes | BB92: No | BC92: Yes | BD92: Yes | BE92: No | BF92: Yes | BG92: Yes | BH92: Yes | BI92: No | BJ92: No | BK92: Yes | BL92: Yes | BM92: Yes | BN92: Yes | BO92: Not elected | BP92: Not elected | BQ92: Non-signatory | BR92: Non-signatory | BS92: Non-signatory | BU92: =SUM(BV92:BY92) -> 41070 | BV92: 41070 | CC92: Yes
A93: =LOOKUP(H93,'Letter grades'!$A$1:$B$6) -> F | B93: =RANK(H93,H:H) -> 89 | C93: Dwight | D93: Evans | E93: PA-03 | F93: =((COUNTIF($J93:$BP93,"Sponsor")+COUNTIF($J93:$BP93, "Not sponsoring (correct)"))/(COUNTIF($J93:$BP93,"Sponsor")+COUNTIF($J93:$BP93,"Not sponsoring")+COUNTIF($J93:$BP93, "Not sponsoring (correct)")+COUNTIF($J93:$BP93, "Sponsor (incorrect)"))) -> 0.5 | G93: =(COUNTIF($K93:$BP93,"No")+COUNTIF($K93:$BP93,"Yes (correct)")+(COUNTIF($K93:$BP93,"Present")*0.5))/(COUNTIF($K93:$BP93,"Yes")+COUNTIF($K93:$BP93,"No")+COUNTIF($K93:$BP93,"Yes (correct)")+COUNTIF($K93:$BP93,"No (incorrect)")+COUNTIF($K93:$BP93,"Present")) -> 0.33333333 | H93: =((F93*(1/3))+(G93*(2/3))) -> 0.38888889 | I93: J Street | J93: Sponsor | K93: Sponsor | L93: Not sponsoring | M93: Not sponsoring | N93: Not sponsoring | O93: Not sponsoring (correct) | P93: No | Q93: No | R93: Yes (correct) | S93: No | T93: Yes | U93: No | V93: Not on committee | W93: Not on committee | X93: No (incorrect) | Y93: Yes | Z93: Not voting | AA93: Not voting | AB93: Not voting | AC93: Not voting | AD93: Not voting | AE93: Not voting | AF93: Not voting | AG93: Not voting | AH93: Not voting | AI93: No | AJ93: Yes | AK93: Yes | AL93: Yes | AM93: Yes | AN93: Yes | AO93: Yes | AP93: Yes | AQ93: Yes | AR93: No | AS93: Yes | AT93: No | AU93: No | AV93: Present | AW93: Yes | AX93: Not voting | AY93: Yes | AZ93: No | BA93: Yes | BB93: No | BC93: Not voting | BD93: Yes | BE93: No | BF93: Yes | BG93: Yes | BH93: Yes | BI93: Yes | BJ93: Yes | BK93: Yes | BL93: Yes | BM93: Yes | BN93: Yes | BO93: Present | BP93: Not elected
A94: =LOOKUP(H94,'Letter grades'!$A$1:$B$6) -> F | B94: =RANK(H94,H:H) -> 89 | C94: James | D94: Walkinshaw | E94: VA-11 | F94: =((COUNTIF($J94:$BP94,"Sponsor")+COUNTIF($J94:$BP94, "Not sponsoring (correct)"))/(COUNTIF($J94:$BP94,"Sponsor")+COUNTIF($J94:$BP94,"Not sponsoring")+COUNTIF($J94:$BP94, "Not sponsoring (correct)")+COUNTIF($J94:$BP94, "Sponsor (incorrect)"))) -> 0.16666667 | G94: =(COUNTIF($K94:$BP94,"No")+COUNTIF($K94:$BP94,"Yes (correct)")+(COUNTIF($K94:$BP94,"Present")*0.5))/(COUNTIF($K94:$BP94,"Yes")+COUNTIF($K94:$BP94,"No")+COUNTIF($K94:$BP94,"Yes (correct)")+COUNTIF($K94:$BP94,"No (incorrect)")+COUNTIF($K94:$BP94,"Present")) -> 0.5 | H94: =((F94*(1/3))+(G94*(2/3))) -> 0.38888889 | I94: J Street | J94: Sponsor | K94: Not sponsoring | L94: Not sponsoring | M94: Not sponsoring | N94: Not sponsoring | O94: Sponsor (incorrect) | P94: No | Q94: No | R94: No (incorrect) | S94: No | T94: Yes | U94: Yes | V94: Not on committee | W94: Not on committee | X94: Not elected | Y94: Not elected | Z94: Not elected | AA94: Not elected | AB94: Not elected | AC94: Not elected | AD94: Not elected | AE94: Not elected | AF94: Not elected | AG94: Not elected | AH94: Not elected | AI94: Not elected | AJ94: Not elected | AK94: Not elected | AL94: Not elected | AM94: Not elected | AN94: Not elected | AO94: Not elected | AP94: Not elected | AQ94: Not elected | AR94: Not elected | AS94: Not elected | AT94: Not elected | AU94: Not elected | AV94: Not elected | AW94: Not elected | AX94: Not elected | AY94: Not elected | AZ94: Not elected | BA94: Not elected | BB94: Not elected | BC94: Not elected | BD94: Not elected | BE94: Not elected | BF94: Not elected | BG94: Not elected | BH94: Not elected | BI94: Not elected | BJ94: Not elected | BK94: Not elected | BL94: Not elected | BM94: Not elected | BN94: Not elected | BO94: Not elected | BP94: Not elected
A95: =LOOKUP(H95,'Letter grades'!$A$1:$B$6) -> F | B95: =RANK(H95,H:H) -> 91 | C95: Sydney | D95: Kamlager-Dove | E95: CA-37 | F95: =((COUNTIF($J95:$BP95,"Sponsor")+COUNTIF($J95:$BP95, "Not sponsoring (correct)"))/(COUNTIF($J95:$BP95,"Sponsor")+COUNTIF($J95:$BP95,"Not sponsoring")+COUNTIF($J95:$BP95, "Not sponsoring (correct)")+COUNTIF($J95:$BP95, "Sponsor (incorrect)"))) -> 0.16666667 | G95: =(COUNTIF($K95:$BP95,"No")+COUNTIF($K95:$BP95,"Yes (correct)")+(COUNTIF($K95:$BP95,"Present")*0.5))/(COUNTIF($K95:$BP95,"Yes")+COUNTIF($K95:$BP95,"No")+COUNTIF($K95:$BP95,"Yes (correct)")+COUNTIF($K95:$BP95,"No (incorrect)")+COUNTIF($K95:$BP95,"Present")) -> 0.48809524 | H95: =((F95*(1/3))+(G95*(2/3))) -> 0.38095238 | I95: J Street | J95: Not sponsoring | K95: Not sponsoring | L95: Sponsor | M95: Not sponsoring | N95: Not sponsoring | O95: Sponsor (incorrect) | P95: No | Q95: No | R95: Yes (correct) | S95: No | T95: No | U95: No | V95: No (incorrect) | W95: No (incorrect) | X95: No (incorrect) | Y95: Yes | Z95: Not voting | AA95: No | AB95: No | AC95: Yes | AD95: Not voting | AE95: No | AF95: No | AG95: No | AH95: No | AI95: Yes | AJ95: Yes | AK95: No | AL95: Yes | AM95: No | AN95: Yes | AO95: Not voting | AP95: Yes | AQ95: Yes | AR95: No | AS95: Yes | AT95: No | AU95: Yes | AV95: Present | AW95: Yes | AX95: Yes | AY95: No | AZ95: No | BA95: Yes | BB95: No | BC95: No | BD95: Yes | BE95: Yes | BF95: Yes | BG95: Yes | BH95: Yes | BI95: Not elected | BJ95: Not elected | BK95: Not elected | BL95: Not elected | BM95: Not elected | BN95: Not elected | BO95: Not elected | BP95: Not elected | BQ95: Non-signatory | BR95: Non-signatory | BS95: Non-signatory | BU95: =SUM(BV95:BY95) -> 238783 | BV95: 5500 | BX95: =2000 -> 2000 | BY95: 231283 | CA95: Yes | CB95: Yes
A96: =LOOKUP(H96,'Letter grades'!$A$1:$B$6) -> F | B96: =RANK(H96,H:H) -> 92 | C96: Steve | D96: Cohen | E96: TN-09 | F96: =((COUNTIF($J96:$BP96,"Sponsor")+COUNTIF($J96:$BP96, "Not sponsoring (correct)"))/(COUNTIF($J96:$BP96,"Sponsor")+COUNTIF($J96:$BP96,"Not sponsoring")+COUNTIF($J96:$BP96, "Not sponsoring (correct)")+COUNTIF($J96:$BP96, "Sponsor (incorrect)"))) -> 0.5 | G96: =(COUNTIF($K96:$BP96,"No")+COUNTIF($K96:$BP96,"Yes (correct)")+(COUNTIF($K96:$BP96,"Present")*0.5))/(COUNTIF($K96:$BP96,"Yes")+COUNTIF($K96:$BP96,"No")+COUNTIF($K96:$BP96,"Yes (correct)")+COUNTIF($K96:$BP96,"No (incorrect)")+COUNTIF($K96:$BP96,"Present")) -> 0.31372549 | H96: =((F96*(1/3))+(G96*(2/3))) -> 0.37581699 | I96: J Street, DMFI | J96: Sponsor | K96: Sponsor | L96: Not sponsoring | M96: Not sponsoring | N96: Not sponsoring | O96: Not sponsoring (correct) | P96: No | Q96: No | R96: No (incorrect) | S96: No | T96: No | U96: No | V96: Not on committee | W96: Not on committee | X96: No (incorrect) | Y96: Yes | Z96: No | AA96: No | AB96: No | AC96: Yes | AD96: No | AE96: No | AF96: Yes | AG96: No | AH96: No | AI96: Yes | AJ96: Yes | AK96: Yes | AL96: Yes | AM96: Yes | AN96: Yes | AO96: Yes | AP96: Yes | AQ96: Yes | AR96: No | AS96: Yes | AT96: Yes | AU96: Yes | AV96: Yes | AW96: Yes | AX96: Yes | AY96: Yes | AZ96: Yes | BA96: Yes | BB96: No | BC96: Yes | BD96: Yes | BE96: Yes | BF96: Yes | BG96: Yes | BH96: Yes | BI96: No | BJ96: Yes | BK96: Yes | BL96: Yes | BM96: Yes | BN96: Yes | BO96: No | BP96: Yes | BQ96: Non-signatory | BR96: Signatory | BS96: Non-signatory | BU96: =SUM(BV96:BY96) -> 0 | CA96: Yes
